Workbook

Sheet 00_README
A1: 三區制度框架 R4.5.3 (純分數版) | 18項指標單一加權合成分 = 唯一判區 | 事件鎖存已移除
A3: 版本 | B3: 2026R4.5.3 | 修訂日: 2026-07-11 | 依用戶指示: ①移除事件覆蓋鎖存(判區=單一純分數); ②新增T4(NDX 5日/10日均線動能+衝擊)與T5(最熱板塊ETF動能, 現用SOXX); ③重新測試權重(WA/WB/WC三組, 採用WB, 紀錄於01表)。
A4: 6/4問題的誠實答案 | B4: 收盤價數據裡6/4只是溫和下跌日(NDX -0.53%, VIX下跌, 廣度上升, 信用持平, SOXX收盤僅-2.10%)——任何純收盤引擎都看不到。真正可量化的6/4訊號是SOXX開盤跳空-4.56%(587.64 vs 前收615.68, AVGO指引證偽後的板塊缺口)。R4.5.3把它編入T5的HARD衝擊條款(跳空≤-3%), 令6/4單憑合成分=66.2跌入UNCERTAIN——用真實板塊數據, 非人手旗標。
A5: T5數據覆蓋 | B5: 真實SOXX開盤/收盤 2026/4/29-7/10共50個交易日(stockanalysis.com, S&P Global來源, 抓取於2026-07-11, 淡紫底標示)。更早日期AY/AZ為藍格待回填; 空白日T5權重(26)自動移出分母, 不扭曲歷史判區。回填十年SOXX數據後, T5立即全期參與。
A6: 純分數的代價(如實揭露) | B6: 移除鎖存後, 判區隨分數即日擺動: 2026/6/4-7/10為 6 EASY / 18 UNCERTAIN / 1 HARD——6個EASY島全部落在SOXX單日+4%~+8%的暴力反彈日(6/8,6/17,6/18,6/22,6/24,6/25)。這是高敏感引擎的誠實輸出: 六月市場本身就在±5-10%劇烈擺動。若需要「一旦變速、維持警戒」的滯後行為, 那正是被移除的鎖存層的功能, 兩者不可兼得。
A7: 校準狀態(公式活算於05表) | B7: 窗口① 2026/4/4-5/14: 93.1% EASY (27/29; 4/6-4/7修復期) ✓ | 窗口② 6/3=EASY(100)→6/4=UNCERTAIN(66.2)單憑分數 ✓ | 窗口③ 2025/5/1-10/31: 93.8% EASY(較R4.5.1的82.8%更高: 鎖存移除釋放了十月分數滿分日) ✓ | 2017年EASY 245/251, 2022年HARD 216/251。
A8: 工作表 | B8: 00_README | 01_指標庫(18項) | 02A_每日分段(55欄) | 05_統計摘要 | 06_監察面板 | 07_L1政策步階
A9: 顏色 | B9: 綠=EASY | 黃=UNCERTAIN | 紅=HARD | 藍字=可輸入 | 淡紫底=審核修正格 | 綠字=跨表公式

Sheet 01_指標庫
A1: 量化指標庫 R4.5.3: 18項指標純分數引擎 | 判區=合成分(02A之AX): ≥70 EASY / 40-70 UNCERTAIN / ≤40 HARD | 無事件覆蓋層
A3: ID | B3: 類別 | C3: 指標名稱 | D3: EASY區 | E3: UNCERTAIN區 | F3: HARD區 | G3: 重要性 | H3: 權重% | I3: 關連性 / 領先-滯後描述 | J3: 可持續監察來源 | K3: 頻率
A4: T1 | B4: 技術/趨勢 | C4: NDX vs 40週均線 | D4: 收巿>40週線且上斜 | E4: 40週線±2%拉鋸 / 單週失守未連續 | F4: 連續2週收於線下 或 均線下斜 | G4: ★★★★★ | H4: 8 | I4: 同步至輕微滯後。區分制度最穩健單一規則; R2以「連續2週」過濾2019/5、2024/8式單週假破。 | J4: 自家週線圖 | K4: 週
A5: T2 | B5: 技術/趨勢 | C5: 10週/40週均線交叉 | D5: 金叉且乖離擴大 | E5: 跌破10週線 / 10週線走平 | F5: 死叉 | G5: ★★★★ | H5: 2 | I5: 滯後確認。死叉鎖定2022全年; 對V型底滯後6-10週, 急V條款由T3+B1代償。 | J5: 自家週線圖 | K5: 週
A6: T3 | B6: 技術/趨勢 | C6: 距52週高位回撤 | D6: >-6% | E6: -6% ~ -15% | F6: ≤-15% | G6: ★★★★★ | H6: 8 | I6: 同步; R2敏感度核心。-6%線十年觸發約20次, 全部對應真實警戒事件; -15%線僅真熊觸發, 零假警報。 | J6: 指數行情 | K6: 週
A7: B1 | B7: 廣度 | C7: 成份股>200日線比例 | D7: >60%且回升 | E7: 40-60% 或 自高位急降 | F7: <40%且下行 | G7: ★★★★★ | H7: 8 | I7: 領先1-4週。廣度先於指數: 2021年中已崩=2022最早預警; >90%推力=新EASY最強確認。 | J7: Barchart $NDXA200R / StockCharts | K7: 週
A8: B2 | B8: 廣度 | C8: 淨新高-新低(10日) | D8: 持續為正 | E8: 正負反覆 / 淨新低放大 | F8: 淨新低持續擴張 | G8: ★★★★ | H8: 4 | I8: 領先1-3週。與Market Breadth Dashboard同源; 熊巿反彈證偽關鍵。 | J8: Stockbee Market Monitor | K8: 日/週
A9: B3 | B9: 廣度 | C9: A/D線對指數背離 | D9: 同創新高 | E9: 溫和背離(1-2月) | F9: 持續多月背離+指數新高 | G9: ★★★ | H9: 2 | I9: 領先數週至數月。2021/11、2024/7頂前均現; 輔助用。 | J9: StockCharts | K9: 週
A10: L1 | B10: 流動性/政策 | C10: Fed政策方向+巿場加息/減息定價 | D10: 減息或寬鬆指引 | E10: 暫停+加息定價20-50% / 移除寬鬆傾向 | F10: 加息定價>50% 或 實際加息 | G10: ★★★★★ | H10: 5 | I10: 領先1-3個月, 制度級。2019/2023/2024轉向開EASY; 2018/2022緊縮製造HARD。2026/6/17移除寬鬆傾向+9月加息定價逾六成=十年內第三次制度級轉鷹。 | J10: CME FedWatch / FOMC | K10: 日/會期
A11: L2 | B11: 流動性/政策 | C11: 淨流動性(B/S−TGA−RRP) | D11: 按週回升 | E11: 走平 | F11: 收縮且加速 | G11: ★★★★ | H11: 4 | I11: 領先2-6週。2022後與NDX高相關; QRA/RRP釋放為2023-24隱形推手。 | J11: FRED: WALCL−WTREGEN−RRPONTSYD | K11: 週
A12: L3 | B12: 流動性/政策 | C12: M2同比 | D12: 回升且>4% | E12: 0-4%放緩 | F12: 負增長 | G12: ★★★ | H12: 2 | I12: 長領先3-12個月, 只作背景。 | J12: FRED: M2SL | K12: 月
A13: L4 | B13: 流動性/政策 | C13: 10Y-3M曲線 | D13: 正斜且趨陡 | E13: 走平/初倒掛 | F13: 深倒掛後快速熊陡 | G13: ★★★ | H13: 2 | I13: 長領先6-18個月(衰退); 對週度判區偏慢, 與C1並用。 | J13: FRED: T10Y3M | K13: 週
A14: C1 | B14: 信用 | C14: HY OAS | D14: <350bp且收窄 | E14: 350-450bp 或 4週急闊>+50bp | F14: >450bp且走闊 | G14: ★★★★★ | H14: 8 | I14: 同步至領先1-2週。股巿測謊機: 股跌而利差不闊=大概率震倉(UNCERTAIN)而非制度轉變; 2025/4峰值461bp即HARD確認。 | J14: FRED: BAMLH0A0HYM2 | K14: 日
A15: C2 | B15: 信用 | C15: SLOOS信貸標準 | D15: 放鬆 | E15: 溫和收緊 | F15: 大幅淨收緊 | G15: ★★ | H15: 2 | I15: 領先1-2季, 背景確認。 | J15: Fed SLOOS | K15: 季
... A19: S2 | B19: 情緒/投機 | C19: 投機活躍度(BTC距高回撤/IPO/低價股成交) | D19: BTC距高>-20%, 溫和擴張 | E19: BTC -20~-40% / 狂熱後急凍 | F19: BTC≤-40% / 冰封 | G19: ★★ | H19: 1 | I19: 雙向領先。投機性流動性是最快退潮的一層; BTC自2025/10記錄跌逾五成=本輪最早的HARD級單項訊號。 | J19: 行情 / FINRA | K19: 日/月
A20: T4 | B20: 技術/趨勢 | C20: NDX 5日/10日均線動能+衝擊 | D20: 乖離≥+1% 且 單日>-2% | E20: 乖離0~+1% 或 單日≤-2% | F20: 乖離<-0.3% 或 單日≤-3% | G20: ★★★★ | H20: 6 | I20: 快層動能: 5/10交叉對頂部同步至領先數日; 單日-3%衝擊條款把原事件層規則收編為指標本身。 | J20: 自NDX收巿序列公式衍生(BA欄) | K20: 日
A21: T5 | B21: 板塊動能 | C21: 最熱板塊ETF動能(現用SOXX半導體) | D21: 乖離≥+0.5% 且 無衝擊 | E21: 單日≤-2% 或 乖離<+0.5% | F21: 開盤跳空≤-3% 或 單日≤-4.5% 或 乖離<-1% | G21: ★★★★★ | H21: 26 | I21: 本週期領導板塊=AI半導體。領導板塊先於指數變盤: 6/4指數僅-0.53%而SOXX開盤跳空-4.56%——訊號載體。權重26=經實測能令6/4單憑分數跌入UNCERTAIN且不毀十年校準的最小級別。 | J21: stockanalysis.com (S&P Global) 真實數據 2026/4/29-7/10; 更早由用戶回填AY/AZ藍格 | K21: 日
C22: 權重合計 (18項=100) | H22: =SUM(H4:H21) -> 68
A24: R4.5.3 權重測試紀錄 (用戶指示「重新調整weighting」之依據)
A25: WA: T5=24,T4=8 | C25: 6/4=68.8 UNC ✓ | 窗①93.1% 窗③93.8% | 2017 EASY 217
A26: WB: T5=26,T4=6 (採用) | C26: 6/4=66.2 UNC ✓(邊際最穩) | 窗①93.1% 窗③93.8% | 2017 EASY 245 | 2022 HARD 216
A27: WC: T5=22 | C27: 6/4=71.8 → 仍EASY ✗ 否決 (T5權重不足以承載板塊訊號)
A29: 採用權重(18項合計100): T1=8 T2=2 T3=8 B1=8 B2=4 B3=2 L1=5 L2=4 L3=2 L4=2 C1=8 C2=2 V1=6 V2=4 S1=2 S2=1 T4=6 T5=26。T5空白日(2026/4/29前)其權重自動移出分母, 歷史判區由其餘指標承擔。

Sheet 02A_每日分段
A1: R4.5.3 每日判區(純分數版): 18項指標加權合成分(動態分母) = 唯一判區依據 | 事件鎖存已依用戶指示移除 | 新增T4(NDX 5/10動能)+T5(最熱板塊SOXX動能, 真實數據)
A2: A-K=數據層; L-P/AL-AV/BB-BC=子分; S/T=日變%(資訊); AA-AK=輸入; AY/AZ=SOXX開盤/收盤[真實50日+藍格回填]; BA=T4輸入; AW=有效權重和; AX=合成分; Y=最終ZONE=IF(AX≥70,EASY,IF(AX>40,UNCERTAIN,HARD)) — 無任何覆蓋層。
A4: 交易日# | B4: 日期 | C4: 年份 | D4: 週內 | E4: NDX收盤 | F4: T1:距200D% | G4: T3:距52週高% | H4: B1:廣度%代理 | I4: C1:HYOAS(bp) | J4: C1來源 | K4: V1:VIX | L4: T1子分(式) | M4: T3子分(式) | N4: B1子分(式) | O4: C1子分(式) | P4: V1子分(式) | S4: NDX日變% | T4: VIX日變% | Y4: 最終ZONE | AA4: T2輸入:50/200乖離% | AB4: L1輸入:政策碼(07表) | AC4: L2輸入:淨流動性週變%[藍] | AD4: L3輸入:M2同比%[藍] | AE4: L4輸入:10Y-3M bp[藍] | AF4: B2輸入:淨新高低10日[藍] | AG4: B3輸入:A/D碼[藍] | AH4: C2輸入:SLOOS%[藍] | AI4: V2輸入:VIX/VIX3M[藍] | AJ4: S1輸入:NAAIM[藍] | AK4: S2輸入:BTC距高%[藍] | AL4: T2子分 | AM4: L1子分 | AN4: L2子分 | AO4: L3子分 | AP4: L4子分 | AQ4: B2子分 | AR4: B3子分 | AS4: C2子分 | AT4: V2子分 | AU4: S1子分 | AV4: S2子分 | AW4: 有效權重和(式) | AX4: 16項合成分(式) | AY4: T5板塊ETF開盤(SOXX)[藍] | AZ4: T5板塊ETF收盤(SOXX)[藍] | BA4: T4輸入:NDX5/10乖離%(式) | BB4: T4子分(式) | BC4: T5子分(式)
A5: 1 | B5: 42559 | C5: 2016 | D5: 五 | E5: 4528.36 | F5: 0.024988 | G5: -0.040409 | H5: 0.7347 | I5: 588 | J5: real | K5: 13.2 | L5: =IF(COUNT(F5)=0,50,IF(F5>=0,100,IF(F5>=-0.02,50,0))) -> 100 | M5: =IF(COUNT(G5)=0,50,IF(G5>-0.06,100,IF(G5>-0.15,50,0))) -> 100 | N5: =IF(COUNT(H5)=0,50,IF(H5>=0.6,100,IF(H5>=0.4,50,0))) -> 100 | O5: =IF(COUNT(I5)=0,50,IF(J5="proxy_vix",50,IF(I5<350,100,IF(I5<=450,50,0)))) -> 0 | P5: =IF(COUNT(K5)=0,50,IF(K5<20,100,IF(K5<=25,50,0))) -> 100 | Y5: =IF(AX5>=70,"EASY",IF(AX5>40,"UNCERTAIN","HARD")) -> EASY | AA5: =IF($A5<200,"",AVERAGE($E5:$E5)/AVERAGE($E5:$E5)-1) | AB5: =LOOKUP($B5,07_L1政策步階!$A$4:$A$14,07_L1政策步階!$C$4:$C$14) -> 0 | AL5: =IF(ISNUMBER($AA5),IF($AA5>=0.005,100,IF($AA5>=-0.015,50,0)),"") | AM5: =IF(ISNUMBER($AB5),IF($AB5=1,100,IF($AB5=0,50,0)),"") -> 50 | AN5: =IF(ISNUMBER($AC5),IF($AC5>=0.001,100,IF($AC5>=-0.003,50,0)),"") | AO5: =IF(ISNUMBER($AD5),IF($AD5>=0.04,100,IF($AD5>=0,50,0)),"") | AP5: =IF(ISNUMBER($AE5),IF($AE5>=25,100,IF($AE5>=-75,50,0)),"") | AQ5: =IF(ISNUMBER($AF5),IF($AF5>0,100,IF($AF5>=-50,50,0)),"") | AR5: =IF(ISNUMBER($AG5),IF($AG5=1,100,IF($AG5=0,50,0)),"") | AS5: =IF(ISNUMBER($AH5),IF($AH5<0,100,IF($AH5<=20,50,0)),"") | AT5: =IF(ISNUMBER($AI5),IF($AI5<0.95,100,IF($AI5<=1,50,0)),"") | AU5: =IF(ISNUMBER($AJ5),IF($AJ5<30,0,IF($AJ5<40,50,IF($AJ5<=90,100,50))),"") | AV5: =IF(ISNUMBER($AK5),IF($AK5>-0.2,100,IF($AK5>=-0.4,50,0)),"") | AW5: =01_指標庫!$H$4*ISNUMBER($F5)+01_指標庫!$H$5*ISNUMBER($AA5)+01_指標庫!$H$6*ISNUMBER($G5)+01_指標庫!$H$7*ISNUMBER($H5)+01_指標庫!$H$8*ISNUMBER($AF5)+01_指標庫!$H$9*ISNUMBER($AG5)+01_指標庫!$H$10*ISNUMBER($AB5)+01_指標庫!$H$11*ISNUMBER($AC5)+01_指標庫!$H$12*ISNUMBER($AD5)+01_指標庫!$H$13*ISNUMBER($AE5)+01_指標庫!$H$14*ISNUMBER($I5)+01_指標庫!$H$15*ISNUMBER($AH5)+01_指標庫!$H$16*ISNUMBER($K5)+01_指標庫!$H$17*ISNUMBER($AI5)+01_指標庫!$H$18*ISNUMBER($AJ5)+01_指標庫!$H$19*ISNUMBER($AK5)+01_指標庫!$H$20*ISNUMBER($BB5)+01_指標庫!$H$21*ISNUMBER($BC5) -> 43 | AX5: =IF(AW5=0,50,ROUND((01_指標庫!$H$4*IF(ISNUMBER($F5),L5,0)+01_指標庫!$H$5*IF(ISNUMBER($AA5),AL5,0)+01_指標庫!$H$6*IF(ISNUMBER($G5),M5,0)+01_指標庫!$H$7*IF(ISNUMBER($H5),N5,0)+01_指標庫!$H$8*IF(ISNUMBER($AF5),AQ5,0)+01_指標庫!$H$9*IF(ISNUMBER($AG5),AR5,0)+01_指標庫!$H$10*IF(ISNUMBER($AB5),AM5,0)+01_指標庫!$H$11*IF(ISNUMBER($AC5),AN5,0)+01_指標庫!$H$12*IF(ISNUMBER($AD5),AO5,0)+01_指標庫!$H$13*IF(ISNUMBER($AE5),AP5,0)+01_指標庫!$H$14*IF(ISNUMBER($I5),O5,0)+01_指標庫!$H$15*IF(ISNUMBER($AH5),AS5,0)+01_指標庫!$H$16*IF(ISNUMBER($K5),P5,0)+01_指標庫!$H$17*IF(ISNUMBER($AI5),AT5,0)+01_指標庫!$H$18*IF(ISNUMBER($AJ5),AU5,0)+01_指標庫!$H$19*IF(ISNUMBER($AK5),AV5,0)+01_指標庫!$H$20*IF(ISNUMBER($BB5),BB5,0)+01_指標庫!$H$21*IF(ISNUMBER($BC5),BC5,0))/AW5,1)) -> 75.6
A6: 2 | B6: 42562 | C6: 2016 | D6: 一 | E6: 4554.71 | F6: 0.030625 | G6: -0.034825 | H6: 0.7959 | I6: 566 | J6: real | K6: 13.54 | L6: =IF(COUNT(F6)=0,50,IF(F6>=0,100,IF(F6>=-0.02,50,0))) -> 100 | M6: =IF(COUNT(G6)=0,50,IF(G6>-0.06,100,IF(G6>-0.15,50,0))) -> 100 | N6: =IF(COUNT(H6)=0,50,IF(H6>=0.6,100,IF(H6>=0.4,50,0))) -> 100 | O6: =IF(COUNT(I6)=0,50,IF(J6="proxy_vix",50,IF(I6<350,100,IF(I6<=450,50,0)))) -> 0 | P6: =IF(COUNT(K6)=0,50,IF(K6<20,100,IF(K6<=25,50,0))) -> 100 | S6: =$E6/$E5-1 -> 0.0058188837 | T6: =$K6/$K5-1 -> 0.025757576 | Y6: =IF(AX6>=70,"EASY",IF(AX6>40,"UNCERTAIN","HARD")) -> EASY | AA6: =IF($A6<200,"",AVERAGE($E5:$E6)/AVERAGE($E5:$E6)-1) | AB6: =LOOKUP($B6,07_L1政策步階!$A$4:$A$14,07_L1政策步階!$C$4:$C$14) -> 0 | AL6: =IF(ISNUMBER($AA6),IF($AA6>=0.005,100,IF($AA6>=-0.015,50,0)),"") | AM6: =IF(ISNUMBER($AB6),IF($AB6=1,100,IF($AB6=0,50,0)),"") -> 50 | AN6: =IF(ISNUMBER($AC6),IF($AC6>=0.001,100,IF($AC6>=-0.003,50,0)),"") | AO6: =IF(ISNUMBER($AD6),IF($AD6>=0.04,100,IF($AD6>=0,50,0)),"") | AP6: =IF(ISNUMBER($AE6),IF($AE6>=25,100,IF($AE6>=-75,50,0)),"") | AQ6: =IF(ISNUMBER($AF6),IF($AF6>0,100,IF($AF6>=-50,50,0)),"") | AR6: =IF(ISNUMBER($AG6),IF($AG6=1,100,IF($AG6=0,50,0)),"") | AS6: =IF(ISNUMBER($AH6),IF($AH6<0,100,IF($AH6<=20,50,0)),"") | AT6: =IF(ISNUMBER($AI6),IF($AI6<0.95,100,IF($AI6<=1,50,0)),"") | AU6: =IF(ISNUMBER($AJ6),IF($AJ6<30,0,IF($AJ6<40,50,IF($AJ6<=90,100,50))),"") | AV6: =IF(ISNUMBER($AK6),IF($AK6>-0.2,100,IF($AK6>=-0.4,50,0)),"") | AW6: =01_指標庫!$H$4*ISNUMBER($F6)+01_指標庫!$H$5*ISNUMBER($AA6)+01_指標庫!$H$6*ISNUMBER($G6)+01_指標庫!$H$7*ISNUMBER($H6)+01_指標庫!$H$8*ISNUMBER($AF6)+01_指標庫!$H$9*ISNUMBER($AG6)+01_指標庫!$H$10*ISNUMBER($AB6)+01_指標庫!$H$11*ISNUMBER($AC6)+01_指標庫!$H$12*ISNUMBER($AD6)+01_指標庫!$H$13*ISNUMBER($AE6)+01_指標庫!$H$14*ISNUMBER($I6)+01_指標庫!$H$15*ISNUMBER($AH6)+01_指標庫!$H$16*ISNUMBER($K6)+01_指標庫!$H$17*ISNUMBER($AI6)+01_指標庫!$H$18*ISNUMBER($AJ6)+01_指標庫!$H$19*ISNUMBER($AK6)+01_指標庫!$H$20*ISNUMBER($BB6)+01_指標庫!$H$21*ISNUMBER($BC6) -> 43 | AX6: =IF(AW6=0,50,ROUND((01_指標庫!$H$4*IF(ISNUMBER($F6),L6,0)+01_指標庫!$H$5*IF(ISNUMBER($AA6),AL6,0)+01_指標庫!$H$6*IF(ISNUMBER($G6),M6,0)+01_指標庫!$H$7*IF(ISNUMBER($H6),N6,0)+01_指標庫!$H$8*IF(ISNUMBER($AF6),AQ6,0)+01_指標庫!$H$9*IF(ISNUMBER($AG6),AR6,0)+01_指標庫!$H$10*IF(ISNUMBER($AB6),AM6,0)+01_指標庫!$H$11*IF(ISNUMBER($AC6),AN6,0)+01_指標庫!$H$12*IF(ISNUMBER($AD6),AO6,0)+01_指標庫!$H$13*IF(ISNUMBER($AE6),AP6,0)+01_指標庫!$H$14*IF(ISNUMBER($I6),O6,0)+01_指標庫!$H$15*IF(ISNUMBER($AH6),AS6,0)+01_指標庫!$H$16*IF(ISNUMBER($K6),P6,0)+01_指標庫!$H$17*IF(ISNUMBER($AI6),AT6,0)+01_指標庫!$H$18*IF(ISNUMBER($AJ6),AU6,0)+01_指標庫!$H$19*IF(ISNUMBER($AK6),AV6,0)+01_指標庫!$H$20*IF(ISNUMBER($BB6),BB6,0)+01_指標庫!$H$21*IF(ISNUMBER($BC6),BC6,0))/AW6,1)) -> 75.6 | BC6: =IF(OR(COUNT($AZ6)=0,COUNT($AZ5)=0),"",IF(OR($AY6/$AZ5-1<=-0.03,$AZ6/$AZ5-1<=-0.045,IF(COUNT($AZ5:$AZ6)=10,AVERAGE($AZ5:$AZ6)/AVERAGE($AZ5:$AZ6)-1<-0.01,FALSE())),0,IF(OR($AZ6/$AZ5-1<=-0.02,IF(COUNT($AZ5:$AZ6)=10,AVERAGE($AZ5:$AZ6)/AVERAGE($AZ5:$AZ6)-1<0.005,FALSE())),50,100)))
A7: 3 | B7: 42563 | C7: 2016 | D7: 二 | E7: 4577.61 | F7: 0.035435 | G7: -0.029972 | H7: 0.8163 | I7: 546 | J7: real | K7: 13.55 | L7: =IF(COUNT(F7)=0,50,IF(F7>=0,100,IF(F7>=-0.02,50,0))) -> 100 | M7: =IF(COUNT(G7)=0,50,IF(G7>-0.06,100,IF(G7>-0.15,50,0))) -> 100 | N7: =IF(COUNT(H7)=0,50,IF(H7>=0.6,100,IF(H7>=0.4,50,0))) -> 100 | O7: =IF(COUNT(I7)=0,50,IF(J7="proxy_vix",50,IF(I7<350,100,IF(I7<=450,50,0)))) -> 0 | P7: =IF(COUNT(K7)=0,50,IF(K7<20,100,IF(K7<=25,50,0))) -> 100 | S7: =$E7/$E6-1 -> 0.0050277625 | T7: =$K7/$K6-1 -> 0.00073855244 | Y7: =IF(AX7>=70,"EASY",IF(AX7>40,"UNCERTAIN","HARD")) -> EASY | AA7: =IF($A7<200,"",AVERAGE($E5:$E7)/AVERAGE($E5:$E7)-1) | AB7: =LOOKUP($B7,07_L1政策步階!$A$4:$A$14,07_L1政策步階!$C$4:$C$14) -> 0 | AL7: =IF(ISNUMBER($AA7),IF($AA7>=0.005,100,IF($AA7>=-0.015,50,0)),"") | AM7: =IF(ISNUMBER($AB7),IF($AB7=1,100,IF($AB7=0,50,0)),"") -> 50 | AN7: =IF(ISNUMBER($AC7),IF($AC7>=0.001,100,IF($AC7>=-0.003,50,0)),"") | AO7: =IF(ISNUMBER($AD7),IF($AD7>=0.04,100,IF($AD7>=0,50,0)),"") | AP7: =IF(ISNUMBER($AE7),IF($AE7>=25,100,IF($AE7>=-75,50,0)),"") | AQ7: =IF(ISNUMBER($AF7),IF($AF7>0,100,IF($AF7>=-50,50,0)),"") | AR7: =IF(ISNUMBER($AG7),IF($AG7=1,100,IF($AG7=0,50,0)),"") | AS7: =IF(ISNUMBER($AH7),IF($AH7<0,100,IF($AH7<=20,50,0)),"") | AT7: =IF(ISNUMBER($AI7),IF($AI7<0.95,100,IF($AI7<=1,50,0)),"") | AU7: =IF(ISNUMBER($AJ7),IF($AJ7<30,0,IF($AJ7<40,50,IF($AJ7<=90,100,50))),"") | AV7: =IF(ISNUMBER($AK7),IF($AK7>-0.2,100,IF($AK7>=-0.4,50,0)),"") | AW7: =01_指標庫!$H$4*ISNUMBER($F7)+01_指標庫!$H$5*ISNUMBER($AA7)+01_指標庫!$H$6*ISNUMBER($G7)+01_指標庫!$H$7*ISNUMBER($H7)+01_指標庫!$H$8*ISNUMBER($AF7)+01_指標庫!$H$9*ISNUMBER($AG7)+01_指標庫!$H$10*ISNUMBER($AB7)+01_指標庫!$H$11*ISNUMBER($AC7)+01_指標庫!$H$12*ISNUMBER($AD7)+01_指標庫!$H$13*ISNUMBER($AE7)+01_指標庫!$H$14*ISNUMBER($I7)+01_指標庫!$H$15*ISNUMBER($AH7)+01_指標庫!$H$16*ISNUMBER($K7)+01_指標庫!$H$17*ISNUMBER($AI7)+01_指標庫!$H$18*ISNUMBER($AJ7)+01_指標庫!$H$19*ISNUMBER($AK7)+01_指標庫!$H$20*ISNUMBER($BB7)+01_指標庫!$H$21*ISNUMBER($BC7) -> 43 | AX7: =IF(AW7=0,50,ROUND((01_指標庫!$H$4*IF(ISNUMBER($F7),L7,0)+01_指標庫!$H$5*IF(ISNUMBER($AA7),AL7,0)+01_指標庫!$H$6*IF(ISNUMBER($G7),M7,0)+01_指標庫!$H$7*IF(ISNUMBER($H7),N7,0)+01_指標庫!$H$8*IF(ISNUMBER($AF7),AQ7,0)+01_指標庫!$H$9*IF(ISNUMBER($AG7),AR7,0)+01_指標庫!$H$10*IF(ISNUMBER($AB7),AM7,0)+01_指標庫!$H$11*IF(ISNUMBER($AC7),AN7,0)+01_指標庫!$H$12*IF(ISNUMBER($AD7),AO7,0)+01_指標庫!$H$13*IF(ISNUMBER($AE7),AP7,0)+01_指標庫!$H$14*IF(ISNUMBER($I7),O7,0)+01_指標庫!$H$15*IF(ISNUMBER($AH7),AS7,0)+01_指標庫!$H$16*IF(ISNUMBER($K7),P7,0)+01_指標庫!$H$17*IF(ISNUMBER($AI7),AT7,0)+01_指標庫!$H$18*IF(ISNUMBER($AJ7),AU7,0)+01_指標庫!$H$19*IF(ISNUMBER($AK7),AV7,0)+01_指標庫!$H$20*IF(ISNUMBER($BB7),BB7,0)+01_指標庫!$H$21*IF(ISNUMBER($BC7),BC7,0))/AW7,1)) -> 75.6 | BC7: =IF(OR(COUNT($AZ7)=0,COUNT($AZ6)=0),"",IF(OR($AY7/$AZ6-1<=-0.03,$AZ7/$AZ6-1<=-0.045,IF(COUNT($AZ5:$AZ7)=10,AVERAGE($AZ5:$AZ7)/AVERAGE($AZ5:$AZ7)-1<-0.01,FALSE())),0,IF(OR($AZ7/$AZ6-1<=-0.02,IF(COUNT($AZ5:$AZ7)=10,AVERAGE($AZ5:$AZ7)/AVERAGE($AZ5:$AZ7)-1<0.005,FALSE())),50,100)))
A8: 4 | B8: 42564 | C8: 2016 | D8: 三 | E8: 4565.77 | F8: 0.032359 | G8: -0.032481 | H8: 0.8163 | I8: 558 | J8: real | K8: 13.04 | L8: =IF(COUNT(F8)=0,50,IF(F8>=0,100,IF(F8>=-0.02,50,0))) -> 100 | M8: =IF(COUNT(G8)=0,50,IF(G8>-0.06,100,IF(G8>-0.15,50,0))) -> 100 | N8: =IF(COUNT(H8)=0,50,IF(H8>=0.6,100,IF(H8>=0.4,50,0))) -> 100 | O8: =IF(COUNT(I8)=0,50,IF(J8="proxy_vix",50,IF(I8<350,100,IF(I8<=450,50,0)))) -> 0 | P8: =IF(COUNT(K8)=0,50,IF(K8<20,100,IF(K8<=25,50,0))) -> 100 | S8: =$E8/$E7-1 -> -0.0025865026 | T8: =$K8/$K7-1 -> -0.037638376 | Y8: =IF(AX8>=70,"EASY",IF(AX8>40,"UNCERTAIN","HARD")) -> EASY | AA8: =IF($A8<200,"",AVERAGE($E5:$E8)/AVERAGE($E5:$E8)-1) | AB8: =LOOKUP($B8,07_L1政策步階!$A$4:$A$14,07_L1政策步階!$C$4:$C$14) -> 0 | AL8: =IF(ISNUMBER($AA8),IF($AA8>=0.005,100,IF($AA8>=-0.015,50,0)),"") | AM8: =IF(ISNUMBER($AB8),IF($AB8=1,100,IF($AB8=0,50,0)),"") -> 50 | AN8: =IF(ISNUMBER($AC8),IF($AC8>=0.001,100,IF($AC8>=-0.003,50,0)),"") | AO8: =IF(ISNUMBER($AD8),IF($AD8>=0.04,100,IF($AD8>=0,50,0)),"") | AP8: =IF(ISNUMBER($AE8),IF($AE8>=25,100,IF($AE8>=-75,50,0)),"") | AQ8: =IF(ISNUMBER($AF8),IF($AF8>0,100,IF($AF8>=-50,50,0)),"") | AR8: =IF(ISNUMBER($AG8),IF($AG8=1,100,IF($AG8=0,50,0)),"") | AS8: =IF(ISNUMBER($AH8),IF($AH8<0,100,IF($AH8<=20,50,0)),"") | AT8: =IF(ISNUMBER($AI8),IF($AI8<0.95,100,IF($AI8<=1,50,0)),"") | AU8: =IF(ISNUMBER($AJ8),IF($AJ8<30,0,IF($AJ8<40,50,IF($AJ8<=90,100,50))),"") | AV8: =IF(ISNUMBER($AK8),IF($AK8>-0.2,100,IF($AK8>=-0.4,50,0)),"") | AW8: =01_指標庫!$H$4*ISNUMBER($F8)+01_指標庫!$H$5*ISNUMBER($AA8)+01_指標庫!$H$6*ISNUMBER($G8)+01_指標庫!$H$7*ISNUMBER($H8)+01_指標庫!$H$8*ISNUMBER($AF8)+01_指標庫!$H$9*ISNUMBER($AG8)+01_指標庫!$H$10*ISNUMBER($AB8)+01_指標庫!$H$11*ISNUMBER($AC8)+01_指標庫!$H$12*ISNUMBER($AD8)+01_指標庫!$H$13*ISNUMBER($AE8)+01_指標庫!$H$14*ISNUMBER($I8)+01_指標庫!$H$15*ISNUMBER($AH8)+01_指標庫!$H$16*ISNUMBER($K8)+01_指標庫!$H$17*ISNUMBER($AI8)+01_指標庫!$H$18*ISNUMBER($AJ8)+01_指標庫!$H$19*ISNUMBER($AK8)+01_指標庫!$H$20*ISNUMBER($BB8)+01_指標庫!$H$21*ISNUMBER($BC8) -> 43 | AX8: =IF(AW8=0,50,ROUND((01_指標庫!$H$4*IF(ISNUMBER($F8),L8,0)+01_指標庫!$H$5*IF(ISNUMBER($AA8),AL8,0)+01_指標庫!$H$6*IF(ISNUMBER($G8),M8,0)+01_指標庫!$H$7*IF(ISNUMBER($H8),N8,0)+01_指標庫!$H$8*IF(ISNUMBER($AF8),AQ8,0)+01_指標庫!$H$9*IF(ISNUMBER($AG8),AR8,0)+01_指標庫!$H$10*IF(ISNUMBER($AB8),AM8,0)+01_指標庫!$H$11*IF(ISNUMBER($AC8),AN8,0)+01_指標庫!$H$12*IF(ISNUMBER($AD8),AO8,0)+01_指標庫!$H$13*IF(ISNUMBER($AE8),AP8,0)+01_指標庫!$H$14*IF(ISNUMBER($I8),O8,0)+01_指標庫!$H$15*IF(ISNUMBER($AH8),AS8,0)+01_指標庫!$H$16*IF(ISNUMBER($K8),P8,0)+01_指標庫!$H$17*IF(ISNUMBER($AI8),AT8,0)+01_指標庫!$H$18*IF(ISNUMBER($AJ8),AU8,0)+01_指標庫!$H$19*IF(ISNUMBER($AK8),AV8,0)+01_指標庫!$H$20*IF(ISNUMBER($BB8),BB8,0)+01_指標庫!$H$21*IF(ISNUMBER($BC8),BC8,0))/AW8,1)) -> 75.6 | BC8: =IF(OR(COUNT($AZ8)=0,COUNT($AZ7)=0),"",IF(OR($AY8/$AZ7-1<=-0.03,$AZ8/$AZ7-1<=-0.045,IF(COUNT($AZ5:$AZ8)=10,AVERAGE($AZ5:$AZ8)/AVERAGE($AZ5:$AZ8)-1<-0.01,FALSE())),0,IF(OR($AZ8/$AZ7-1<=-0.02,IF(COUNT($AZ5:$AZ8)=10,AVERAGE($AZ5:$AZ8)/AVERAGE($AZ5:$AZ8)-1<0.005,FALSE())),50,100)))
A9: 5 | B9: 42565 | C9: 2016 | D9: 四 | E9: 4596.49 | F9: 0.038726 | G9: -0.025971 | H9: 0.8367 | I9: 544 | J9: real | K9: 12.82 | L9: =IF(COUNT(F9)=0,50,IF(F9>=0,100,IF(F9>=-0.02,50,0))) -> 100 | M9: =IF(COUNT(G9)=0,50,IF(G9>-0.06,100,IF(G9>-0.15,50,0))) -> 100 | N9: =IF(COUNT(H9)=0,50,IF(H9>=0.6,100,IF(H9>=0.4,50,0))) -> 100 | O9: =IF(COUNT(I9)=0,50,IF(J9="proxy_vix",50,IF(I9<350,100,IF(I9<=450,50,0)))) -> 0 | P9: =IF(COUNT(K9)=0,50,IF(K9<20,100,IF(K9<=25,50,0))) -> 100 | S9: =$E9/$E8-1 -> 0.0067283284 | T9: =$K9/$K8-1 -> -0.016871166 | Y9: =IF(AX9>=70,"EASY",IF(AX9>40,"UNCERTAIN","HARD")) -> EASY | AA9: =IF($A9<200,"",AVERAGE($E5:$E9)/AVERAGE($E5:$E9)-1) | AB9: =LOOKUP($B9,07_L1政策步階!$A$4:$A$14,07_L1政策步階!$C$4:$C$14) -> 0 | AL9: =IF(ISNUMBER($AA9),IF($AA9>=0.005,100,IF($AA9>=-0.015,50,0)),"") | AM9: =IF(ISNUMBER($AB9),IF($AB9=1,100,IF($AB9=0,50,0)),"") -> 50 | AN9: =IF(ISNUMBER($AC9),IF($AC9>=0.001,100,IF($AC9>=-0.003,50,0)),"") | AO9: =IF(ISNUMBER($AD9),IF($AD9>=0.04,100,IF($AD9>=0,50,0)),"") | AP9: =IF(ISNUMBER($AE9),IF($AE9>=25,100,IF($AE9>=-75,50,0)),"") | AQ9: =IF(ISNUMBER($AF9),IF($AF9>0,100,IF($AF9>=-50,50,0)),"") | AR9: =IF(ISNUMBER($AG9),IF($AG9=1,100,IF($AG9=0,50,0)),"") | AS9: =IF(ISNUMBER($AH9),IF($AH9<0,100,IF($AH9<=20,50,0)),"") | AT9: =IF(ISNUMBER($AI9),IF($AI9<0.95,100,IF($AI9<=1,50,0)),"") | AU9: =IF(ISNUMBER($AJ9),IF($AJ9<30,0,IF($AJ9<40,50,IF($AJ9<=90,100,50))),"") | AV9: =IF(ISNUMBER($AK9),IF($AK9>-0.2,100,IF($AK9>=-0.4,50,0)),"") | AW9: =01_指標庫!$H$4*ISNUMBER($F9)+01_指標庫!$H$5*ISNUMBER($AA9)+01_指標庫!$H$6*ISNUMBER($G9)+01_指標庫!$H$7*ISNUMBER($H9)+01_指標庫!$H$8*ISNUMBER($AF9)+01_指標庫!$H$9*ISNUMBER($AG9)+01_指標庫!$H$10*ISNUMBER($AB9)+01_指標庫!$H$11*ISNUMBER($AC9)+01_指標庫!$H$12*ISNUMBER($AD9)+01_指標庫!$H$13*ISNUMBER($AE9)+01_指標庫!$H$14*ISNUMBER($I9)+01_指標庫!$H$15*ISNUMBER($AH9)+01_指標庫!$H$16*ISNUMBER($K9)+01_指標庫!$H$17*ISNUMBER($AI9)+01_指標庫!$H$18*ISNUMBER($AJ9)+01_指標庫!$H$19*ISNUMBER($AK9)+01_指標庫!$H$20*ISNUMBER($BB9)+01_指標庫!$H$21*ISNUMBER($BC9) -> 43 | AX9: =IF(AW9=0,50,ROUND((01_指標庫!$H$4*IF(ISNUMBER($F9),L9,0)+01_指標庫!$H$5*IF(ISNUMBER($AA9),AL9,0)+01_指標庫!$H$6*IF(ISNUMBER($G9),M9,0)+01_指標庫!$H$7*IF(ISNUMBER($H9),N9,0)+01_指標庫!$H$8*IF(ISNUMBER($AF9),AQ9,0)+01_指標庫!$H$9*IF(ISNUMBER($AG9),AR9,0)+01_指標庫!$H$10*IF(ISNUMBER($AB9),AM9,0)+01_指標庫!$H$11*IF(ISNUMBER($AC9),AN9,0)+01_指標庫!$H$12*IF(ISNUMBER($AD9),AO9,0)+01_指標庫!$H$13*IF(ISNUMBER($AE9),AP9,0)+01_指標庫!$H$14*IF(ISNUMBER($I9),O9,0)+01_指標庫!$H$15*IF(ISNUMBER($AH9),AS9,0)+01_指標庫!$H$16*IF(ISNUMBER($K9),P9,0)+01_指標庫!$H$17*IF(ISNUMBER($AI9),AT9,0)+01_指標庫!$H$18*IF(ISNUMBER($AJ9),AU9,0)+01_指標庫!$H$19*IF(ISNUMBER($AK9),AV9,0)+01_指標庫!$H$20*IF(ISNUMBER($BB9),BB9,0)+01_指標庫!$H$21*IF(ISNUMBER($BC9),BC9,0))/AW9,1)) -> 75.6 | BC9: =IF(OR(COUNT($AZ9)=0,COUNT($AZ8)=0),"",IF(OR($AY9/$AZ8-1<=-0.03,$AZ9/$AZ8-1<=-0.045,IF(COUNT($AZ5:$AZ9)=10,AVERAGE($AZ5:$AZ9)/AVERAGE($AZ5:$AZ9)-1<-0.01,FALSE())),0,IF(OR($AZ9/$AZ8-1<=-0.02,IF(COUNT($AZ5:$AZ9)=10,AVERAGE($AZ5:$AZ9)/AVERAGE($AZ5:$AZ9)-1<0.005,FALSE())),50,100)))
A10: 6 | B10: 42566 | C10: 2016 | D10: 五 | E10: 4589.83 | F10: 0.036628 | G10: -0.027383 | H10: 0.8367 | I10: 542 | J10: real | K10: 12.67 | L10: =IF(COUNT(F10)=0,50,IF(F10>=0,100,IF(F10>=-0.02,50,0))) -> 100 | M10: =IF(COUNT(G10)=0,50,IF(G10>-0.06,100,IF(G10>-0.15,50,0))) -> 100 | N10: =IF(COUNT(H10)=0,50,IF(H10>=0.6,100,IF(H10>=0.4,50,0))) -> 100 | O10: =IF(COUNT(I10)=0,50,IF(J10="proxy_vix",50,IF(I10<350,100,IF(I10<=450,50,0)))) -> 0 | P10: =IF(COUNT(K10)=0,50,IF(K10<20,100,IF(K10<=25,50,0))) -> 100 | S10: =$E10/$E9-1 -> -0.0014489317 | T10: =$K10/$K9-1 -> -0.011700468 | Y10: =IF(AX10>=70,"EASY",IF(AX10>40,"UNCERTAIN","HARD")) -> EASY | AA10: =IF($A10<200,"",AVERAGE($E5:$E10)/AVERAGE($E5:$E10)-1) | AB10: =LOOKUP($B10,07_L1政策步階!$A$4:$A$14,07_L1政策步階!$C$4:$C$14) -> 0 | AL10: =IF(ISNUMBER($AA10),IF($AA10>=0.005,100,IF($AA10>=-0.015,50,0)),"") | AM10: =IF(ISNUMBER($AB10),IF($AB10=1,100,IF($AB10=0,50,0)),"") -> 50 | AN10: =IF(ISNUMBER($AC10),IF($AC10>=0.001,100,IF($AC10>=-0.003,50,0)),"") | AO10: =IF(ISNUMBER($AD10),IF($AD10>=0.04,100,IF($AD10>=0,50,0)),"") | AP10: =IF(ISNUMBER($AE10),IF($AE10>=25,100,IF($AE10>=-75,50,0)),"") | AQ10: =IF(ISNUMBER($AF10),IF($AF10>0,100,IF($AF10>=-50,50,0)),"") | AR10: =IF(ISNUMBER($AG10),IF($AG10=1,100,IF($AG10=0,50,0)),"") | AS10: =IF(ISNUMBER($AH10),IF($AH10<0,100,IF($AH10<=20,50,0)),"") | AT10: =IF(ISNUMBER($AI10),IF($AI10<0.95,100,IF($AI10<=1,50,0)),"") | AU10: =IF(ISNUMBER($AJ10),IF($AJ10<30,0,IF($AJ10<40,50,IF($AJ10<=90,100,50))),"") | AV10: =IF(ISNUMBER($AK10),IF($AK10>-0.2,100,IF($AK10>=-0.4,50,0)),"") | AW10: =01_指標庫!$H$4*ISNUMBER($F10)+01_指標庫!$H$5*ISNUMBER($AA10)+01_指標庫!$H$6*ISNUMBER($G10)+01_指標庫!$H$7*ISNUMBER($H10)+01_指標庫!$H$8*ISNUMBER($AF10)+01_指標庫!$H$9*ISNUMBER($AG10)+01_指標庫!$H$10*ISNUMBER($AB10)+01_指標庫!$H$11*ISNUMBER($AC10)+01_指標庫!$H$12*ISNUMBER($AD10)+01_指標庫!$H$13*ISNUMBER($AE10)+01_指標庫!$H$14*ISNUMBER($I10)+01_指標庫!$H$15*ISNUMBER($AH10)+01_指標庫!$H$16*ISNUMBER($K10)+01_指標庫!$H$17*ISNUMBER($AI10)+01_指標庫!$H$18*ISNUMBER($AJ10)+01_指標庫!$H$19*ISNUMBER($AK10)+01_指標庫!$H$20*ISNUMBER($BB10)+01_指標庫!$H$21*ISNUMBER($BC10) -> 43 | AX10: =IF(AW10=0,50,ROUND((01_指標庫!$H$4*IF(ISNUMBER($F10),L10,0)+01_指標庫!$H$5*IF(ISNUMBER($AA10),AL10,0)+01_指標庫!$H$6*IF(ISNUMBER($G10),M10,0)+01_指標庫!$H$7*IF(ISNUMBER($H10),N10,0)+01_指標庫!$H$8*IF(ISNUMBER($AF10),AQ10,0)+01_指標庫!$H$9*IF(ISNUMBER($AG10),AR10,0)+01_指標庫!$H$10*IF(ISNUMBER($AB10),AM10,0)+01_指標庫!$H$11*IF(ISNUMBER($AC10),AN10,0)+01_指標庫!$H$12*IF(ISNUMBER($AD10),AO10,0)+01_指標庫!$H$13*IF(ISNUMBER($AE10),AP10,0)+01_指標庫!$H$14*IF(ISNUMBER($I10),O10,0)+01_指標庫!$H$15*IF(ISNUMBER($AH10),AS10,0)+01_指標庫!$H$16*IF(ISNUMBER($K10),P10,0)+01_指標庫!$H$17*IF(ISNUMBER($AI10),AT10,0)+01_指標庫!$H$18*IF(ISNUMBER($AJ10),AU10,0)+01_指標庫!$H$19*IF(ISNUMBER($AK10),AV10,0)+01_指標庫!$H$20*IF(ISNUMBER($BB10),BB10,0)+01_指標庫!$H$21*IF(ISNUMBER($BC10),BC10,0))/AW10,1)) -> 75.6 | BC10: =IF(OR(COUNT($AZ10)=0,COUNT($AZ9)=0),"",IF(OR($AY10/$AZ9-1<=-0.03,$AZ10/$AZ9-1<=-0.045,IF(COUNT($AZ5:$AZ10)=10,AVERAGE($AZ6:$AZ10)/AVERAGE($AZ5:$AZ10)-1<-0.01,FALSE())),0,IF(OR($AZ10/$AZ9-1<=-0.02,IF(COUNT($AZ5:$AZ10)=10,AVERAGE($AZ6:$AZ10)/AVERAGE($AZ5:$AZ10)-1<0.005,FALSE())),50,100)))
A11: 7 | B11: 42569 | C11: 2016 | D11: 一 | E11: 4619.68 | F11: 0.042853 | G11: -0.021057 | H11: 0.8367 | I11: 544 | J11: real | K11: 12.44 | L11: =IF(COUNT(F11)=0,50,IF(F11>=0,100,IF(F11>=-0.02,50,0))) -> 100 | M11: =IF(COUNT(G11)=0,50,IF(G11>-0.06,100,IF(G11>-0.15,50,0))) -> 100 | N11: =IF(COUNT(H11)=0,50,IF(H11>=0.6,100,IF(H11>=0.4,50,0))) -> 100 | O11: =IF(COUNT(I11)=0,50,IF(J11="proxy_vix",50,IF(I11<350,100,IF(I11<=450,50,0)))) -> 0 | P11: =IF(COUNT(K11)=0,50,IF(K11<20,100,IF(K11<=25,50,0))) -> 100 | S11: =$E11/$E10-1 -> 0.0065035088 | T11: =$K11/$K10-1 -> -0.018153118 | Y11: =IF(AX11>=70,"EASY",IF(AX11>40,"UNCERTAIN","HARD")) -> EASY | AA11: =IF($A11<200,"",AVERAGE($E5:$E11)/AVERAGE($E5:$E11)-1) | AB11: =LOOKUP($B11,07_L1政策步階!$A$4:$A$14,07_L1政策步階!$C$4:$C$14) -> 0 | AL11: =IF(ISNUMBER($AA11),IF($AA11>=0.005,100,IF($AA11>=-0.015,50,0)),"") | AM11: =IF(ISNUMBER($AB11),IF($AB11=1,100,IF($AB11=0,50,0)),"") -> 50 | AN11: =IF(ISNUMBER($AC11),IF($AC11>=0.001,100,IF($AC11>=-0.003,50,0)),"") | AO11: =IF(ISNUMBER($AD11),IF($AD11>=0.04,100,IF($AD11>=0,50,0)),"") | AP11: =IF(ISNUMBER($AE11),IF($AE11>=25,100,IF($AE11>=-75,50,0)),"") | AQ11: =IF(ISNUMBER($AF11),IF($AF11>0,100,IF($AF11>=-50,50,0)),"") | AR11: =IF(ISNUMBER($AG11),IF($AG11=1,100,IF($AG11=0,50,0)),"") | AS11: =IF(ISNUMBER($AH11),IF($AH11<0,100,IF($AH11<=20,50,0)),"") | AT11: =IF(ISNUMBER($AI11),IF($AI11<0.95,100,IF($AI11<=1,50,0)),"") | AU11: =IF(ISNUMBER($AJ11),IF($AJ11<30,0,IF($AJ11<40,50,IF($AJ11<=90,100,50))),"") | AV11: =IF(ISNUMBER($AK11),IF($AK11>-0.2,100,IF($AK11>=-0.4,50,0)),"") | AW11: =01_指標庫!$H$4*ISNUMBER($F11)+01_指標庫!$H$5*ISNUMBER($AA11)+01_指標庫!$H$6*ISNUMBER($G11)+01_指標庫!$H$7*ISNUMBER($H11)+01_指標庫!$H$8*ISNUMBER($AF11)+01_指標庫!$H$9*ISNUMBER($AG11)+01_指標庫!$H$10*ISNUMBER($AB11)+01_指標庫!$H$11*ISNUMBER($AC11)+01_指標庫!$H$12*ISNUMBER($AD11)+01_指標庫!$H$13*ISNUMBER($AE11)+01_指標庫!$H$14*ISNUMBER($I11)+01_指標庫!$H$15*ISNUMBER($AH11)+01_指標庫!$H$16*ISNUMBER($K11)+01_指標庫!$H$17*ISNUMBER($AI11)+01_指標庫!$H$18*ISNUMBER($AJ11)+01_指標庫!$H$19*ISNUMBER($AK11)+01_指標庫!$H$20*ISNUMBER($BB11)+01_指標庫!$H$21*ISNUMBER($BC11) -> 43 | AX11: =IF(AW11=0,50,ROUND((01_指標庫!$H$4*IF(ISNUMBER($F11),L11,0)+01_指標庫!$H$5*IF(ISNUMBER($AA11),AL11,0)+01_指標庫!$H$6*IF(ISNUMBER($G11),M11,0)+01_指標庫!$H$7*IF(ISNUMBER($H11),N11,0)+01_指標庫!$H$8*IF(ISNUMBER($AF11),AQ11,0)+01_指標庫!$H$9*IF(ISNUMBER($AG11),AR11,0)+01_指標庫!$H$10*IF(ISNUMBER($AB11),AM11,0)+01_指標庫!$H$11*IF(ISNUMBER($AC11),AN11,0)+01_指標庫!$H$12*IF(ISNUMBER($AD11),AO11,0)+01_指標庫!$H$13*IF(ISNUMBER($AE11),AP11,0)+01_指標庫!$H$14*IF(ISNUMBER($I11),O11,0)+01_指標庫!$H$15*IF(ISNUMBER($AH11),AS11,0)+01_指標庫!$H$16*IF(ISNUMBER($K11),P11,0)+01_指標庫!$H$17*IF(ISNUMBER($AI11),AT11,0)+01_指標庫!$H$18*IF(ISNUMBER($AJ11),AU11,0)+01_指標庫!$H$19*IF(ISNUMBER($AK11),AV11,0)+01_指標庫!$H$20*IF(ISNUMBER($BB11),BB11,0)+01_指標庫!$H$21*IF(ISNUMBER($BC11),BC11,0))/AW11,1)) -> 75.6 | BC11: =IF(OR(COUNT($AZ11)=0,COUNT($AZ10)=0),"",IF(OR($AY11/$AZ10-1<=-0.03,$AZ11/$AZ10-1<=-0.045,IF(COUNT($AZ5:$AZ11)=10,AVERAGE($AZ7:$AZ11)/AVERAGE($AZ5:$AZ11)-1<-0.01,FALSE())),0,IF(OR($AZ11/$AZ10-1<=-0.02,IF(COUNT($AZ5:$AZ11)=10,AVERAGE($AZ7:$AZ11)/AVERAGE($AZ5:$AZ11)-1<0.005,FALSE())),50,100)))
A12: 8 | B12: 42570 | C12: 2016 | D12: 二 | E12: 4603.28 | F12: 0.03867 | G12: -0.024532 | H12: 0.8367 | I12: 545 | J12: real | K12: 11.97 | L12: =IF(COUNT(F12)=0,50,IF(F12>=0,100,IF(F12>=-0.02,50,0))) -> 100 | M12: =IF(COUNT(G12)=0,50,IF(G12>-0.06,100,IF(G12>-0.15,50,0))) -> 100 | N12: =IF(COUNT(H12)=0,50,IF(H12>=0.6,100,IF(H12>=0.4,50,0))) -> 100 | O12: =IF(COUNT(I12)=0,50,IF(J12="proxy_vix",50,IF(I12<350,100,IF(I12<=450,50,0)))) -> 0 | P12: =IF(COUNT(K12)=0,50,IF(K12<20,100,IF(K12<=25,50,0))) -> 100 | S12: =$E12/$E11-1 -> -0.0035500294 | T12: =$K12/$K11-1 -> -0.03778135 | Y12: =IF(AX12>=70,"EASY",IF(AX12>40,"UNCERTAIN","HARD")) -> EASY | AA12: =IF($A12<200,"",AVERAGE($E5:$E12)/AVERAGE($E5:$E12)-1) | AB12: =LOOKUP($B12,07_L1政策步階!$A$4:$A$14,07_L1政策步階!$C$4:$C$14) -> 0 | AL12: =IF(ISNUMBER($AA12),IF($AA12>=0.005,100,IF($AA12>=-0.015,50,0)),"") | AM12: =IF(ISNUMBER($AB12),IF($AB12=1,100,IF($AB12=0,50,0)),"") -> 50 | AN12: =IF(ISNUMBER($AC12),IF($AC12>=0.001,100,IF($AC12>=-0.003,50,0)),"") | AO12: =IF(ISNUMBER($AD12),IF($AD12>=0.04,100,IF($AD12>=0,50,0)),"") | AP12: =IF(ISNUMBER($AE12),IF($AE12>=25,100,IF($AE12>=-75,50,0)),"") | AQ12: =IF(ISNUMBER($AF12),IF($AF12>0,100,IF($AF12>=-50,50,0)),"") | AR12: =IF(ISNUMBER($AG12),IF($AG12=1,100,IF($AG12=0,50,0)),"") | AS12: =IF(ISNUMBER($AH12),IF($AH12<0,100,IF($AH12<=20,50,0)),"") | AT12: =IF(ISNUMBER($AI12),IF($AI12<0.95,100,IF($AI12<=1,50,0)),"") | AU12: =IF(ISNUMBER($AJ12),IF($AJ12<30,0,IF($AJ12<40,50,IF($AJ12<=90,100,50))),"") | AV12: =IF(ISNUMBER($AK12),IF($AK12>-0.2,100,IF($AK12>=-0.4,50,0)),"") | AW12: =01_指標庫!$H$4*ISNUMBER($F12)+01_指標庫!$H$5*ISNUMBER($AA12)+01_指標庫!$H$6*ISNUMBER($G12)+01_指標庫!$H$7*ISNUMBER($H12)+01_指標庫!$H$8*ISNUMBER($AF12)+01_指標庫!$H$9*ISNUMBER($AG12)+01_指標庫!$H$10*ISNUMBER($AB12)+01_指標庫!$H$11*ISNUMBER($AC12)+01_指標庫!$H$12*ISNUMBER($AD12)+01_指標庫!$H$13*ISNUMBER($AE12)+01_指標庫!$H$14*ISNUMBER($I12)+01_指標庫!$H$15*ISNUMBER($AH12)+01_指標庫!$H$16*ISNUMBER($K12)+01_指標庫!$H$17*ISNUMBER($AI12)+01_指標庫!$H$18*ISNUMBER($AJ12)+01_指標庫!$H$19*ISNUMBER($AK12)+01_指標庫!$H$20*ISNUMBER($BB12)+01_指標庫!$H$21*ISNUMBER($BC12) -> 43 | AX12: =IF(AW12=0,50,ROUND((01_指標庫!$H$4*IF(ISNUMBER($F12),L12,0)+01_指標庫!$H$5*IF(ISNUMBER($AA12),AL12,0)+01_指標庫!$H$6*IF(ISNUMBER($G12),M12,0)+01_指標庫!$H$7*IF(ISNUMBER($H12),N12,0)+01_指標庫!$H$8*IF(ISNUMBER($AF12),AQ12,0)+01_指標庫!$H$9*IF(ISNUMBER($AG12),AR12,0)+01_指標庫!$H$10*IF(ISNUMBER($AB12),AM12,0)+01_指標庫!$H$11*IF(ISNUMBER($AC12),AN12,0)+01_指標庫!$H$12*IF(ISNUMBER($AD12),AO12,0)+01_指標庫!$H$13*IF(ISNUMBER($AE12),AP12,0)+01_指標庫!$H$14*IF(ISNUMBER($I12),O12,0)+01_指標庫!$H$15*IF(ISNUMBER($AH12),AS12,0)+01_指標庫!$H$16*IF(ISNUMBER($K12),P12,0)+01_指標庫!$H$17*IF(ISNUMBER($AI12),AT12,0)+01_指標庫!$H$18*IF(ISNUMBER($AJ12),AU12,0)+01_指標庫!$H$19*IF(ISNUMBER($AK12),AV12,0)+01_指標庫!$H$20*IF(ISNUMBER($BB12),BB12,0)+01_指標庫!$H$21*IF(ISNUMBER($BC12),BC12,0))/AW12,1)) -> 75.6 | BC12: =IF(OR(COUNT($AZ12)=0,COUNT($AZ11)=0),"",IF(OR($AY12/$AZ11-1<=-0.03,$AZ12/$AZ11-1<=-0.045,IF(COUNT($AZ5:$AZ12)=10,AVERAGE($AZ8:$AZ12)/AVERAGE($AZ5:$AZ12)-1<-0.01,FALSE())),0,IF(OR($AZ12/$AZ11-1<=-0.02,IF(COUNT($AZ5:$AZ12)=10,AVERAGE($AZ8:$AZ12)/AVERAGE($AZ5:$AZ12)-1<0.005,FALSE())),50,100)))
A13: 9 | B13: 42571 | C13: 2016 | D13: 三 | E13: 4657.2 | F13: 0.050374 | G13: -0.013106 | H13: 0.8571 | I13: 540 | J13: real | K13: 11.77 | L13: =IF(COUNT(F13)=0,50,IF(F13>=0,100,IF(F13>=-0.02,50,0))) -> 100 | M13: =IF(COUNT(G13)=0,50,IF(G13>-0.06,100,IF(G13>-0.15,50,0))) -> 100 | N13: =IF(COUNT(H13)=0,50,IF(H13>=0.6,100,IF(H13>=0.4,50,0))) -> 100 | O13: =IF(COUNT(I13)=0,50,IF(J13="proxy_vix",50,IF(I13<350,100,IF(I13<=450,50,0)))) -> 0 | P13: =IF(COUNT(K13)=0,50,IF(K13<20,100,IF(K13<=25,50,0))) -> 100 | S13: =$E13/$E12-1 -> 0.011713387 | T13: =$K13/$K12-1 -> -0.016708438 | Y13: =IF(AX13>=70,"EASY",IF(AX13>40,"UNCERTAIN","HARD")) -> EASY | AA13: =IF($A13<200,"",AVERAGE($E5:$E13)/AVERAGE($E5:$E13)-1) | AB13: =LOOKUP($B13,07_L1政策步階!$A$4:$A$14,07_L1政策步階!$C$4:$C$14) -> 0 | AL13: =IF(ISNUMBER($AA13),IF($AA13>=0.005,100,IF($AA13>=-0.015,50,0)),"") | AM13: =IF(ISNUMBER($AB13),IF($AB13=1,100,IF($AB13=0,50,0)),"") -> 50 | AN13: =IF(ISNUMBER($AC13),IF($AC13>=0.001,100,IF($AC13>=-0.003,50,0)),"") | AO13: =IF(ISNUMBER($AD13),IF($AD13>=0.04,100,IF($AD13>=0,50,0)),"") | AP13: =IF(ISNUMBER($AE13),IF($AE13>=25,100,IF($AE13>=-75,50,0)),"") | AQ13: =IF(ISNUMBER($AF13),IF($AF13>0,100,IF($AF13>=-50,50,0)),"") | AR13: =IF(ISNUMBER($AG13),IF($AG13=1,100,IF($AG13=0,50,0)),"") | AS13: =IF(ISNUMBER($AH13),IF($AH13<0,100,IF($AH13<=20,50,0)),"") | AT13: =IF(ISNUMBER($AI13),IF($AI13<0.95,100,IF($AI13<=1,50,0)),"") | AU13: =IF(ISNUMBER($AJ13),IF($AJ13<30,0,IF($AJ13<40,50,IF($AJ13<=90,100,50))),"") | AV13: =IF(ISNUMBER($AK13),IF($AK13>-0.2,100,IF($AK13>=-0.4,50,0)),"") | AW13: =01_指標庫!$H$4*ISNUMBER($F13)+01_指標庫!$H$5*ISNUMBER($AA13)+01_指標庫!$H$6*ISNUMBER($G13)+01_指標庫!$H$7*ISNUMBER($H13)+01_指標庫!$H$8*ISNUMBER($AF13)+01_指標庫!$H$9*ISNUMBER($AG13)+01_指標庫!$H$10*ISNUMBER($AB13)+01_指標庫!$H$11*ISNUMBER($AC13)+01_指標庫!$H$12*ISNUMBER($AD13)+01_指標庫!$H$13*ISNUMBER($AE13)+01_指標庫!$H$14*ISNUMBER($I13)+01_指標庫!$H$15*ISNUMBER($AH13)+01_指標庫!$H$16*ISNUMBER($K13)+01_指標庫!$H$17*ISNUMBER($AI13)+01_指標庫!$H$18*ISNUMBER($AJ13)+01_指標庫!$H$19*ISNUMBER($AK13)+01_指標庫!$H$20*ISNUMBER($BB13)+01_指標庫!$H$21*ISNUMBER($BC13) -> 43 | AX13: =IF(AW13=0,50,ROUND((01_指標庫!$H$4*IF(ISNUMBER($F13),L13,0)+01_指標庫!$H$5*IF(ISNUMBER($AA13),AL13,0)+01_指標庫!$H$6*IF(ISNUMBER($G13),M13,0)+01_指標庫!$H$7*IF(ISNUMBER($H13),N13,0)+01_指標庫!$H$8*IF(ISNUMBER($AF13),AQ13,0)+01_指標庫!$H$9*IF(ISNUMBER($AG13),AR13,0)+01_指標庫!$H$10*IF(ISNUMBER($AB13),AM13,0)+01_指標庫!$H$11*IF(ISNUMBER($AC13),AN13,0)+01_指標庫!$H$12*IF(ISNUMBER($AD13),AO13,0)+01_指標庫!$H$13*IF(ISNUMBER($AE13),AP13,0)+01_指標庫!$H$14*IF(ISNUMBER($I13),O13,0)+01_指標庫!$H$15*IF(ISNUMBER($AH13),AS13,0)+01_指標庫!$H$16*IF(ISNUMBER($K13),P13,0)+01_指標庫!$H$17*IF(ISNUMBER($AI13),AT13,0)+01_指標庫!$H$18*IF(ISNUMBER($AJ13),AU13,0)+01_指標庫!$H$19*IF(ISNUMBER($AK13),AV13,0)+01_指標庫!$H$20*IF(ISNUMBER($BB13),BB13,0)+01_指標庫!$H$21*IF(ISNUMBER($BC13),BC13,0))/AW13,1)) -> 75.6 | BC13: =IF(OR(COUNT($AZ13)=0,COUNT($AZ12)=0),"",IF(OR($AY13/$AZ12-1<=-0.03,$AZ13/$AZ12-1<=-0.045,IF(COUNT($AZ5:$AZ13)=10,AVERAGE($AZ9:$AZ13)/AVERAGE($AZ5:$AZ13)-1<-0.01,FALSE())),0,IF(OR($AZ13/$AZ12-1<=-0.02,IF(COUNT($AZ5:$AZ13)=10,AVERAGE($AZ9:$AZ13)/AVERAGE($AZ5:$AZ13)-1<0.005,FALSE())),50,100)))
A14: 10 | B14: 42572 | C14: 2016 | D14: 四 | E14: 4647.02 | F14: 0.047706 | G14: -0.015264 | H14: 0.8571 | I14: 541 | J14: real | K14: 12.74 | L14: =IF(COUNT(F14)=0,50,IF(F14>=0,100,IF(F14>=-0.02,50,0))) -> 100 | M14: =IF(COUNT(G14)=0,50,IF(G14>-0.06,100,IF(G14>-0.15,50,0))) -> 100 | N14: =IF(COUNT(H14)=0,50,IF(H14>=0.6,100,IF(H14>=0.4,50,0))) -> 100 | O14: =IF(COUNT(I14)=0,50,IF(J14="proxy_vix",50,IF(I14<350,100,IF(I14<=450,50,0)))) -> 0 | P14: =IF(COUNT(K14)=0,50,IF(K14<20,100,IF(K14<=25,50,0))) -> 100 | S14: =$E14/$E13-1 -> -0.0021858628 | T14: =$K14/$K13-1 -> 0.082412914 | Y14: =IF(AX14>=70,"EASY",IF(AX14>40,"UNCERTAIN","HARD")) -> EASY | AA14: =IF($A14<200,"",AVERAGE($E5:$E14)/AVERAGE($E5:$E14)-1) | AB14: =LOOKUP($B14,07_L1政策步階!$A$4:$A$14,07_L1政策步階!$C$4:$C$14) -> 0 | AL14: =IF(ISNUMBER($AA14),IF($AA14>=0.005,100,IF($AA14>=-0.015,50,0)),"") | AM14: =IF(ISNUMBER($AB14),IF($AB14=1,100,IF($AB14=0,50,0)),"") -> 50 | AN14: =IF(ISNUMBER($AC14),IF($AC14>=0.001,100,IF($AC14>=-0.003,50,0)),"") | AO14: =IF(ISNUMBER($AD14),IF($AD14>=0.04,100,IF($AD14>=0,50,0)),"") | AP14: =IF(ISNUMBER($AE14),IF($AE14>=25,100,IF($AE14>=-75,50,0)),"") | AQ14: =IF(ISNUMBER($AF14),IF($AF14>0,100,IF($AF14>=-50,50,0)),"") | AR14: =IF(ISNUMBER($AG14),IF($AG14=1,100,IF($AG14=0,50,0)),"") | AS14: =IF(ISNUMBER($AH14),IF($AH14<0,100,IF($AH14<=20,50,0)),"") | AT14: =IF(ISNUMBER($AI14),IF($AI14<0.95,100,IF($AI14<=1,50,0)),"") | AU14: =IF(ISNUMBER($AJ14),IF($AJ14<30,0,IF($AJ14<40,50,IF($AJ14<=90,100,50))),"") | AV14: =IF(ISNUMBER($AK14),IF($AK14>-0.2,100,IF($AK14>=-0.4,50,0)),"") | AW14: =01_指標庫!$H$4*ISNUMBER($F14)+01_指標庫!$H$5*ISNUMBER($AA14)+01_指標庫!$H$6*ISNUMBER($G14)+01_指標庫!$H$7*ISNUMBER($H14)+01_指標庫!$H$8*ISNUMBER($AF14)+01_指標庫!$H$9*ISNUMBER($AG14)+01_指標庫!$H$10*ISNUMBER($AB14)+01_指標庫!$H$11*ISNUMBER($AC14)+01_指標庫!$H$12*ISNUMBER($AD14)+01_指標庫!$H$13*ISNUMBER($AE14)+01_指標庫!$H$14*ISNUMBER($I14)+01_指標庫!$H$15*ISNUMBER($AH14)+01_指標庫!$H$16*ISNUMBER($K14)+01_指標庫!$H$17*ISNUMBER($AI14)+01_指標庫!$H$18*ISNUMBER($AJ14)+01_指標庫!$H$19*ISNUMBER($AK14)+01_指標庫!$H$20*ISNUMBER($BB14)+01_指標庫!$H$21*ISNUMBER($BC14) -> 49 | AX14: =IF(AW14=0,50,ROUND((01_指標庫!$H$4*IF(ISNUMBER($F14),L14,0)+01_指標庫!$H$5*IF(ISNUMBER($AA14),AL14,0)+01_指標庫!$H$6*IF(ISNUMBER($G14),M14,0)+01_指標庫!$H$7*IF(ISNUMBER($H14),N14,0)+01_指標庫!$H$8*IF(ISNUMBER($AF14),AQ14,0)+01_指標庫!$H$9*IF(ISNUMBER($AG14),AR14,0)+01_指標庫!$H$10*IF(ISNUMBER($AB14),AM14,0)+01_指標庫!$H$11*IF(ISNUMBER($AC14),AN14,0)+01_指標庫!$H$12*IF(ISNUMBER($AD14),AO14,0)+01_指標庫!$H$13*IF(ISNUMBER($AE14),AP14,0)+01_指標庫!$H$14*IF(ISNUMBER($I14),O14,0)+01_指標庫!$H$15*IF(ISNUMBER($AH14),AS14,0)+01_指標庫!$H$16*IF(ISNUMBER($K14),P14,0)+01_指標庫!$H$17*IF(ISNUMBER($AI14),AT14,0)+01_指標庫!$H$18*IF(ISNUMBER($AJ14),AU14,0)+01_指標庫!$H$19*IF(ISNUMBER($AK14),AV14,0)+01_指標庫!$H$20*IF(ISNUMBER($BB14),BB14,0)+01_指標庫!$H$21*IF(ISNUMBER($BC14),BC14,0))/AW14,1)) -> 72.4 | BA14: =AVERAGE($E10:$E14)/AVERAGE($E5:$E14)-1 -> 0.0064011824 | BB14: =IF(ISNUMBER($BA14),IF(OR($S14<=-0.03,$BA14<-0.003),0,IF(OR($S14<=-0.02,$BA14<0.01),50,100)),"") -> 50 | BC14: =IF(OR(COUNT($AZ14)=0,COUNT($AZ13)=0),"",IF(OR($AY14/$AZ13-1<=-0.03,$AZ14/$AZ13-1<=-0.045,IF(COUNT($AZ5:$AZ14)=10,AVERAGE($AZ10:$AZ14)/AVERAGE($AZ5:$AZ14)-1<-0.01,FALSE())),0,IF(OR($AZ14/$AZ13-1<=-0.02,IF(COUNT($AZ5:$AZ14)=10,AVERAGE($AZ10:$AZ14)/AVERAGE($AZ5:$AZ14)-1<0.005,FALSE())),50,100)))
A15: 11 | B15: 42573 | C15: 2016 | D15: 五 | E15: 4666.07 | F15: 0.051575 | G15: -0.011227 | H15: 0.8571 | I15: 539 | J15: real | K15: 12.02 | L15: =IF(COUNT(F15)=0,50,IF(F15>=0,100,IF(F15>=-0.02,50,0))) -> 100 | M15: =IF(COUNT(G15)=0,50,IF(G15>-0.06,100,IF(G15>-0.15,50,0))) -> 100 | N15: =IF(COUNT(H15)=0,50,IF(H15>=0.6,100,IF(H15>=0.4,50,0))) -> 100 | O15: =IF(COUNT(I15)=0,50,IF(J15="proxy_vix",50,IF(I15<350,100,IF(I15<=450,50,0)))) -> 0 | P15: =IF(COUNT(K15)=0,50,IF(K15<20,100,IF(K15<=25,50,0))) -> 100 | S15: =$E15/$E14-1 -> 0.0040994013 | T15: =$K15/$K14-1 -> -0.056514914 | Y15: =IF(AX15>=70,"EASY",IF(AX15>40,"UNCERTAIN","HARD")) -> EASY | AA15: =IF($A15<200,"",AVERAGE($E5:$E15)/AVERAGE($E5:$E15)-1) | AB15: =LOOKUP($B15,07_L1政策步階!$A$4:$A$14,07_L1政策步階!$C$4:$C$14) -> 0 | AL15: =IF(ISNUMBER($AA15),IF($AA15>=0.005,100,IF($AA15>=-0.015,50,0)),"") | AM15: =IF(ISNUMBER($AB15),IF($AB15=1,100,IF($AB15=0,50,0)),"") -> 50 | AN15: =IF(ISNUMBER($AC15),IF($AC15>=0.001,100,IF($AC15>=-0.003,50,0)),"") | AO15: =IF(ISNUMBER($AD15),IF($AD15>=0.04,100,IF($AD15>=0,50,0)),"") | AP15: =IF(ISNUMBER($AE15),IF($AE15>=25,100,IF($AE15>=-75,50,0)),"") | AQ15: =IF(ISNUMBER($AF15),IF($AF15>0,100,IF($AF15>=-50,50,0)),"") | AR15: =IF(ISNUMBER($AG15),IF($AG15=1,100,IF($AG15=0,50,0)),"") | AS15: =IF(ISNUMBER($AH15),IF($AH15<0,100,IF($AH15<=20,50,0)),"") | AT15: =IF(ISNUMBER($AI15),IF($AI15<0.95,100,IF($AI15<=1,50,0)),"") | AU15: =IF(ISNUMBER($AJ15),IF($AJ15<30,0,IF($AJ15<40,50,IF($AJ15<=90,100,50))),"") | AV15: =IF(ISNUMBER($AK15),IF($AK15>-0.2,100,IF($AK15>=-0.4,50,0)),"") | AW15: =01_指標庫!$H$4*ISNUMBER($F15)+01_指標庫!$H$5*ISNUMBER($AA15)+01_指標庫!$H$6*ISNUMBER($G15)+01_指標庫!$H$7*ISNUMBER($H15)+01_指標庫!$H$8*ISNUMBER($AF15)+01_指標庫!$H$9*ISNUMBER($AG15)+01_指標庫!$H$10*ISNUMBER($AB15)+01_指標庫!$H$11*ISNUMBER($AC15)+01_指標庫!$H$12*ISNUMBER($AD15)+01_指標庫!$H$13*ISNUMBER($AE15)+01_指標庫!$H$14*ISNUMBER($I15)+01_指標庫!$H$15*ISNUMBER($AH15)+01_指標庫!$H$16*ISNUMBER($K15)+01_指標庫!$H$17*ISNUMBER($AI15)+01_指標庫!$H$18*ISNUMBER($AJ15)+01_指標庫!$H$19*ISNUMBER($AK15)+01_指標庫!$H$20*ISNUMBER($BB15)+01_指標庫!$H$21*ISNUMBER($BC15) -> 49 | AX15: =IF(AW15=0,50,ROUND((01_指標庫!$H$4*IF(ISNUMBER($F15),L15,0)+01_指標庫!$H$5*IF(ISNUMBER($AA15),AL15,0)+01_指標庫!$H$6*IF(ISNUMBER($G15),M15,0)+01_指標庫!$H$7*IF(ISNUMBER($H15),N15,0)+01_指標庫!$H$8*IF(ISNUMBER($AF15),AQ15,0)+01_指標庫!$H$9*IF(ISNUMBER($AG15),AR15,0)+01_指標庫!$H$10*IF(ISNUMBER($AB15),AM15,0)+01_指標庫!$H$11*IF(ISNUMBER($AC15),AN15,0)+01_指標庫!$H$12*IF(ISNUMBER($AD15),AO15,0)+01_指標庫!$H$13*IF(ISNUMBER($AE15),AP15,0)+01_指標庫!$H$14*IF(ISNUMBER($I15),O15,0)+01_指標庫!$H$15*IF(ISNUMBER($AH15),AS15,0)+01_指標庫!$H$16*IF(ISNUMBER($K15),P15,0)+01_指標庫!$H$17*IF(ISNUMBER($AI15),AT15,0)+01_指標庫!$H$18*IF(ISNUMBER($AJ15),AU15,0)+01_指標庫!$H$19*IF(ISNUMBER($AK15),AV15,0)+01_指標庫!$H$20*IF(ISNUMBER($BB15),BB15,0)+01_指標庫!$H$21*IF(ISNUMBER($BC15),BC15,0))/AW15,1)) -> 72.4 | BA15: =AVERAGE($E11:$E15)/AVERAGE($E6:$E15)-1 -> 0.0067025973 | BB15: =IF(ISNUMBER($BA15),IF(OR($S15<=-0.03,$BA15<-0.003),0,IF(OR($S15<=-0.02,$BA15<0.01),50,100)),"") -> 50 | BC15: =IF(OR(COUNT($AZ15)=0,COUNT($AZ14)=0),"",IF(OR($AY15/$AZ14-1<=-0.03,$AZ15/$AZ14-1<=-0.045,IF(COUNT($AZ6:$AZ15)=10,AVERAGE($AZ11:$AZ15)/AVERAGE($AZ6:$AZ15)-1<-0.01,FALSE())),0,IF(OR($AZ15/$AZ14-1<=-0.02,IF(COUNT($AZ6:$AZ15)=10,AVERAGE($AZ11:$AZ15)/AVERAGE($AZ6:$AZ15)-1<0.005,FALSE())),50,100)))
A16: 12 | B16: 42576 | C16: 2016 | D16: 一 | E16: 4665.93 | F16: 0.051149 | G16: -0.011256 | H16: 0.8571 | I16: 539 | J16: real | K16: 12.87 | L16: =IF(COUNT(F16)=0,50,IF(F16>=0,100,IF(F16>=-0.02,50,0))) -> 100 | M16: =IF(COUNT(G16)=0,50,IF(G16>-0.06,100,IF(G16>-0.15,50,0))) -> 100 | N16: =IF(COUNT(H16)=0,50,IF(H16>=0.6,100,IF(H16>=0.4,50,0))) -> 100 | O16: =IF(COUNT(I16)=0,50,IF(J16="proxy_vix",50,IF(I16<350,100,IF(I16<=450,50,0)))) -> 0 | P16: =IF(COUNT(K16)=0,50,IF(K16<20,100,IF(K16<=25,50,0))) -> 100 | S16: =$E16/$E15-1 -> -3.0003836e-05 | T16: =$K16/$K15-1 -> 0.070715474 | Y16: =IF(AX16>=70,"EASY",IF(AX16>40,"UNCERTAIN","HARD")) -> EASY | AA16: =IF($A16<200,"",AVERAGE($E5:$E16)/AVERAGE($E5:$E16)-1) | AB16: =LOOKUP($B16,07_L1政策步階!$A$4:$A$14,07_L1政策步階!$C$4:$C$14) -> 0 | AL16: =IF(ISNUMBER($AA16),IF($AA16>=0.005,100,IF($AA16>=-0.015,50,0)),"") | AM16: =IF(ISNUMBER($AB16),IF($AB16=1,100,IF($AB16=0,50,0)),"") -> 50 | AN16: =IF(ISNUMBER($AC16),IF($AC16>=0.001,100,IF($AC16>=-0.003,50,0)),"") | AO16: =IF(ISNUMBER($AD16),IF($AD16>=0.04,100,IF($AD16>=0,50,0)),"") | AP16: =IF(ISNUMBER($AE16),IF($AE16>=25,100,IF($AE16>=-75,50,0)),"") | AQ16: =IF(ISNUMBER($AF16),IF($AF16>0,100,IF($AF16>=-50,50,0)),"") | AR16: =IF(ISNUMBER($AG16),IF($AG16=1,100,IF($AG16=0,50,0)),"") | AS16: =IF(ISNUMBER($AH16),IF($AH16<0,100,IF($AH16<=20,50,0)),"") | AT16: =IF(ISNUMBER($AI16),IF($AI16<0.95,100,IF($AI16<=1,50,0)),"") | AU16: =IF(ISNUMBER($AJ16),IF($AJ16<30,0,IF($AJ16<40,50,IF($AJ16<=90,100,50))),"") | AV16: =IF(ISNUMBER($AK16),IF($AK16>-0.2,100,IF($AK16>=-0.4,50,0)),"") | AW16: =01_指標庫!$H$4*ISNUMBER($F16)+01_指標庫!$H$5*ISNUMBER($AA16)+01_指標庫!$H$6*ISNUMBER($G16)+01_指標庫!$H$7*ISNUMBER($H16)+01_指標庫!$H$8*ISNUMBER($AF16)+01_指標庫!$H$9*ISNUMBER($AG16)+01_指標庫!$H$10*ISNUMBER($AB16)+01_指標庫!$H$11*ISNUMBER($AC16)+01_指標庫!$H$12*ISNUMBER($AD16)+01_指標庫!$H$13*ISNUMBER($AE16)+01_指標庫!$H$14*ISNUMBER($I16)+01_指標庫!$H$15*ISNUMBER($AH16)+01_指標庫!$H$16*ISNUMBER($K16)+01_指標庫!$H$17*ISNUMBER($AI16)+01_指標庫!$H$18*ISNUMBER($AJ16)+01_指標庫!$H$19*ISNUMBER($AK16)+01_指標庫!$H$20*ISNUMBER($BB16)+01_指標庫!$H$21*ISNUMBER($BC16) -> 49 | AX16: =IF(AW16=0,50,ROUND((01_指標庫!$H$4*IF(ISNUMBER($F16),L16,0)+01_指標庫!$H$5*IF(ISNUMBER($AA16),AL16,0)+01_指標庫!$H$6*IF(ISNUMBER($G16),M16,0)+01_指標庫!$H$7*IF(ISNUMBER($H16),N16,0)+01_指標庫!$H$8*IF(ISNUMBER($AF16),AQ16,0)+01_指標庫!$H$9*IF(ISNUMBER($AG16),AR16,0)+01_指標庫!$H$10*IF(ISNUMBER($AB16),AM16,0)+01_指標庫!$H$11*IF(ISNUMBER($AC16),AN16,0)+01_指標庫!$H$12*IF(ISNUMBER($AD16),AO16,0)+01_指標庫!$H$13*IF(ISNUMBER($AE16),AP16,0)+01_指標庫!$H$14*IF(ISNUMBER($I16),O16,0)+01_指標庫!$H$15*IF(ISNUMBER($AH16),AS16,0)+01_指標庫!$H$16*IF(ISNUMBER($K16),P16,0)+01_指標庫!$H$17*IF(ISNUMBER($AI16),AT16,0)+01_指標庫!$H$18*IF(ISNUMBER($AJ16),AU16,0)+01_指標庫!$H$19*IF(ISNUMBER($AK16),AV16,0)+01_指標庫!$H$20*IF(ISNUMBER($BB16),BB16,0)+01_指標庫!$H$21*IF(ISNUMBER($BC16),BC16,0))/AW16,1)) -> 72.4 | BA16: =AVERAGE($E12:$E16)/AVERAGE($E7:$E16)-1 -> 0.0062811655 | BB16: =IF(ISNUMBER($BA16),IF(OR($S16<=-0.03,$BA16<-0.003),0,IF(OR($S16<=-0.02,$BA16<0.01),50,100)),"") -> 50 | BC16: =IF(OR(COUNT($AZ16)=0,COUNT($AZ15)=0),"",IF(OR($AY16/$AZ15-1<=-0.03,$AZ16/$AZ15-1<=-0.045,IF(COUNT($AZ7:$AZ16)=10,AVERAGE($AZ12:$AZ16)/AVERAGE($AZ7:$AZ16)-1<-0.01,FALSE())),0,IF(OR($AZ16/$AZ15-1<=-0.02,IF(COUNT($AZ7:$AZ16)=10,AVERAGE($AZ12:$AZ16)/AVERAGE($AZ7:$AZ16)-1<0.005,FALSE())),50,100)))
A17: 13 | B17: 42577 | C17: 2016 | D17: 二 | E17: 4672.11 | F17: 0.05216 | G17: -0.009947 | H17: 0.8776 | I17: 545 | J17: real | K17: 13.05 | L17: =IF(COUNT(F17)=0,50,IF(F17>=0,100,IF(F17>=-0.02,50,0))) -> 100 | M17: =IF(COUNT(G17)=0,50,IF(G17>-0.06,100,IF(G17>-0.15,50,0))) -> 100 | N17: =IF(COUNT(H17)=0,50,IF(H17>=0.6,100,IF(H17>=0.4,50,0))) -> 100 | O17: =IF(COUNT(I17)=0,50,IF(J17="proxy_vix",50,IF(I17<350,100,IF(I17<=450,50,0)))) -> 0 | P17: =IF(COUNT(K17)=0,50,IF(K17<20,100,IF(K17<=25,50,0))) -> 100 | S17: =$E17/$E16-1 -> 0.0013244948 | T17: =$K17/$K16-1 -> 0.013986014 | Y17: =IF(AX17>=70,"EASY",IF(AX17>40,"UNCERTAIN","HARD")) -> EASY | AA17: =IF($A17<200,"",AVERAGE($E5:$E17)/AVERAGE($E5:$E17)-1) | AB17: =LOOKUP($B17,07_L1政策步階!$A$4:$A$14,07_L1政策步階!$C$4:$C$14) -> 0 | AL17: =IF(ISNUMBER($AA17),IF($AA17>=0.005,100,IF($AA17>=-0.015,50,0)),"") | AM17: =IF(ISNUMBER($AB17),IF($AB17=1,100,IF($AB17=0,50,0)),"") -> 50 | AN17: =IF(ISNUMBER($AC17),IF($AC17>=0.001,100,IF($AC17>=-0.003,50,0)),"") | AO17: =IF(ISNUMBER($AD17),IF($AD17>=0.04,100,IF($AD17>=0,50,0)),"") | AP17: =IF(ISNUMBER($AE17),IF($AE17>=25,100,IF($AE17>=-75,50,0)),"") | AQ17: =IF(ISNUMBER($AF17),IF($AF17>0,100,IF($AF17>=-50,50,0)),"") | AR17: =IF(ISNUMBER($AG17),IF($AG17=1,100,IF($AG17=0,50,0)),"") | AS17: =IF(ISNUMBER($AH17),IF($AH17<0,100,IF($AH17<=20,50,0)),"") | AT17: =IF(ISNUMBER($AI17),IF($AI17<0.95,100,IF($AI17<=1,50,0)),"") | AU17: =IF(ISNUMBER($AJ17),IF($AJ17<30,0,IF($AJ17<40,50,IF($AJ17<=90,100,50))),"") | AV17: =IF(ISNUMBER($AK17),IF($AK17>-0.2,100,IF($AK17>=-0.4,50,0)),"") | AW17: =01_指標庫!$H$4*ISNUMBER($F17)+01_指標庫!$H$5*ISNUMBER($AA17)+01_指標庫!$H$6*ISNUMBER($G17)+01_指標庫!$H$7*ISNUMBER($H17)+01_指標庫!$H$8*ISNUMBER($AF17)+01_指標庫!$H$9*ISNUMBER($AG17)+01_指標庫!$H$10*ISNUMBER($AB17)+01_指標庫!$H$11*ISNUMBER($AC17)+01_指標庫!$H$12*ISNUMBER($AD17)+01_指標庫!$H$13*ISNUMBER($AE17)+01_指標庫!$H$14*ISNUMBER($I17)+01_指標庫!$H$15*ISNUMBER($AH17)+01_指標庫!$H$16*ISNUMBER($K17)+01_指標庫!$H$17*ISNUMBER($AI17)+01_指標庫!$H$18*ISNUMBER($AJ17)+01_指標庫!$H$19*ISNUMBER($AK17)+01_指標庫!$H$20*ISNUMBER($BB17)+01_指標庫!$H$21*ISNUMBER($BC17) -> 49 | AX17: =IF(AW17=0,50,ROUND((01_指標庫!$H$4*IF(ISNUMBER($F17),L17,0)+01_指標庫!$H$5*IF(ISNUMBER($AA17),AL17,0)+01_指標庫!$H$6*IF(ISNUMBER($G17),M17,0)+01_指標庫!$H$7*IF(ISNUMBER($H17),N17,0)+01_指標庫!$H$8*IF(ISNUMBER($AF17),AQ17,0)+01_指標庫!$H$9*IF(ISNUMBER($AG17),AR17,0)+01_指標庫!$H$10*IF(ISNUMBER($AB17),AM17,0)+01_指標庫!$H$11*IF(ISNUMBER($AC17),AN17,0)+01_指標庫!$H$12*IF(ISNUMBER($AD17),AO17,0)+01_指標庫!$H$13*IF(ISNUMBER($AE17),AP17,0)+01_指標庫!$H$14*IF(ISNUMBER($I17),O17,0)+01_指標庫!$H$15*IF(ISNUMBER($AH17),AS17,0)+01_指標庫!$H$16*IF(ISNUMBER($K17),P17,0)+01_指標庫!$H$17*IF(ISNUMBER($AI17),AT17,0)+01_指標庫!$H$18*IF(ISNUMBER($AJ17),AU17,0)+01_指標庫!$H$19*IF(ISNUMBER($AK17),AV17,0)+01_指標庫!$H$20*IF(ISNUMBER($BB17),BB17,0)+01_指標庫!$H$21*IF(ISNUMBER($BC17),BC17,0))/AW17,1)) -> 72.4 | BA17: =AVERAGE($E13:$E17)/AVERAGE($E8:$E17)-1 -> 0.007200857 | BB17: =IF(ISNUMBER($BA17),IF(OR($S17<=-0.03,$BA17<-0.003),0,IF(OR($S17<=-0.02,$BA17<0.01),50,100)),"") -> 50 | BC17: =IF(OR(COUNT($AZ17)=0,COUNT($AZ16)=0),"",IF(OR($AY17/$AZ16-1<=-0.03,$AZ17/$AZ16-1<=-0.045,IF(COUNT($AZ8:$AZ17)=10,AVERAGE($AZ13:$AZ17)/AVERAGE($AZ8:$AZ17)-1<-0.01,FALSE())),0,IF(OR($AZ17/$AZ16-1<=-0.02,IF(COUNT($AZ8:$AZ17)=10,AVERAGE($AZ13:$AZ17)/AVERAGE($AZ8:$AZ17)-1<0.005,FALSE())),50,100)))
A18: 14 | B18: 42578 | C18: 2016 | D18: 三 | E18: 4702.88 | F18: 0.058692 | G18: -0.003427 | H18: 0.8571 | I18: 551 | J18: real | K18: 12.83 | L18: =IF(COUNT(F18)=0,50,IF(F18>=0,100,IF(F18>=-0.02,50,0))) -> 100 | M18: =IF(COUNT(G18)=0,50,IF(G18>-0.06,100,IF(G18>-0.15,50,0))) -> 100 | N18: =IF(COUNT(H18)=0,50,IF(H18>=0.6,100,IF(H18>=0.4,50,0))) -> 100 | O18: =IF(COUNT(I18)=0,50,IF(J18="proxy_vix",50,IF(I18<350,100,IF(I18<=450,50,0)))) -> 0 | P18: =IF(COUNT(K18)=0,50,IF(K18<20,100,IF(K18<=25,50,0))) -> 100 | S18: =$E18/$E17-1 -> 0.0065858895 | T18: =$K18/$K17-1 -> -0.016858238 | Y18: =IF(AX18>=70,"EASY",IF(AX18>40,"UNCERTAIN","HARD")) -> EASY | AA18: =IF($A18<200,"",AVERAGE($E5:$E18)/AVERAGE($E5:$E18)-1) | AB18: =LOOKUP($B18,07_L1政策步階!$A$4:$A$14,07_L1政策步階!$C$4:$C$14) -> 0 | AL18: =IF(ISNUMBER($AA18),IF($AA18>=0.005,100,IF($AA18>=-0.015,50,0)),"") | AM18: =IF(ISNUMBER($AB18),IF($AB18=1,100,IF($AB18=0,50,0)),"") -> 50 | AN18: =IF(ISNUMBER($AC18),IF($AC18>=0.001,100,IF($AC18>=-0.003,50,0)),"") | AO18: =IF(ISNUMBER($AD18),IF($AD18>=0.04,100,IF($AD18>=0,50,0)),"") | AP18: =IF(ISNUMBER($AE18),IF($AE18>=25,100,IF($AE18>=-75,50,0)),"") | AQ18: =IF(ISNUMBER($AF18),IF($AF18>0,100,IF($AF18>=-50,50,0)),"") | AR18: =IF(ISNUMBER($AG18),IF($AG18=1,100,IF($AG18=0,50,0)),"") | AS18: =IF(ISNUMBER($AH18),IF($AH18<0,100,IF($AH18<=20,50,0)),"") | AT18: =IF(ISNUMBER($AI18),IF($AI18<0.95,100,IF($AI18<=1,50,0)),"") | AU18: =IF(ISNUMBER($AJ18),IF($AJ18<30,0,IF($AJ18<40,50,IF($AJ18<=90,100,50))),"") | AV18: =IF(ISNUMBER($AK18),IF($AK18>-0.2,100,IF($AK18>=-0.4,50,0)),"") | AW18: =01_指標庫!$H$4*ISNUMBER($F18)+01_指標庫!$H$5*ISNUMBER($AA18)+01_指標庫!$H$6*ISNUMBER($G18)+01_指標庫!$H$7*ISNUMBER($H18)+01_指標庫!$H$8*ISNUMBER($AF18)+01_指標庫!$H$9*ISNUMBER($AG18)+01_指標庫!$H$10*ISNUMBER($AB18)+01_指標庫!$H$11*ISNUMBER($AC18)+01_指標庫!$H$12*ISNUMBER($AD18)+01_指標庫!$H$13*ISNUMBER($AE18)+01_指標庫!$H$14*ISNUMBER($I18)+01_指標庫!$H$15*ISNUMBER($AH18)+01_指標庫!$H$16*ISNUMBER($K18)+01_指標庫!$H$17*ISNUMBER($AI18)+01_指標庫!$H$18*ISNUMBER($AJ18)+01_指標庫!$H$19*ISNUMBER($AK18)+01_指標庫!$H$20*ISNUMBER($BB18)+01_指標庫!$H$21*ISNUMBER($BC18) -> 49 | AX18: =IF(AW18=0,50,ROUND((01_指標庫!$H$4*IF(ISNUMBER($F18),L18,0)+01_指標庫!$H$5*IF(ISNUMBER($AA18),AL18,0)+01_指標庫!$H$6*IF(ISNUMBER($G18),M18,0)+01_指標庫!$H$7*IF(ISNUMBER($H18),N18,0)+01_指標庫!$H$8*IF(ISNUMBER($AF18),AQ18,0)+01_指標庫!$H$9*IF(ISNUMBER($AG18),AR18,0)+01_指標庫!$H$10*IF(ISNUMBER($AB18),AM18,0)+01_指標庫!$H$11*IF(ISNUMBER($AC18),AN18,0)+01_指標庫!$H$12*IF(ISNUMBER($AD18),AO18,0)+01_指標庫!$H$13*IF(ISNUMBER($AE18),AP18,0)+01_指標庫!$H$14*IF(ISNUMBER($I18),O18,0)+01_指標庫!$H$15*IF(ISNUMBER($AH18),AS18,0)+01_指標庫!$H$16*IF(ISNUMBER($K18),P18,0)+01_指標庫!$H$17*IF(ISNUMBER($AI18),AT18,0)+01_指標庫!$H$18*IF(ISNUMBER($AJ18),AU18,0)+01_指標庫!$H$19*IF(ISNUMBER($AK18),AV18,0)+01_指標庫!$H$20*IF(ISNUMBER($BB18),BB18,0)+01_指標庫!$H$21*IF(ISNUMBER($BC18),BC18,0))/AW18,1)) -> 72.4 | BA18: =AVERAGE($E14:$E18)/AVERAGE($E9:$E18)-1 -> 0.006194032 | BB18: =IF(ISNUMBER($BA18),IF(OR($S18<=-0.03,$BA18<-0.003),0,IF(OR($S18<=-0.02,$BA18<0.01),50,100)),"") -> 50 | BC18: =IF(OR(COUNT($AZ18)=0,COUNT($AZ17)=0),"",IF(OR($AY18/$AZ17-1<=-0.03,$AZ18/$AZ17-1<=-0.045,IF(COUNT($AZ9:$AZ18)=10,AVERAGE($AZ14:$AZ18)/AVERAGE($AZ9:$AZ18)-1<-0.01,FALSE())),0,IF(OR($AZ18/$AZ17-1<=-0.02,IF(COUNT($AZ9:$AZ18)=10,AVERAGE($AZ14:$AZ18)/AVERAGE($AZ9:$AZ18)-1<0.005,FALSE())),50,100)))
A19: 15 | B19: 42579 | C19: 2016 | D19: 四 | E19: 4721.41 | F19: 0.062459 | G19: 0 | H19: 0.8776 | I19: 554 | J19: real | K19: 12.72 | L19: =IF(COUNT(F19)=0,50,IF(F19>=0,100,IF(F19>=-0.02,50,0))) -> 100 | M19: =IF(COUNT(G19)=0,50,IF(G19>-0.06,100,IF(G19>-0.15,50,0))) -> 100 | N19: =IF(COUNT(H19)=0,50,IF(H19>=0.6,100,IF(H19>=0.4,50,0))) -> 100 | O19: =IF(COUNT(I19)=0,50,IF(J19="proxy_vix",50,IF(I19<350,100,IF(I19<=450,50,0)))) -> 0 | P19: =IF(COUNT(K19)=0,50,IF(K19<20,100,IF(K19<=25,50,0))) -> 100 | S19: =$E19/$E18-1 -> 0.0039401388 | T19: =$K19/$K18-1 -> -0.0085736555 | Y19: =IF(AX19>=70,"EASY",IF(AX19>40,"UNCERTAIN","HARD")) -> EASY | AA19: =IF($A19<200,"",AVERAGE($E5:$E19)/AVERAGE($E5:$E19)-1) | AB19: =LOOKUP($B19,07_L1政策步階!$A$4:$A$14,07_L1政策步階!$C$4:$C$14) -> 0 | AL19: =IF(ISNUMBER($AA19),IF($AA19>=0.005,100,IF($AA19>=-0.015,50,0)),"") | AM19: =IF(ISNUMBER($AB19),IF($AB19=1,100,IF($AB19=0,50,0)),"") -> 50 | AN19: =IF(ISNUMBER($AC19),IF($AC19>=0.001,100,IF($AC19>=-0.003,50,0)),"") | AO19: =IF(ISNUMBER($AD19),IF($AD19>=0.04,100,IF($AD19>=0,50,0)),"") | AP19: =IF(ISNUMBER($AE19),IF($AE19>=25,100,IF($AE19>=-75,50,0)),"") | AQ19: =IF(ISNUMBER($AF19),IF($AF19>0,100,IF($AF19>=-50,50,0)),"") | AR19: =IF(ISNUMBER($AG19),IF($AG19=1,100,IF($AG19=0,50,0)),"") | AS19: =IF(ISNUMBER($AH19),IF($AH19<0,100,IF($AH19<=20,50,0)),"") | AT19: =IF(ISNUMBER($AI19),IF($AI19<0.95,100,IF($AI19<=1,50,0)),"") | AU19: =IF(ISNUMBER($AJ19),IF($AJ19<30,0,IF($AJ19<40,50,IF($AJ19<=90,100,50))),"") | AV19: =IF(ISNUMBER($AK19),IF($AK19>-0.2,100,IF($AK19>=-0.4,50,0)),"") | AW19: =01_指標庫!$H$4*ISNUMBER($F19)+01_指標庫!$H$5*ISNUMBER($AA19)+01_指標庫!$H$6*ISNUMBER($G19)+01_指標庫!$H$7*ISNUMBER($H19)+01_指標庫!$H$8*ISNUMBER($AF19)+01_指標庫!$H$9*ISNUMBER($AG19)+01_指標庫!$H$10*ISNUMBER($AB19)+01_指標庫!$H$11*ISNUMBER($AC19)+01_指標庫!$H$12*ISNUMBER($AD19)+01_指標庫!$H$13*ISNUMBER($AE19)+01_指標庫!$H$14*ISNUMBER($I19)+01_指標庫!$H$15*ISNUMBER($AH19)+01_指標庫!$H$16*ISNUMBER($K19)+01_指標庫!$H$17*ISNUMBER($AI19)+01_指標庫!$H$18*ISNUMBER($AJ19)+01_指標庫!$H$19*ISNUMBER($AK19)+01_指標庫!$H$20*ISNUMBER($BB19)+01_指標庫!$H$21*ISNUMBER($BC19) -> 49 | AX19: =IF(AW19=0,50,ROUND((01_指標庫!$H$4*IF(ISNUMBER($F19),L19,0)+01_指標庫!$H$5*IF(ISNUMBER($AA19),AL19,0)+01_指標庫!$H$6*IF(ISNUMBER($G19),M19,0)+01_指標庫!$H$7*IF(ISNUMBER($H19),N19,0)+01_指標庫!$H$8*IF(ISNUMBER($AF19),AQ19,0)+01_指標庫!$H$9*IF(ISNUMBER($AG19),AR19,0)+01_指標庫!$H$10*IF(ISNUMBER($AB19),AM19,0)+01_指標庫!$H$11*IF(ISNUMBER($AC19),AN19,0)+01_指標庫!$H$12*IF(ISNUMBER($AD19),AO19,0)+01_指標庫!$H$13*IF(ISNUMBER($AE19),AP19,0)+01_指標庫!$H$14*IF(ISNUMBER($I19),O19,0)+01_指標庫!$H$15*IF(ISNUMBER($AH19),AS19,0)+01_指標庫!$H$16*IF(ISNUMBER($K19),P19,0)+01_指標庫!$H$17*IF(ISNUMBER($AI19),AT19,0)+01_指標庫!$H$18*IF(ISNUMBER($AJ19),AU19,0)+01_指標庫!$H$19*IF(ISNUMBER($AK19),AV19,0)+01_指標庫!$H$20*IF(ISNUMBER($BB19),BB19,0)+01_指標庫!$H$21*IF(ISNUMBER($BC19),BC19,0))/AW19,1)) -> 72.4 | BA19: =AVERAGE($E15:$E19)/AVERAGE($E10:$E19)-1 -> 0.0066900259 | BB19: =IF(ISNUMBER($BA19),IF(OR($S19<=-0.03,$BA19<-0.003),0,IF(OR($S19<=-0.02,$BA19<0.01),50,100)),"") -> 50 | BC19: =IF(OR(COUNT($AZ19)=0,COUNT($AZ18)=0),"",IF(OR($AY19/$AZ18-1<=-0.03,$AZ19/$AZ18-1<=-0.045,IF(COUNT($AZ10:$AZ19)=10,AVERAGE($AZ15:$AZ19)/AVERAGE($AZ10:$AZ19)-1<-0.01,FALSE())),0,IF(OR($AZ19/$AZ18-1<=-0.02,IF(COUNT($AZ10:$AZ19)=10,AVERAGE($AZ15:$AZ19)/AVERAGE($AZ10:$AZ19)-1<0.005,FALSE())),50,100)))
A20: 16 | B20: 42580 | C20: 2016 | D20: 五 | E20: 4730.23 | F20: 0.063992 | G20: 0 | H20: 0.8776 | I20: 561 | J20: real | K20: 11.87 | L20: =IF(COUNT(F20)=0,50,IF(F20>=0,100,IF(F20>=-0.02,50,0))) -> 100 | M20: =IF(COUNT(G20)=0,50,IF(G20>-0.06,100,IF(G20>-0.15,50,0))) -> 100 | N20: =IF(COUNT(H20)=0,50,IF(H20>=0.6,100,IF(H20>=0.4,50,0))) -> 100 | O20: =IF(COUNT(I20)=0,50,IF(J20="proxy_vix",50,IF(I20<350,100,IF(I20<=450,50,0)))) -> 0 | P20: =IF(COUNT(K20)=0,50,IF(K20<20,100,IF(K20<=25,50,0))) -> 100 | S20: =$E20/$E19-1 -> 0.001868086 | T20: =$K20/$K19-1 -> -0.066823899 | Y20: =IF(AX20>=70,"EASY",IF(AX20>40,"UNCERTAIN","HARD")) -> EASY | AA20: =IF($A20<200,"",AVERAGE($E5:$E20)/AVERAGE($E5:$E20)-1) | AB20: =LOOKUP($B20,07_L1政策步階!$A$4:$A$14,07_L1政策步階!$C$4:$C$14) -> 0 | AL20: =IF(ISNUMBER($AA20),IF($AA20>=0.005,100,IF($AA20>=-0.015,50,0)),"") | AM20: =IF(ISNUMBER($AB20),IF($AB20=1,100,IF($AB20=0,50,0)),"") -> 50 | AN20: =IF(ISNUMBER($AC20),IF($AC20>=0.001,100,IF($AC20>=-0.003,50,0)),"") | AO20: =IF(ISNUMBER($AD20),IF($AD20>=0.04,100,IF($AD20>=0,50,0)),"") | AP20: =IF(ISNUMBER($AE20),IF($AE20>=25,100,IF($AE20>=-75,50,0)),"") | AQ20: =IF(ISNUMBER($AF20),IF($AF20>0,100,IF($AF20>=-50,50,0)),"") | AR20: =IF(ISNUMBER($AG20),IF($AG20=1,100,IF($AG20=0,50,0)),"") | AS20: =IF(ISNUMBER($AH20),IF($AH20<0,100,IF($AH20<=20,50,0)),"") | AT20: =IF(ISNUMBER($AI20),IF($AI20<0.95,100,IF($AI20<=1,50,0)),"") | AU20: =IF(ISNUMBER($AJ20),IF($AJ20<30,0,IF($AJ20<40,50,IF($AJ20<=90,100,50))),"") | AV20: =IF(ISNUMBER($AK20),IF($AK20>-0.2,100,IF($AK20>=-0.4,50,0)),"") | AW20: =01_指標庫!$H$4*ISNUMBER($F20)+01_指標庫!$H$5*ISNUMBER($AA20)+01_指標庫!$H$6*ISNUMBER($G20)+01_指標庫!$H$7*ISNUMBER($H20)+01_指標庫!$H$8*ISNUMBER($AF20)+01_指標庫!$H$9*ISNUMBER($AG20)+01_指標庫!$H$10*ISNUMBER($AB20)+01_指標庫!$H$11*ISNUMBER($AC20)+01_指標庫!$H$12*ISNUMBER($AD20)+01_指標庫!$H$13*ISNUMBER($AE20)+01_指標庫!$H$14*ISNUMBER($I20)+01_指標庫!$H$15*ISNUMBER($AH20)+01_指標庫!$H$16*ISNUMBER($K20)+01_指標庫!$H$17*ISNUMBER($AI20)+01_指標庫!$H$18*ISNUMBER($AJ20)+01_指標庫!$H$19*ISNUMBER($AK20)+01_指標庫!$H$20*ISNUMBER($BB20)+01_指標庫!$H$21*ISNUMBER($BC20) -> 49 | AX20: =IF(AW20=0,50,ROUND((01_指標庫!$H$4*IF(ISNUMBER($F20),L20,0)+01_指標庫!$H$5*IF(ISNUMBER($AA20),AL20,0)+01_指標庫!$H$6*IF(ISNUMBER($G20),M20,0)+01_指標庫!$H$7*IF(ISNUMBER($H20),N20,0)+01_指標庫!$H$8*IF(ISNUMBER($AF20),AQ20,0)+01_指標庫!$H$9*IF(ISNUMBER($AG20),AR20,0)+01_指標庫!$H$10*IF(ISNUMBER($AB20),AM20,0)+01_指標庫!$H$11*IF(ISNUMBER($AC20),AN20,0)+01_指標庫!$H$12*IF(ISNUMBER($AD20),AO20,0)+01_指標庫!$H$13*IF(ISNUMBER($AE20),AP20,0)+01_指標庫!$H$14*IF(ISNUMBER($I20),O20,0)+01_指標庫!$H$15*IF(ISNUMBER($AH20),AS20,0)+01_指標庫!$H$16*IF(ISNUMBER($K20),P20,0)+01_指標庫!$H$17*IF(ISNUMBER($AI20),AT20,0)+01_指標庫!$H$18*IF(ISNUMBER($AJ20),AU20,0)+01_指標庫!$H$19*IF(ISNUMBER($AK20),AV20,0)+01_指標庫!$H$20*IF(ISNUMBER($BB20),BB20,0)+01_指標庫!$H$21*IF(ISNUMBER($BC20),BC20,0))/AW20,1)) -> 72.4 | BA20: =AVERAGE($E16:$E20)/AVERAGE($E11:$E20)-1 -> 0.0064111558 | BB20: =IF(ISNUMBER($BA20),IF(OR($S20<=-0.03,$BA20<-0.003),0,IF(OR($S20<=-0.02,$BA20<0.01),50,100)),"") -> 50 | BC20: =IF(OR(COUNT($AZ20)=0,COUNT($AZ19)=0),"",IF(OR($AY20/$AZ19-1<=-0.03,$AZ20/$AZ19-1<=-0.045,IF(COUNT($AZ11:$AZ20)=10,AVERAGE($AZ16:$AZ20)/AVERAGE($AZ11:$AZ20)-1<-0.01,FALSE())),0,IF(OR($AZ20/$AZ19-1<=-0.02,IF(COUNT($AZ11:$AZ20)=10,AVERAGE($AZ16:$AZ20)/AVERAGE($AZ11:$AZ20)-1<0.005,FALSE())),50,100)))
A21: 17 | B21: 42583 | C21: 2016 | D21: 一 | E21: 4756.04 | F21: 0.069305 | G21: 0 | H21: 0.898 | I21: 569 | J21: real | K21: 12.44 | L21: =IF(COUNT(F21)=0,50,IF(F21>=0,100,IF(F21>=-0.02,50,0))) -> 100 | M21: =IF(COUNT(G21)=0,50,IF(G21>-0.06,100,IF(G21>-0.15,50,0))) -> 100 | N21: =IF(COUNT(H21)=0,50,IF(H21>=0.6,100,IF(H21>=0.4,50,0))) -> 100 | O21: =IF(COUNT(I21)=0,50,IF(J21="proxy_vix",50,IF(I21<350,100,IF(I21<=450,50,0)))) -> 0 | P21: =IF(COUNT(K21)=0,50,IF(K21<20,100,IF(K21<=25,50,0))) -> 100 | S21: =$E21/$E20-1 -> 0.0054563943 | T21: =$K21/$K20-1 -> 0.048020219 | Y21: =IF(AX21>=70,"EASY",IF(AX21>40,"UNCERTAIN","HARD")) -> EASY | AA21: =IF($A21<200,"",AVERAGE($E5:$E21)/AVERAGE($E5:$E21)-1) | AB21: =LOOKUP($B21,07_L1政策步階!$A$4:$A$14,07_L1政策步階!$C$4:$C$14) -> 0 | AL21: =IF(ISNUMBER($AA21),IF($AA21>=0.005,100,IF($AA21>=-0.015,50,0)),"") | AM21: =IF(ISNUMBER($AB21),IF($AB21=1,100,IF($AB21=0,50,0)),"") -> 50 | AN21: =IF(ISNUMBER($AC21),IF($AC21>=0.001,100,IF($AC21>=-0.003,50,0)),"") | AO21: =IF(ISNUMBER($AD21),IF($AD21>=0.04,100,IF($AD21>=0,50,0)),"") | AP21: =IF(ISNUMBER($AE21),IF($AE21>=25,100,IF($AE21>=-75,50,0)),"") | AQ21: =IF(ISNUMBER($AF21),IF($AF21>0,100,IF($AF21>=-50,50,0)),"") | AR21: =IF(ISNUMBER($AG21),IF($AG21=1,100,IF($AG21=0,50,0)),"") | AS21: =IF(ISNUMBER($AH21),IF($AH21<0,100,IF($AH21<=20,50,0)),"") | AT21: =IF(ISNUMBER($AI21),IF($AI21<0.95,100,IF($AI21<=1,50,0)),"") | AU21: =IF(ISNUMBER($AJ21),IF($AJ21<30,0,IF($AJ21<40,50,IF($AJ21<=90,100,50))),"") | AV21: =IF(ISNUMBER($AK21),IF($AK21>-0.2,100,IF($AK21>=-0.4,50,0)),"") | AW21: =01_指標庫!$H$4*ISNUMBER($F21)+01_指標庫!$H$5*ISNUMBER($AA21)+01_指標庫!$H$6*ISNUMBER($G21)+01_指標庫!$H$7*ISNUMBER($H21)+01_指標庫!$H$8*ISNUMBER($AF21)+01_指標庫!$H$9*ISNUMBER($AG21)+01_指標庫!$H$10*ISNUMBER($AB21)+01_指標庫!$H$11*ISNUMBER($AC21)+01_指標庫!$H$12*ISNUMBER($AD21)+01_指標庫!$H$13*ISNUMBER($AE21)+01_指標庫!$H$14*ISNUMBER($I21)+01_指標庫!$H$15*ISNUMBER($AH21)+01_指標庫!$H$16*ISNUMBER($K21)+01_指標庫!$H$17*ISNUMBER($AI21)+01_指標庫!$H$18*ISNUMBER($AJ21)+01_指標庫!$H$19*ISNUMBER($AK21)+01_指標庫!$H$20*ISNUMBER($BB21)+01_指標庫!$H$21*ISNUMBER($BC21) -> 49 | AX21: =IF(AW21=0,50,ROUND((01_指標庫!$H$4*IF(ISNUMBER($F21),L21,0)+01_指標庫!$H$5*IF(ISNUMBER($AA21),AL21,0)+01_指標庫!$H$6*IF(ISNUMBER($G21),M21,0)+01_指標庫!$H$7*IF(ISNUMBER($H21),N21,0)+01_指標庫!$H$8*IF(ISNUMBER($AF21),AQ21,0)+01_指標庫!$H$9*IF(ISNUMBER($AG21),AR21,0)+01_指標庫!$H$10*IF(ISNUMBER($AB21),AM21,0)+01_指標庫!$H$11*IF(ISNUMBER($AC21),AN21,0)+01_指標庫!$H$12*IF(ISNUMBER($AD21),AO21,0)+01_指標庫!$H$13*IF(ISNUMBER($AE21),AP21,0)+01_指標庫!$H$14*IF(ISNUMBER($I21),O21,0)+01_指標庫!$H$15*IF(ISNUMBER($AH21),AS21,0)+01_指標庫!$H$16*IF(ISNUMBER($K21),P21,0)+01_指標庫!$H$17*IF(ISNUMBER($AI21),AT21,0)+01_指標庫!$H$18*IF(ISNUMBER($AJ21),AU21,0)+01_指標庫!$H$19*IF(ISNUMBER($AK21),AV21,0)+01_指標庫!$H$20*IF(ISNUMBER($BB21),BB21,0)+01_指標庫!$H$21*IF(ISNUMBER($BC21),BC21,0))/AW21,1)) -> 72.4 | BA21: =AVERAGE($E17:$E21)/AVERAGE($E12:$E21)-1 -> 0.0073292203 | BB21: =IF(ISNUMBER($BA21),IF(OR($S21<=-0.03,$BA21<-0.003),0,IF(OR($S21<=-0.02,$BA21<0.01),50,100)),"") -> 50 | BC21: =IF(OR(COUNT($AZ21)=0,COUNT($AZ20)=0),"",IF(OR($AY21/$AZ20-1<=-0.03,$AZ21/$AZ20-1<=-0.045,IF(COUNT($AZ12:$AZ21)=10,AVERAGE($AZ17:$AZ21)/AVERAGE($AZ12:$AZ21)-1<-0.01,FALSE())),0,IF(OR($AZ21/$AZ20-1<=-0.02,IF(COUNT($AZ12:$AZ21)=10,AVERAGE($AZ17:$AZ21)/AVERAGE($AZ12:$AZ21)-1<0.005,FALSE())),50,100)))
A22: 18 | B22: 42584 | C22: 2016 | D22: 二 | E22: 4719.21 | F22: 0.060666 | G22: -0.007744 | H22: 0.898 | I22: 573 | J22: real | K22: 13.37 | L22: =IF(COUNT(F22)=0,50,IF(F22>=0,100,IF(F22>=-0.02,50,0))) -> 100 | M22: =IF(COUNT(G22)=0,50,IF(G22>-0.06,100,IF(G22>-0.15,50,0))) -> 100 | N22: =IF(COUNT(H22)=0,50,IF(H22>=0.6,100,IF(H22>=0.4,50,0))) -> 100 | O22: =IF(COUNT(I22)=0,50,IF(J22="proxy_vix",50,IF(I22<350,100,IF(I22<=450,50,0)))) -> 0 | P22: =IF(COUNT(K22)=0,50,IF(K22<20,100,IF(K22<=25,50,0))) -> 100 | S22: =$E22/$E21-1 -> -0.0077438373 | T22: =$K22/$K21-1 -> 0.074758842 | Y22: =IF(AX22>=70,"EASY",IF(AX22>40,"UNCERTAIN","HARD")) -> EASY | AA22: =IF($A22<200,"",AVERAGE($E5:$E22)/AVERAGE($E5:$E22)-1) | AB22: =LOOKUP($B22,07_L1政策步階!$A$4:$A$14,07_L1政策步階!$C$4:$C$14) -> 0 | AL22: =IF(ISNUMBER($AA22),IF($AA22>=0.005,100,IF($AA22>=-0.015,50,0)),"") | AM22: =IF(ISNUMBER($AB22),IF($AB22=1,100,IF($AB22=0,50,0)),"") -> 50 | AN22: =IF(ISNUMBER($AC22),IF($AC22>=0.001,100,IF($AC22>=-0.003,50,0)),"") | AO22: =IF(ISNUMBER($AD22),IF($AD22>=0.04,100,IF($AD22>=0,50,0)),"") | AP22: =IF(ISNUMBER($AE22),IF($AE22>=25,100,IF($AE22>=-75,50,0)),"") | AQ22: =IF(ISNUMBER($AF22),IF($AF22>0,100,IF($AF22>=-50,50,0)),"") | AR22: =IF(ISNUMBER($AG22),IF($AG22=1,100,IF($AG22=0,50,0)),"") | AS22: =IF(ISNUMBER($AH22),IF($AH22<0,100,IF($AH22<=20,50,0)),"") | AT22: =IF(ISNUMBER($AI22),IF($AI22<0.95,100,IF($AI22<=1,50,0)),"") | AU22: =IF(ISNUMBER($AJ22),IF($AJ22<30,0,IF($AJ22<40,50,IF($AJ22<=90,100,50))),"") | AV22: =IF(ISNUMBER($AK22),IF($AK22>-0.2,100,IF($AK22>=-0.4,50,0)),"") | AW22: =01_指標庫!$H$4*ISNUMBER($F22)+01_指標庫!$H$5*ISNUMBER($AA22)+01_指標庫!$H$6*ISNUMBER($G22)+01_指標庫!$H$7*ISNUMBER($H22)+01_指標庫!$H$8*ISNUMBER($AF22)+01_指標庫!$H$9*ISNUMBER($AG22)+01_指標庫!$H$10*ISNUMBER($AB22)+01_指標庫!$H$11*ISNUMBER($AC22)+01_指標庫!$H$12*ISNUMBER($AD22)+01_指標庫!$H$13*ISNUMBER($AE22)+01_指標庫!$H$14*ISNUMBER($I22)+01_指標庫!$H$15*ISNUMBER($AH22)+01_指標庫!$H$16*ISNUMBER($K22)+01_指標庫!$H$17*ISNUMBER($AI22)+01_指標庫!$H$18*ISNUMBER($AJ22)+01_指標庫!$H$19*ISNUMBER($AK22)+01_指標庫!$H$20*ISNUMBER($BB22)+01_指標庫!$H$21*ISNUMBER($BC22) -> 49 | AX22: =IF(AW22=0,50,ROUND((01_指標庫!$H$4*IF(ISNUMBER($F22),L22,0)+01_指標庫!$H$5*IF(ISNUMBER($AA22),AL22,0)+01_指標庫!$H$6*IF(ISNUMBER($G22),M22,0)+01_指標庫!$H$7*IF(ISNUMBER($H22),N22,0)+01_指標庫!$H$8*IF(ISNUMBER($AF22),AQ22,0)+01_指標庫!$H$9*IF(ISNUMBER($AG22),AR22,0)+01_指標庫!$H$10*IF(ISNUMBER($AB22),AM22,0)+01_指標庫!$H$11*IF(ISNUMBER($AC22),AN22,0)+01_指標庫!$H$12*IF(ISNUMBER($AD22),AO22,0)+01_指標庫!$H$13*IF(ISNUMBER($AE22),AP22,0)+01_指標庫!$H$14*IF(ISNUMBER($I22),O22,0)+01_指標庫!$H$15*IF(ISNUMBER($AH22),AS22,0)+01_指標庫!$H$16*IF(ISNUMBER($K22),P22,0)+01_指標庫!$H$17*IF(ISNUMBER($AI22),AT22,0)+01_指標庫!$H$18*IF(ISNUMBER($AJ22),AU22,0)+01_指標庫!$H$19*IF(ISNUMBER($AK22),AV22,0)+01_指標庫!$H$20*IF(ISNUMBER($BB22),BB22,0)+01_指標庫!$H$21*IF(ISNUMBER($BC22),BC22,0))/AW22,1)) -> 72.4 | BA22: =AVERAGE($E18:$E22)/AVERAGE($E13:$E22)-1 -> 0.0068481681 | BB22: =IF(ISNUMBER($BA22),IF(OR($S22<=-0.03,$BA22<-0.003),0,IF(OR($S22<=-0.02,$BA22<0.01),50,100)),"") -> 50 | BC22: =IF(OR(COUNT($AZ22)=0,COUNT($AZ21)=0),"",IF(OR($AY22/$AZ21-1<=-0.03,$AZ22/$AZ21-1<=-0.045,IF(COUNT($AZ13:$AZ22)=10,AVERAGE($AZ18:$AZ22)/AVERAGE($AZ13:$AZ22)-1<-0.01,FALSE())),0,IF(OR($AZ22/$AZ21-1<=-0.02,IF(COUNT($AZ13:$AZ22)=10,AVERAGE($AZ18:$AZ22)/AVERAGE($AZ13:$AZ22)-1<0.005,FALSE())),50,100)))
A23: 19 | B23: 42585 | C23: 2016 | D23: 三 | E23: 4734.33 | F23: 0.063711 | G23: -0.004565 | H23: 0.9184 | I23: 572 | J23: real | K23: 12.86 | L23: =IF(COUNT(F23)=0,50,IF(F23>=0,100,IF(F23>=-0.02,50,0))) -> 100 | M23: =IF(COUNT(G23)=0,50,IF(G23>-0.06,100,IF(G23>-0.15,50,0))) -> 100 | N23: =IF(COUNT(H23)=0,50,IF(H23>=0.6,100,IF(H23>=0.4,50,0))) -> 100 | O23: =IF(COUNT(I23)=0,50,IF(J23="proxy_vix",50,IF(I23<350,100,IF(I23<=450,50,0)))) -> 0 | P23: =IF(COUNT(K23)=0,50,IF(K23<20,100,IF(K23<=25,50,0))) -> 100 | S23: =$E23/$E22-1 -> 0.0032039261 | T23: =$K23/$K22-1 -> -0.038145101 | Y23: =IF(AX23>=70,"EASY",IF(AX23>40,"UNCERTAIN","HARD")) -> EASY | AA23: =IF($A23<200,"",AVERAGE($E5:$E23)/AVERAGE($E5:$E23)-1) | AB23: =LOOKUP($B23,07_L1政策步階!$A$4:$A$14,07_L1政策步階!$C$4:$C$14) -> 0 | AL23: =IF(ISNUMBER($AA23),IF($AA23>=0.005,100,IF($AA23>=-0.015,50,0)),"") | AM23: =IF(ISNUMBER($AB23),IF($AB23=1,100,IF($AB23=0,50,0)),"") -> 50 | AN23: =IF(ISNUMBER($AC23),IF($AC23>=0.001,100,IF($AC23>=-0.003,50,0)),"") | AO23: =IF(ISNUMBER($AD23),IF($AD23>=0.04,100,IF($AD23>=0,50,0)),"") | AP23: =IF(ISNUMBER($AE23),IF($AE23>=25,100,IF($AE23>=-75,50,0)),"") | AQ23: =IF(ISNUMBER($AF23),IF($AF23>0,100,IF($AF23>=-50,50,0)),"") | AR23: =IF(ISNUMBER($AG23),IF($AG23=1,100,IF($AG23=0,50,0)),"") | AS23: =IF(ISNUMBER($AH23),IF($AH23<0,100,IF($AH23<=20,50,0)),"") | AT23: =IF(ISNUMBER($AI23),IF($AI23<0.95,100,IF($AI23<=1,50,0)),"") | AU23: =IF(ISNUMBER($AJ23),IF($AJ23<30,0,IF($AJ23<40,50,IF($AJ23<=90,100,50))),"") | AV23: =IF(ISNUMBER($AK23),IF($AK23>-0.2,100,IF($AK23>=-0.4,50,0)),"") | AW23: =01_指標庫!$H$4*ISNUMBER($F23)+01_指標庫!$H$5*ISNUMBER($AA23)+01_指標庫!$H$6*ISNUMBER($G23)+01_指標庫!$H$7*ISNUMBER($H23)+01_指標庫!$H$8*ISNUMBER($AF23)+01_指標庫!$H$9*ISNUMBER($AG23)+01_指標庫!$H$10*ISNUMBER($AB23)+01_指標庫!$H$11*ISNUMBER($AC23)+01_指標庫!$H$12*ISNUMBER($AD23)+01_指標庫!$H$13*ISNUMBER($AE23)+01_指標庫!$H$14*ISNUMBER($I23)+01_指標庫!$H$15*ISNUMBER($AH23)+01_指標庫!$H$16*ISNUMBER($K23)+01_指標庫!$H$17*ISNUMBER($AI23)+01_指標庫!$H$18*ISNUMBER($AJ23)+01_指標庫!$H$19*ISNUMBER($AK23)+01_指標庫!$H$20*ISNUMBER($BB23)+01_指標庫!$H$21*ISNUMBER($BC23) -> 49 | AX23: =IF(AW23=0,50,ROUND((01_指標庫!$H$4*IF(ISNUMBER($F23),L23,0)+01_指標庫!$H$5*IF(ISNUMBER($AA23),AL23,0)+01_指標庫!$H$6*IF(ISNUMBER($G23),M23,0)+01_指標庫!$H$7*IF(ISNUMBER($H23),N23,0)+01_指標庫!$H$8*IF(ISNUMBER($AF23),AQ23,0)+01_指標庫!$H$9*IF(ISNUMBER($AG23),AR23,0)+01_指標庫!$H$10*IF(ISNUMBER($AB23),AM23,0)+01_指標庫!$H$11*IF(ISNUMBER($AC23),AN23,0)+01_指標庫!$H$12*IF(ISNUMBER($AD23),AO23,0)+01_指標庫!$H$13*IF(ISNUMBER($AE23),AP23,0)+01_指標庫!$H$14*IF(ISNUMBER($I23),O23,0)+01_指標庫!$H$15*IF(ISNUMBER($AH23),AS23,0)+01_指標庫!$H$16*IF(ISNUMBER($K23),P23,0)+01_指標庫!$H$17*IF(ISNUMBER($AI23),AT23,0)+01_指標庫!$H$18*IF(ISNUMBER($AJ23),AU23,0)+01_指標庫!$H$19*IF(ISNUMBER($AK23),AV23,0)+01_指標庫!$H$20*IF(ISNUMBER($BB23),BB23,0)+01_指標庫!$H$21*IF(ISNUMBER($BC23),BC23,0))/AW23,1)) -> 72.4 | BA23: =AVERAGE($E19:$E23)/AVERAGE($E14:$E23)-1 -> 0.0065342656 | BB23: =IF(ISNUMBER($BA23),IF(OR($S23<=-0.03,$BA23<-0.003),0,IF(OR($S23<=-0.02,$BA23<0.01),50,100)),"") -> 50 | BC23: =IF(OR(COUNT($AZ23)=0,COUNT($AZ22)=0),"",IF(OR($AY23/$AZ22-1<=-0.03,$AZ23/$AZ22-1<=-0.045,IF(COUNT($AZ14:$AZ23)=10,AVERAGE($AZ19:$AZ23)/AVERAGE($AZ14:$AZ23)-1<-0.01,FALSE())),0,IF(OR($AZ23/$AZ22-1<=-0.02,IF(COUNT($AZ14:$AZ23)=10,AVERAGE($AZ19:$AZ23)/AVERAGE($AZ14:$AZ23)-1<0.005,FALSE())),50,100)))
A24: 20 | B24: 42586 | C24: 2016 | D24: 四 | E24: 4743.81 | F24: 0.065503 | G24: -0.002571 | H24: 0.898 | I24: 565 | J24: real | K24: 12.42 | L24: =IF(COUNT(F24)=0,50,IF(F24>=0,100,IF(F24>=-0.02,50,0))) -> 100 | M24: =IF(COUNT(G24)=0,50,IF(G24>-0.06,100,IF(G24>-0.15,50,0))) -> 100 | N24: =IF(COUNT(H24)=0,50,IF(H24>=0.6,100,IF(H24>=0.4,50,0))) -> 100 | O24: =IF(COUNT(I24)=0,50,IF(J24="proxy_vix",50,IF(I24<350,100,IF(I24<=450,50,0)))) -> 0 | P24: =IF(COUNT(K24)=0,50,IF(K24<20,100,IF(K24<=25,50,0))) -> 100 | S24: =$E24/$E23-1 -> 0.0020023953 | T24: =$K24/$K23-1 -> -0.034214619 | Y24: =IF(AX24>=70,"EASY",IF(AX24>40,"UNCERTAIN","HARD")) -> EASY | AA24: =IF($A24<200,"",AVERAGE($E5:$E24)/AVERAGE($E5:$E24)-1) | AB24: =LOOKUP($B24,07_L1政策步階!$A$4:$A$14,07_L1政策步階!$C$4:$C$14) -> 0 | AL24: =IF(ISNUMBER($AA24),IF($AA24>=0.005,100,IF($AA24>=-0.015,50,0)),"") | AM24: =IF(ISNUMBER($AB24),IF($AB24=1,100,IF($AB24=0,50,0)),"") -> 50 | AN24: =IF(ISNUMBER($AC24),IF($AC24>=0.001,100,IF($AC24>=-0.003,50,0)),"") | AO24: =IF(ISNUMBER($AD24),IF($AD24>=0.04,100,IF($AD24>=0,50,0)),"") | AP24: =IF(ISNUMBER($AE24),IF($AE24>=25,100,IF($AE24>=-75,50,0)),"") | AQ24: =IF(ISNUMBER($AF24),IF($AF24>0,100,IF($AF24>=-50,50,0)),"") | AR24: =IF(ISNUMBER($AG24),IF($AG24=1,100,IF($AG24=0,50,0)),"") | AS24: =IF(ISNUMBER($AH24),IF($AH24<0,100,IF($AH24<=20,50,0)),"") | AT24: =IF(ISNUMBER($AI24),IF($AI24<0.95,100,IF($AI24<=1,50,0)),"") | AU24: =IF(ISNUMBER($AJ24),IF($AJ24<30,0,IF($AJ24<40,50,IF($AJ24<=90,100,50))),"") | AV24: =IF(ISNUMBER($AK24),IF($AK24>-0.2,100,IF($AK24>=-0.4,50,0)),"") | AW24: =01_指標庫!$H$4*ISNUMBER($F24)+01_指標庫!$H$5*ISNUMBER($AA24)+01_指標庫!$H$6*ISNUMBER($G24)+01_指標庫!$H$7*ISNUMBER($H24)+01_指標庫!$H$8*ISNUMBER($AF24)+01_指標庫!$H$9*ISNUMBER($AG24)+01_指標庫!$H$10*ISNUMBER($AB24)+01_指標庫!$H$11*ISNUMBER($AC24)+01_指標庫!$H$12*ISNUMBER($AD24)+01_指標庫!$H$13*ISNUMBER($AE24)+01_指標庫!$H$14*ISNUMBER($I24)+01_指標庫!$H$15*ISNUMBER($AH24)+01_指標庫!$H$16*ISNUMBER($K24)+01_指標庫!$H$17*ISNUMBER($AI24)+01_指標庫!$H$18*ISNUMBER($AJ24)+01_指標庫!$H$19*ISNUMBER($AK24)+01_指標庫!$H$20*ISNUMBER($BB24)+01_指標庫!$H$21*ISNUMBER($BC24) -> 49 | AX24: =IF(AW24=0,50,ROUND((01_指標庫!$H$4*IF(ISNUMBER($F24),L24,0)+01_指標庫!$H$5*IF(ISNUMBER($AA24),AL24,0)+01_指標庫!$H$6*IF(ISNUMBER($G24),M24,0)+01_指標庫!$H$7*IF(ISNUMBER($H24),N24,0)+01_指標庫!$H$8*IF(ISNUMBER($AF24),AQ24,0)+01_指標庫!$H$9*IF(ISNUMBER($AG24),AR24,0)+01_指標庫!$H$10*IF(ISNUMBER($AB24),AM24,0)+01_指標庫!$H$11*IF(ISNUMBER($AC24),AN24,0)+01_指標庫!$H$12*IF(ISNUMBER($AD24),AO24,0)+01_指標庫!$H$13*IF(ISNUMBER($AE24),AP24,0)+01_指標庫!$H$14*IF(ISNUMBER($I24),O24,0)+01_指標庫!$H$15*IF(ISNUMBER($AH24),AS24,0)+01_指標庫!$H$16*IF(ISNUMBER($K24),P24,0)+01_指標庫!$H$17*IF(ISNUMBER($AI24),AT24,0)+01_指標庫!$H$18*IF(ISNUMBER($AJ24),AU24,0)+01_指標庫!$H$19*IF(ISNUMBER($AK24),AV24,0)+01_指標庫!$H$20*IF(ISNUMBER($BB24),BB24,0)+01_指標庫!$H$21*IF(ISNUMBER($BC24),BC24,0))/AW24,1)) -> 72.4 | BA24: =AVERAGE($E20:$E24)/AVERAGE($E15:$E24)-1 -> 0.0054173011 | BB24: =IF(ISNUMBER($BA24),IF(OR($S24<=-0.03,$BA24<-0.003),0,IF(OR($S24<=-0.02,$BA24<0.01),50,100)),"") -> 50 | BC24: =IF(OR(COUNT($AZ24)=0,COUNT($AZ23)=0),"",IF(OR($AY24/$AZ23-1<=-0.03,$AZ24/$AZ23-1<=-0.045,IF(COUNT($AZ15:$AZ24)=10,AVERAGE($AZ20:$AZ24)/AVERAGE($AZ15:$AZ24)-1<-0.01,FALSE())),0,IF(OR($AZ24/$AZ23-1<=-0.02,IF(COUNT($AZ15:$AZ24)=10,AVERAGE($AZ20:$AZ24)/AVERAGE($AZ15:$AZ24)-1<0.005,FALSE())),50,100)))
A25: 21 | B25: 42587 | C25: 2016 | D25: 五 | E25: 4791.21 | F25: 0.075723 | G25: 0 | H25: 0.898 | I25: 546 | J25: real | K25: 11.39 | L25: =IF(COUNT(F25)=0,50,IF(F25>=0,100,IF(F25>=-0.02,50,0))) -> 100 | M25: =IF(COUNT(G25)=0,50,IF(G25>-0.06,100,IF(G25>-0.15,50,0))) -> 100 | N25: =IF(COUNT(H25)=0,50,IF(H25>=0.6,100,IF(H25>=0.4,50,0))) -> 100 | O25: =IF(COUNT(I25)=0,50,IF(J25="proxy_vix",50,IF(I25<350,100,IF(I25<=450,50,0)))) -> 0 | P25: =IF(COUNT(K25)=0,50,IF(K25<20,100,IF(K25<=25,50,0))) -> 100 | S25: =$E25/$E24-1 -> 0.0099919685 | T25: =$K25/$K24-1 -> -0.082930757 | Y25: =IF(AX25>=70,"EASY",IF(AX25>40,"UNCERTAIN","HARD")) -> EASY | AA25: =IF($A25<200,"",AVERAGE($E5:$E25)/AVERAGE($E5:$E25)-1) | AB25: =LOOKUP($B25,07_L1政策步階!$A$4:$A$14,07_L1政策步階!$C$4:$C$14) -> 0 | AL25: =IF(ISNUMBER($AA25),IF($AA25>=0.005,100,IF($AA25>=-0.015,50,0)),"") | AM25: =IF(ISNUMBER($AB25),IF($AB25=1,100,IF($AB25=0,50,0)),"") -> 50 | AN25: =IF(ISNUMBER($AC25),IF($AC25>=0.001,100,IF($AC25>=-0.003,50,0)),"") | AO25: =IF(ISNUMBER($AD25),IF($AD25>=0.04,100,IF($AD25>=0,50,0)),"") | AP25: =IF(ISNUMBER($AE25),IF($AE25>=25,100,IF($AE25>=-75,50,0)),"") | AQ25: =IF(ISNUMBER($AF25),IF($AF25>0,100,IF($AF25>=-50,50,0)),"") | AR25: =IF(ISNUMBER($AG25),IF($AG25=1,100,IF($AG25=0,50,0)),"") | AS25: =IF(ISNUMBER($AH25),IF($AH25<0,100,IF($AH25<=20,50,0)),"") | AT25: =IF(ISNUMBER($AI25),IF($AI25<0.95,100,IF($AI25<=1,50,0)),"") | AU25: =IF(ISNUMBER($AJ25),IF($AJ25<30,0,IF($AJ25<40,50,IF($AJ25<=90,100,50))),"") | AV25: =IF(ISNUMBER($AK25),IF($AK25>-0.2,100,IF($AK25>=-0.4,50,0)),"") | AW25: =01_指標庫!$H$4*ISNUMBER($F25)+01_指標庫!$H$5*ISNUMBER($AA25)+01_指標庫!$H$6*ISNUMBER($G25)+01_指標庫!$H$7*ISNUMBER($H25)+01_指標庫!$H$8*ISNUMBER($AF25)+01_指標庫!$H$9*ISNUMBER($AG25)+01_指標庫!$H$10*ISNUMBER($AB25)+01_指標庫!$H$11*ISNUMBER($AC25)+01_指標庫!$H$12*ISNUMBER($AD25)+01_指標庫!$H$13*ISNUMBER($AE25)+01_指標庫!$H$14*ISNUMBER($I25)+01_指標庫!$H$15*ISNUMBER($AH25)+01_指標庫!$H$16*ISNUMBER($K25)+01_指標庫!$H$17*ISNUMBER($AI25)+01_指標庫!$H$18*ISNUMBER($AJ25)+01_指標庫!$H$19*ISNUMBER($AK25)+01_指標庫!$H$20*ISNUMBER($BB25)+01_指標庫!$H$21*ISNUMBER($BC25) -> 49 | AX25: =IF(AW25=0,50,ROUND((01_指標庫!$H$4*IF(ISNUMBER($F25),L25,0)+01_指標庫!$H$5*IF(ISNUMBER($AA25),AL25,0)+01_指標庫!$H$6*IF(ISNUMBER($G25),M25,0)+01_指標庫!$H$7*IF(ISNUMBER($H25),N25,0)+01_指標庫!$H$8*IF(ISNUMBER($AF25),AQ25,0)+01_指標庫!$H$9*IF(ISNUMBER($AG25),AR25,0)+01_指標庫!$H$10*IF(ISNUMBER($AB25),AM25,0)+01_指標庫!$H$11*IF(ISNUMBER($AC25),AN25,0)+01_指標庫!$H$12*IF(ISNUMBER($AD25),AO25,0)+01_指標庫!$H$13*IF(ISNUMBER($AE25),AP25,0)+01_指標庫!$H$14*IF(ISNUMBER($I25),O25,0)+01_指標庫!$H$15*IF(ISNUMBER($AH25),AS25,0)+01_指標庫!$H$16*IF(ISNUMBER($K25),P25,0)+01_指標庫!$H$17*IF(ISNUMBER($AI25),AT25,0)+01_指標庫!$H$18*IF(ISNUMBER($AJ25),AU25,0)+01_指標庫!$H$19*IF(ISNUMBER($AK25),AV25,0)+01_指標庫!$H$20*IF(ISNUMBER($BB25),BB25,0)+01_指標庫!$H$21*IF(ISNUMBER($BC25),BC25,0))/AW25,1)) -> 72.4 | BA25: =AVERAGE($E21:$E25)/AVERAGE($E16:$E25)-1 -> 0.0053356298 | BB25: =IF(ISNUMBER($BA25),IF(OR($S25<=-0.03,$BA25<-0.003),0,IF(OR($S25<=-0.02,$BA25<0.01),50,100)),"") -> 50 | BC25: =IF(OR(COUNT($AZ25)=0,COUNT($AZ24)=0),"",IF(OR($AY25/$AZ24-1<=-0.03,$AZ25/$AZ24-1<=-0.045,IF(COUNT($AZ16:$AZ25)=10,AVERAGE($AZ21:$AZ25)/AVERAGE($AZ16:$AZ25)-1<-0.01,FALSE())),0,IF(OR($AZ25/$AZ24-1<=-0.02,IF(COUNT($AZ16:$AZ25)=10,AVERAGE($AZ21:$AZ25)/AVERAGE($AZ16:$AZ25)-1<0.005,FALSE())),50,100)))
A26: 22 | B26: 42590 | C26: 2016 | D26: 一 | E26: 4784.74 | F26: 0.073823 | G26: -0.00135 | H26: 0.898 | I26: 542 | J26: real | K26: 11.5 | L26: =IF(COUNT(F26)=0,50,IF(F26>=0,100,IF(F26>=-0.02,50,0))) -> 100 | M26: =IF(COUNT(G26)=0,50,IF(G26>-0.06,100,IF(G26>-0.15,50,0))) -> 100 | N26: =IF(COUNT(H26)=0,50,IF(H26>=0.6,100,IF(H26>=0.4,50,0))) -> 100 | O26: =IF(COUNT(I26)=0,50,IF(J26="proxy_vix",50,IF(I26<350,100,IF(I26<=450,50,0)))) -> 0 | P26: =IF(COUNT(K26)=0,50,IF(K26<20,100,IF(K26<=25,50,0))) -> 100 | S26: =$E26/$E25-1 -> -0.0013503896 | T26: =$K26/$K25-1 -> 0.0096575944 | Y26: =IF(AX26>=70,"EASY",IF(AX26>40,"UNCERTAIN","HARD")) -> EASY | AA26: =IF($A26<200,"",AVERAGE($E5:$E26)/AVERAGE($E5:$E26)-1) | AB26: =LOOKUP($B26,07_L1政策步階!$A$4:$A$14,07_L1政策步階!$C$4:$C$14) -> 0 | AL26: =IF(ISNUMBER($AA26),IF($AA26>=0.005,100,IF($AA26>=-0.015,50,0)),"") | AM26: =IF(ISNUMBER($AB26),IF($AB26=1,100,IF($AB26=0,50,0)),"") -> 50 | AN26: =IF(ISNUMBER($AC26),IF($AC26>=0.001,100,IF($AC26>=-0.003,50,0)),"") | AO26: =IF(ISNUMBER($AD26),IF($AD26>=0.04,100,IF($AD26>=0,50,0)),"") | AP26: =IF(ISNUMBER($AE26),IF($AE26>=25,100,IF($AE26>=-75,50,0)),"") | AQ26: =IF(ISNUMBER($AF26),IF($AF26>0,100,IF($AF26>=-50,50,0)),"") | AR26: =IF(ISNUMBER($AG26),IF($AG26=1,100,IF($AG26=0,50,0)),"") | AS26: =IF(ISNUMBER($AH26),IF($AH26<0,100,IF($AH26<=20,50,0)),"") | AT26: =IF(ISNUMBER($AI26),IF($AI26<0.95,100,IF($AI26<=1,50,0)),"") | AU26: =IF(ISNUMBER($AJ26),IF($AJ26<30,0,IF($AJ26<40,50,IF($AJ26<=90,100,50))),"") | AV26: =IF(ISNUMBER($AK26),IF($AK26>-0.2,100,IF($AK26>=-0.4,50,0)),"") | AW26: =01_指標庫!$H$4*ISNUMBER($F26)+01_指標庫!$H$5*ISNUMBER($AA26)+01_指標庫!$H$6*ISNUMBER($G26)+01_指標庫!$H$7*ISNUMBER($H26)+01_指標庫!$H$8*ISNUMBER($AF26)+01_指標庫!$H$9*ISNUMBER($AG26)+01_指標庫!$H$10*ISNUMBER($AB26)+01_指標庫!$H$11*ISNUMBER($AC26)+01_指標庫!$H$12*ISNUMBER($AD26)+01_指標庫!$H$13*ISNUMBER($AE26)+01_指標庫!$H$14*ISNUMBER($I26)+01_指標庫!$H$15*ISNUMBER($AH26)+01_指標庫!$H$16*ISNUMBER($K26)+01_指標庫!$H$17*ISNUMBER($AI26)+01_指標庫!$H$18*ISNUMBER($AJ26)+01_指標庫!$H$19*ISNUMBER($AK26)+01_指標庫!$H$20*ISNUMBER($BB26)+01_指標庫!$H$21*ISNUMBER($BC26) -> 49 | AX26: =IF(AW26=0,50,ROUND((01_指標庫!$H$4*IF(ISNUMBER($F26),L26,0)+01_指標庫!$H$5*IF(ISNUMBER($AA26),AL26,0)+01_指標庫!$H$6*IF(ISNUMBER($G26),M26,0)+01_指標庫!$H$7*IF(ISNUMBER($H26),N26,0)+01_指標庫!$H$8*IF(ISNUMBER($AF26),AQ26,0)+01_指標庫!$H$9*IF(ISNUMBER($AG26),AR26,0)+01_指標庫!$H$10*IF(ISNUMBER($AB26),AM26,0)+01_指標庫!$H$11*IF(ISNUMBER($AC26),AN26,0)+01_指標庫!$H$12*IF(ISNUMBER($AD26),AO26,0)+01_指標庫!$H$13*IF(ISNUMBER($AE26),AP26,0)+01_指標庫!$H$14*IF(ISNUMBER($I26),O26,0)+01_指標庫!$H$15*IF(ISNUMBER($AH26),AS26,0)+01_指標庫!$H$16*IF(ISNUMBER($K26),P26,0)+01_指標庫!$H$17*IF(ISNUMBER($AI26),AT26,0)+01_指標庫!$H$18*IF(ISNUMBER($AJ26),AU26,0)+01_指標庫!$H$19*IF(ISNUMBER($AK26),AV26,0)+01_指標庫!$H$20*IF(ISNUMBER($BB26),BB26,0)+01_指標庫!$H$21*IF(ISNUMBER($BC26),BC26,0))/AW26,1)) -> 72.4 | BA26: =AVERAGE($E22:$E26)/AVERAGE($E17:$E26)-1 -> 0.0040254692 | BB26: =IF(ISNUMBER($BA26),IF(OR($S26<=-0.03,$BA26<-0.003),0,IF(OR($S26<=-0.02,$BA26<0.01),50,100)),"") -> 50 | BC26: =IF(OR(COUNT($AZ26)=0,COUNT($AZ25)=0),"",IF(OR($AY26/$AZ25-1<=-0.03,$AZ26/$AZ25-1<=-0.045,IF(COUNT($AZ17:$AZ26)=10,AVERAGE($AZ22:$AZ26)/AVERAGE($AZ17:$AZ26)-1<-0.01,FALSE())),0,IF(OR($AZ26/$AZ25-1<=-0.02,IF(COUNT($AZ17:$AZ26)=10,AVERAGE($AZ22:$AZ26)/AVERAGE($AZ17:$AZ26)-1<0.005,FALSE())),50,100)))
A27: 23 | B27: 42591 | C27: 2016 | D27: 二 | E27: 4795.75 | F27: 0.075941 | G27: 0 | H27: 0.898 | I27: 536 | J27: real | K27: 11.66 | L27: =IF(COUNT(F27)=0,50,IF(F27>=0,100,IF(F27>=-0.02,50,0))) -> 100 | M27: =IF(COUNT(G27)=0,50,IF(G27>-0.06,100,IF(G27>-0.15,50,0))) -> 100 | N27: =IF(COUNT(H27)=0,50,IF(H27>=0.6,100,IF(H27>=0.4,50,0))) -> 100 | O27: =IF(COUNT(I27)=0,50,IF(J27="proxy_vix",50,IF(I27<350,100,IF(I27<=450,50,0)))) -> 0 | P27: =IF(COUNT(K27)=0,50,IF(K27<20,100,IF(K27<=25,50,0))) -> 100 | S27: =$E27/$E26-1 -> 0.0023010655 | T27: =$K27/$K26-1 -> 0.013913043 | Y27: =IF(AX27>=70,"EASY",IF(AX27>40,"UNCERTAIN","HARD")) -> EASY | AA27: =IF($A27<200,"",AVERAGE($E5:$E27)/AVERAGE($E5:$E27)-1) | AB27: =LOOKUP($B27,07_L1政策步階!$A$4:$A$14,07_L1政策步階!$C$4:$C$14) -> 0 | AL27: =IF(ISNUMBER($AA27),IF($AA27>=0.005,100,IF($AA27>=-0.015,50,0)),"") | AM27: =IF(ISNUMBER($AB27),IF($AB27=1,100,IF($AB27=0,50,0)),"") -> 50 | AN27: =IF(ISNUMBER($AC27),IF($AC27>=0.001,100,IF($AC27>=-0.003,50,0)),"") | AO27: =IF(ISNUMBER($AD27),IF($AD27>=0.04,100,IF($AD27>=0,50,0)),"") | AP27: =IF(ISNUMBER($AE27),IF($AE27>=25,100,IF($AE27>=-75,50,0)),"") | AQ27: =IF(ISNUMBER($AF27),IF($AF27>0,100,IF($AF27>=-50,50,0)),"") | AR27: =IF(ISNUMBER($AG27),IF($AG27=1,100,IF($AG27=0,50,0)),"") | AS27: =IF(ISNUMBER($AH27),IF($AH27<0,100,IF($AH27<=20,50,0)),"") | AT27: =IF(ISNUMBER($AI27),IF($AI27<0.95,100,IF($AI27<=1,50,0)),"") | AU27: =IF(ISNUMBER($AJ27),IF($AJ27<30,0,IF($AJ27<40,50,IF($AJ27<=90,100,50))),"") | AV27: =IF(ISNUMBER($AK27),IF($AK27>-0.2,100,IF($AK27>=-0.4,50,0)),"") | AW27: =01_指標庫!$H$4*ISNUMBER($F27)+01_指標庫!$H$5*ISNUMBER($AA27)+01_指標庫!$H$6*ISNUMBER($G27)+01_指標庫!$H$7*ISNUMBER($H27)+01_指標庫!$H$8*ISNUMBER($AF27)+01_指標庫!$H$9*ISNUMBER($AG27)+01_指標庫!$H$10*ISNUMBER($AB27)+01_指標庫!$H$11*ISNUMBER($AC27)+01_指標庫!$H$12*ISNUMBER($AD27)+01_指標庫!$H$13*ISNUMBER($AE27)+01_指標庫!$H$14*ISNUMBER($I27)+01_指標庫!$H$15*ISNUMBER($AH27)+01_指標庫!$H$16*ISNUMBER($K27)+01_指標庫!$H$17*ISNUMBER($AI27)+01_指標庫!$H$18*ISNUMBER($AJ27)+01_指標庫!$H$19*ISNUMBER($AK27)+01_指標庫!$H$20*ISNUMBER($BB27)+01_指標庫!$H$21*ISNUMBER($BC27) -> 49 | AX27: =IF(AW27=0,50,ROUND((01_指標庫!$H$4*IF(ISNUMBER($F27),L27,0)+01_指標庫!$H$5*IF(ISNUMBER($AA27),AL27,0)+01_指標庫!$H$6*IF(ISNUMBER($G27),M27,0)+01_指標庫!$H$7*IF(ISNUMBER($H27),N27,0)+01_指標庫!$H$8*IF(ISNUMBER($AF27),AQ27,0)+01_指標庫!$H$9*IF(ISNUMBER($AG27),AR27,0)+01_指標庫!$H$10*IF(ISNUMBER($AB27),AM27,0)+01_指標庫!$H$11*IF(ISNUMBER($AC27),AN27,0)+01_指標庫!$H$12*IF(ISNUMBER($AD27),AO27,0)+01_指標庫!$H$13*IF(ISNUMBER($AE27),AP27,0)+01_指標庫!$H$14*IF(ISNUMBER($I27),O27,0)+01_指標庫!$H$15*IF(ISNUMBER($AH27),AS27,0)+01_指標庫!$H$16*IF(ISNUMBER($K27),P27,0)+01_指標庫!$H$17*IF(ISNUMBER($AI27),AT27,0)+01_指標庫!$H$18*IF(ISNUMBER($AJ27),AU27,0)+01_指標庫!$H$19*IF(ISNUMBER($AK27),AV27,0)+01_指標庫!$H$20*IF(ISNUMBER($BB27),BB27,0)+01_指標庫!$H$21*IF(ISNUMBER($BC27),BC27,0))/AW27,1)) -> 72.4 | BA27: =AVERAGE($E23:$E27)/AVERAGE($E18:$E27)-1 -> 0.0046350423 | BB27: =IF(ISNUMBER($BA27),IF(OR($S27<=-0.03,$BA27<-0.003),0,IF(OR($S27<=-0.02,$BA27<0.01),50,100)),"") -> 50 | BC27: =IF(OR(COUNT($AZ27)=0,COUNT($AZ26)=0),"",IF(OR($AY27/$AZ26-1<=-0.03,$AZ27/$AZ26-1<=-0.045,IF(COUNT($AZ18:$AZ27)=10,AVERAGE($AZ23:$AZ27)/AVERAGE($AZ18:$AZ27)-1<-0.01,FALSE())),0,IF(OR($AZ27/$AZ26-1<=-0.02,IF(COUNT($AZ18:$AZ27)=10,AVERAGE($AZ23:$AZ27)/AVERAGE($AZ18:$AZ27)-1<0.005,FALSE())),50,100)))
A28: 24 | B28: 42592 | C28: 2016 | D28: 三 | E28: 4783.39 | F28: 0.072976 | G28: -0.002577 | H28: 0.898 | I28: 538 | J28: real | K28: 12.05 | L28: =IF(COUNT(F28)=0,50,IF(F28>=0,100,IF(F28>=-0.02,50,0))) -> 100 | M28: =IF(COUNT(G28)=0,50,IF(G28>-0.06,100,IF(G28>-0.15,50,0))) -> 100 | N28: =IF(COUNT(H28)=0,50,IF(H28>=0.6,100,IF(H28>=0.4,50,0))) -> 100 | O28: =IF(COUNT(I28)=0,50,IF(J28="proxy_vix",50,IF(I28<350,100,IF(I28<=450,50,0)))) -> 0 | P28: =IF(COUNT(K28)=0,50,IF(K28<20,100,IF(K28<=25,50,0))) -> 100 | S28: =$E28/$E27-1 -> -0.002577282 | T28: =$K28/$K27-1 -> 0.033447684 | Y28: =IF(AX28>=70,"EASY",IF(AX28>40,"UNCERTAIN","HARD")) -> EASY | AA28: =IF($A28<200,"",AVERAGE($E5:$E28)/AVERAGE($E5:$E28)-1) | AB28: =LOOKUP($B28,07_L1政策步階!$A$4:$A$14,07_L1政策步階!$C$4:$C$14) -> 0 | AL28: =IF(ISNUMBER($AA28),IF($AA28>=0.005,100,IF($AA28>=-0.015,50,0)),"") | AM28: =IF(ISNUMBER($AB28),IF($AB28=1,100,IF($AB28=0,50,0)),"") -> 50 | AN28: =IF(ISNUMBER($AC28),IF($AC28>=0.001,100,IF($AC28>=-0.003,50,0)),"") | AO28: =IF(ISNUMBER($AD28),IF($AD28>=0.04,100,IF($AD28>=0,50,0)),"") | AP28: =IF(ISNUMBER($AE28),IF($AE28>=25,100,IF($AE28>=-75,50,0)),"") | AQ28: =IF(ISNUMBER($AF28),IF($AF28>0,100,IF($AF28>=-50,50,0)),"") | AR28: =IF(ISNUMBER($AG28),IF($AG28=1,100,IF($AG28=0,50,0)),"") | AS28: =IF(ISNUMBER($AH28),IF($AH28<0,100,IF($AH28<=20,50,0)),"") | AT28: =IF(ISNUMBER($AI28),IF($AI28<0.95,100,IF($AI28<=1,50,0)),"") | AU28: =IF(ISNUMBER($AJ28),IF($AJ28<30,0,IF($AJ28<40,50,IF($AJ28<=90,100,50))),"") | AV28: =IF(ISNUMBER($AK28),IF($AK28>-0.2,100,IF($AK28>=-0.4,50,0)),"") | AW28: =01_指標庫!$H$4*ISNUMBER($F28)+01_指標庫!$H$5*ISNUMBER($AA28)+01_指標庫!$H$6*ISNUMBER($G28)+01_指標庫!$H$7*ISNUMBER($H28)+01_指標庫!$H$8*ISNUMBER($AF28)+01_指標庫!$H$9*ISNUMBER($AG28)+01_指標庫!$H$10*ISNUMBER($AB28)+01_指標庫!$H$11*ISNUMBER($AC28)+01_指標庫!$H$12*ISNUMBER($AD28)+01_指標庫!$H$13*ISNUMBER($AE28)+01_指標庫!$H$14*ISNUMBER($I28)+01_指標庫!$H$15*ISNUMBER($AH28)+01_指標庫!$H$16*ISNUMBER($K28)+01_指標庫!$H$17*ISNUMBER($AI28)+01_指標庫!$H$18*ISNUMBER($AJ28)+01_指標庫!$H$19*ISNUMBER($AK28)+01_指標庫!$H$20*ISNUMBER($BB28)+01_指標庫!$H$21*ISNUMBER($BC28) -> 49 | AX28: =IF(AW28=0,50,ROUND((01_指標庫!$H$4*IF(ISNUMBER($F28),L28,0)+01_指標庫!$H$5*IF(ISNUMBER($AA28),AL28,0)+01_指標庫!$H$6*IF(ISNUMBER($G28),M28,0)+01_指標庫!$H$7*IF(ISNUMBER($H28),N28,0)+01_指標庫!$H$8*IF(ISNUMBER($AF28),AQ28,0)+01_指標庫!$H$9*IF(ISNUMBER($AG28),AR28,0)+01_指標庫!$H$10*IF(ISNUMBER($AB28),AM28,0)+01_指標庫!$H$11*IF(ISNUMBER($AC28),AN28,0)+01_指標庫!$H$12*IF(ISNUMBER($AD28),AO28,0)+01_指標庫!$H$13*IF(ISNUMBER($AE28),AP28,0)+01_指標庫!$H$14*IF(ISNUMBER($I28),O28,0)+01_指標庫!$H$15*IF(ISNUMBER($AH28),AS28,0)+01_指標庫!$H$16*IF(ISNUMBER($K28),P28,0)+01_指標庫!$H$17*IF(ISNUMBER($AI28),AT28,0)+01_指標庫!$H$18*IF(ISNUMBER($AJ28),AU28,0)+01_指標庫!$H$19*IF(ISNUMBER($AK28),AV28,0)+01_指標庫!$H$20*IF(ISNUMBER($BB28),BB28,0)+01_指標庫!$H$21*IF(ISNUMBER($BC28),BC28,0))/AW28,1)) -> 72.4 | BA28: =AVERAGE($E24:$E28)/AVERAGE($E19:$E28)-1 -> 0.0049974643 | BB28: =IF(ISNUMBER($BA28),IF(OR($S28<=-0.03,$BA28<-0.003),0,IF(OR($S28<=-0.02,$BA28<0.01),50,100)),"") -> 50 | BC28: =IF(OR(COUNT($AZ28)=0,COUNT($AZ27)=0),"",IF(OR($AY28/$AZ27-1<=-0.03,$AZ28/$AZ27-1<=-0.045,IF(COUNT($AZ19:$AZ28)=10,AVERAGE($AZ24:$AZ28)/AVERAGE($AZ19:$AZ28)-1<-0.01,FALSE())),0,IF(OR($AZ28/$AZ27-1<=-0.02,IF(COUNT($AZ19:$AZ28)=10,AVERAGE($AZ24:$AZ28)/AVERAGE($AZ19:$AZ28)-1<0.005,FALSE())),50,100)))
A29: 25 | B29: 42593 | C29: 2016 | D29: 四 | E29: 4803.31 | F29: 0.077236 | G29: 0 | H29: 0.8776 | I29: 531 | J29: real | K29: 11.68 | L29: =IF(COUNT(F29)=0,50,IF(F29>=0,100,IF(F29>=-0.02,50,0))) -> 100 | M29: =IF(COUNT(G29)=0,50,IF(G29>-0.06,100,IF(G29>-0.15,50,0))) -> 100 | N29: =IF(COUNT(H29)=0,50,IF(H29>=0.6,100,IF(H29>=0.4,50,0))) -> 100 | O29: =IF(COUNT(I29)=0,50,IF(J29="proxy_vix",50,IF(I29<350,100,IF(I29<=450,50,0)))) -> 0 | P29: =IF(COUNT(K29)=0,50,IF(K29<20,100,IF(K29<=25,50,0))) -> 100 | S29: =$E29/$E28-1 -> 0.0041644106 | T29: =$K29/$K28-1 -> -0.030705394 | Y29: =IF(AX29>=70,"EASY",IF(AX29>40,"UNCERTAIN","HARD")) -> EASY | AA29: =IF($A29<200,"",AVERAGE($E5:$E29)/AVERAGE($E5:$E29)-1) | AB29: =LOOKUP($B29,07_L1政策步階!$A$4:$A$14,07_L1政策步階!$C$4:$C$14) -> 0 | AL29: =IF(ISNUMBER($AA29),IF($AA29>=0.005,100,IF($AA29>=-0.015,50,0)),"") | AM29: =IF(ISNUMBER($AB29),IF($AB29=1,100,IF($AB29=0,50,0)),"") -> 50 | AN29: =IF(ISNUMBER($AC29),IF($AC29>=0.001,100,IF($AC29>=-0.003,50,0)),"") | AO29: =IF(ISNUMBER($AD29),IF($AD29>=0.04,100,IF($AD29>=0,50,0)),"") | AP29: =IF(ISNUMBER($AE29),IF($AE29>=25,100,IF($AE29>=-75,50,0)),"") | AQ29: =IF(ISNUMBER($AF29),IF($AF29>0,100,IF($AF29>=-50,50,0)),"") | AR29: =IF(ISNUMBER($AG29),IF($AG29=1,100,IF($AG29=0,50,0)),"") | AS29: =IF(ISNUMBER($AH29),IF($AH29<0,100,IF($AH29<=20,50,0)),"") | AT29: =IF(ISNUMBER($AI29),IF($AI29<0.95,100,IF($AI29<=1,50,0)),"") | AU29: =IF(ISNUMBER($AJ29),IF($AJ29<30,0,IF($AJ29<40,50,IF($AJ29<=90,100,50))),"") | AV29: =IF(ISNUMBER($AK29),IF($AK29>-0.2,100,IF($AK29>=-0.4,50,0)),"") | AW29: =01_指標庫!$H$4*ISNUMBER($F29)+01_指標庫!$H$5*ISNUMBER($AA29)+01_指標庫!$H$6*ISNUMBER($G29)+01_指標庫!$H$7*ISNUMBER($H29)+01_指標庫!$H$8*ISNUMBER($AF29)+01_指標庫!$H$9*ISNUMBER($AG29)+01_指標庫!$H$10*ISNUMBER($AB29)+01_指標庫!$H$11*ISNUMBER($AC29)+01_指標庫!$H$12*ISNUMBER($AD29)+01_指標庫!$H$13*ISNUMBER($AE29)+01_指標庫!$H$14*ISNUMBER($I29)+01_指標庫!$H$15*ISNUMBER($AH29)+01_指標庫!$H$16*ISNUMBER($K29)+01_指標庫!$H$17*ISNUMBER($AI29)+01_指標庫!$H$18*ISNUMBER($AJ29)+01_指標庫!$H$19*ISNUMBER($AK29)+01_指標庫!$H$20*ISNUMBER($BB29)+01_指標庫!$H$21*ISNUMBER($BC29) -> 49 | AX29: =IF(AW29=0,50,ROUND((01_指標庫!$H$4*IF(ISNUMBER($F29),L29,0)+01_指標庫!$H$5*IF(ISNUMBER($AA29),AL29,0)+01_指標庫!$H$6*IF(ISNUMBER($G29),M29,0)+01_指標庫!$H$7*IF(ISNUMBER($H29),N29,0)+01_指標庫!$H$8*IF(ISNUMBER($AF29),AQ29,0)+01_指標庫!$H$9*IF(ISNUMBER($AG29),AR29,0)+01_指標庫!$H$10*IF(ISNUMBER($AB29),AM29,0)+01_指標庫!$H$11*IF(ISNUMBER($AC29),AN29,0)+01_指標庫!$H$12*IF(ISNUMBER($AD29),AO29,0)+01_指標庫!$H$13*IF(ISNUMBER($AE29),AP29,0)+01_指標庫!$H$14*IF(ISNUMBER($I29),O29,0)+01_指標庫!$H$15*IF(ISNUMBER($AH29),AS29,0)+01_指標庫!$H$16*IF(ISNUMBER($K29),P29,0)+01_指標庫!$H$17*IF(ISNUMBER($AI29),AT29,0)+01_指標庫!$H$18*IF(ISNUMBER($AJ29),AU29,0)+01_指標庫!$H$19*IF(ISNUMBER($AK29),AV29,0)+01_指標庫!$H$20*IF(ISNUMBER($BB29),BB29,0)+01_指標庫!$H$21*IF(ISNUMBER($BC29),BC29,0))/AW29,1)) -> 72.4 | BA29: =AVERAGE($E25:$E29)/AVERAGE($E20:$E29)-1 -> 0.0057675976 | BB29: =IF(ISNUMBER($BA29),IF(OR($S29<=-0.03,$BA29<-0.003),0,IF(OR($S29<=-0.02,$BA29<0.01),50,100)),"") -> 50 | BC29: =IF(OR(COUNT($AZ29)=0,COUNT($AZ28)=0),"",IF(OR($AY29/$AZ28-1<=-0.03,$AZ29/$AZ28-1<=-0.045,IF(COUNT($AZ20:$AZ29)=10,AVERAGE($AZ25:$AZ29)/AVERAGE($AZ20:$AZ29)-1<-0.01,FALSE())),0,IF(OR($AZ29/$AZ28-1<=-0.02,IF(COUNT($AZ20:$AZ29)=10,AVERAGE($AZ25:$AZ29)/AVERAGE($AZ20:$AZ29)-1<0.005,FALSE())),50,100)))
A30: 26 | B30: 42594 | C30: 2016 | D30: 五 | E30: 4807.08 | F30: 0.077879 | G30: 0 | H30: 0.8776 | I30: 534 | J30: real | K30: 11.55 | L30: =IF(COUNT(F30)=0,50,IF(F30>=0,100,IF(F30>=-0.02,50,0))) -> 100 | M30: =IF(COUNT(G30)=0,50,IF(G30>-0.06,100,IF(G30>-0.15,50,0))) -> 100 | N30: =IF(COUNT(H30)=0,50,IF(H30>=0.6,100,IF(H30>=0.4,50,0))) -> 100 | O30: =IF(COUNT(I30)=0,50,IF(J30="proxy_vix",50,IF(I30<350,100,IF(I30<=450,50,0)))) -> 0 | P30: =IF(COUNT(K30)=0,50,IF(K30<20,100,IF(K30<=25,50,0))) -> 100 | S30: =$E30/$E29-1 -> 0.00078487543 | T30: =$K30/$K29-1 -> -0.011130137 | Y30: =IF(AX30>=70,"EASY",IF(AX30>40,"UNCERTAIN","HARD")) -> EASY | AA30: =IF($A30<200,"",AVERAGE($E5:$E30)/AVERAGE($E5:$E30)-1) | AB30: =LOOKUP($B30,07_L1政策步階!$A$4:$A$14,07_L1政策步階!$C$4:$C$14) -> 0 | AL30: =IF(ISNUMBER($AA30),IF($AA30>=0.005,100,IF($AA30>=-0.015,50,0)),"") | AM30: =IF(ISNUMBER($AB30),IF($AB30=1,100,IF($AB30=0,50,0)),"") -> 50 | AN30: =IF(ISNUMBER($AC30),IF($AC30>=0.001,100,IF($AC30>=-0.003,50,0)),"") | AO30: =IF(ISNUMBER($AD30),IF($AD30>=0.04,100,IF($AD30>=0,50,0)),"") | AP30: =IF(ISNUMBER($AE30),IF($AE30>=25,100,IF($AE30>=-75,50,0)),"") | AQ30: =IF(ISNUMBER($AF30),IF($AF30>0,100,IF($AF30>=-50,50,0)),"") | AR30: =IF(ISNUMBER($AG30),IF($AG30=1,100,IF($AG30=0,50,0)),"") | AS30: =IF(ISNUMBER($AH30),IF($AH30<0,100,IF($AH30<=20,50,0)),"") | AT30: =IF(ISNUMBER($AI30),IF($AI30<0.95,100,IF($AI30<=1,50,0)),"") | AU30: =IF(ISNUMBER($AJ30),IF($AJ30<30,0,IF($AJ30<40,50,IF($AJ30<=90,100,50))),"") | AV30: =IF(ISNUMBER($AK30),IF($AK30>-0.2,100,IF($AK30>=-0.4,50,0)),"") | AW30: =01_指標庫!$H$4*ISNUMBER($F30)+01_指標庫!$H$5*ISNUMBER($AA30)+01_指標庫!$H$6*ISNUMBER($G30)+01_指標庫!$H$7*ISNUMBER($H30)+01_指標庫!$H$8*ISNUMBER($AF30)+01_指標庫!$H$9*ISNUMBER($AG30)+01_指標庫!$H$10*ISNUMBER($AB30)+01_指標庫!$H$11*ISNUMBER($AC30)+01_指標庫!$H$12*ISNUMBER($AD30)+01_指標庫!$H$13*ISNUMBER($AE30)+01_指標庫!$H$14*ISNUMBER($I30)+01_指標庫!$H$15*ISNUMBER($AH30)+01_指標庫!$H$16*ISNUMBER($K30)+01_指標庫!$H$17*ISNUMBER($AI30)+01_指標庫!$H$18*ISNUMBER($AJ30)+01_指標庫!$H$19*ISNUMBER($AK30)+01_指標庫!$H$20*ISNUMBER($BB30)+01_指標庫!$H$21*ISNUMBER($BC30) -> 49 | AX30: =IF(AW30=0,50,ROUND((01_指標庫!$H$4*IF(ISNUMBER($F30),L30,0)+01_指標庫!$H$5*IF(ISNUMBER($AA30),AL30,0)+01_指標庫!$H$6*IF(ISNUMBER($G30),M30,0)+01_指標庫!$H$7*IF(ISNUMBER($H30),N30,0)+01_指標庫!$H$8*IF(ISNUMBER($AF30),AQ30,0)+01_指標庫!$H$9*IF(ISNUMBER($AG30),AR30,0)+01_指標庫!$H$10*IF(ISNUMBER($AB30),AM30,0)+01_指標庫!$H$11*IF(ISNUMBER($AC30),AN30,0)+01_指標庫!$H$12*IF(ISNUMBER($AD30),AO30,0)+01_指標庫!$H$13*IF(ISNUMBER($AE30),AP30,0)+01_指標庫!$H$14*IF(ISNUMBER($I30),O30,0)+01_指標庫!$H$15*IF(ISNUMBER($AH30),AS30,0)+01_指標庫!$H$16*IF(ISNUMBER($K30),P30,0)+01_指標庫!$H$17*IF(ISNUMBER($AI30),AT30,0)+01_指標庫!$H$18*IF(ISNUMBER($AJ30),AU30,0)+01_指標庫!$H$19*IF(ISNUMBER($AK30),AV30,0)+01_指標庫!$H$20*IF(ISNUMBER($BB30),BB30,0)+01_指標庫!$H$21*IF(ISNUMBER($BC30),BC30,0))/AW30,1)) -> 72.4 | BA30: =AVERAGE($E26:$E30)/AVERAGE($E21:$E30)-1 -> 0.0048129807 | BB30: =IF(ISNUMBER($BA30),IF(OR($S30<=-0.03,$BA30<-0.003),0,IF(OR($S30<=-0.02,$BA30<0.01),50,100)),"") -> 50 | BC30: =IF(OR(COUNT($AZ30)=0,COUNT($AZ29)=0),"",IF(OR($AY30/$AZ29-1<=-0.03,$AZ30/$AZ29-1<=-0.045,IF(COUNT($AZ21:$AZ30)=10,AVERAGE($AZ26:$AZ30)/AVERAGE($AZ21:$AZ30)-1<-0.01,FALSE())),0,IF(OR($AZ30/$AZ29-1<=-0.02,IF(COUNT($AZ21:$AZ30)=10,AVERAGE($AZ26:$AZ30)/AVERAGE($AZ21:$AZ30)-1<0.005,FALSE())),50,100)))
A31: 27 | B31: 42597 | C31: 2016 | D31: 一 | E31: 4827.12 | F31: 0.082192 | G31: 0 | H31: 0.898 | I31: 523 | J31: real | K31: 11.81 | L31: =IF(COUNT(F31)=0,50,IF(F31>=0,100,IF(F31>=-0.02,50,0))) -> 100 | M31: =IF(COUNT(G31)=0,50,IF(G31>-0.06,100,IF(G31>-0.15,50,0))) -> 100 | N31: =IF(COUNT(H31)=0,50,IF(H31>=0.6,100,IF(H31>=0.4,50,0))) -> 100 | O31: =IF(COUNT(I31)=0,50,IF(J31="proxy_vix",50,IF(I31<350,100,IF(I31<=450,50,0)))) -> 0 | P31: =IF(COUNT(K31)=0,50,IF(K31<20,100,IF(K31<=25,50,0))) -> 100 | S31: =$E31/$E30-1 -> 0.0041688509 | T31: =$K31/$K30-1 -> 0.022510823 | Y31: =IF(AX31>=70,"EASY",IF(AX31>40,"UNCERTAIN","HARD")) -> EASY | AA31: =IF($A31<200,"",AVERAGE($E5:$E31)/AVERAGE($E5:$E31)-1) | AB31: =LOOKUP($B31,07_L1政策步階!$A$4:$A$14,07_L1政策步階!$C$4:$C$14) -> 0 | AL31: =IF(ISNUMBER($AA31),IF($AA31>=0.005,100,IF($AA31>=-0.015,50,0)),"") | AM31: =IF(ISNUMBER($AB31),IF($AB31=1,100,IF($AB31=0,50,0)),"") -> 50 | AN31: =IF(ISNUMBER($AC31),IF($AC31>=0.001,100,IF($AC31>=-0.003,50,0)),"") | AO31: =IF(ISNUMBER($AD31),IF($AD31>=0.04,100,IF($AD31>=0,50,0)),"") | AP31: =IF(ISNUMBER($AE31),IF($AE31>=25,100,IF($AE31>=-75,50,0)),"") | AQ31: =IF(ISNUMBER($AF31),IF($AF31>0,100,IF($AF31>=-50,50,0)),"") | AR31: =IF(ISNUMBER($AG31),IF($AG31=1,100,IF($AG31=0,50,0)),"") | AS31: =IF(ISNUMBER($AH31),IF($AH31<0,100,IF($AH31<=20,50,0)),"") | AT31: =IF(ISNUMBER($AI31),IF($AI31<0.95,100,IF($AI31<=1,50,0)),"") | AU31: =IF(ISNUMBER($AJ31),IF($AJ31<30,0,IF($AJ31<40,50,IF($AJ31<=90,100,50))),"") | AV31: =IF(ISNUMBER($AK31),IF($AK31>-0.2,100,IF($AK31>=-0.4,50,0)),"") | AW31: =01_指標庫!$H$4*ISNUMBER($F31)+01_指標庫!$H$5*ISNUMBER($AA31)+01_指標庫!$H$6*ISNUMBER($G31)+01_指標庫!$H$7*ISNUMBER($H31)+01_指標庫!$H$8*ISNUMBER($AF31)+01_指標庫!$H$9*ISNUMBER($AG31)+01_指標庫!$H$10*ISNUMBER($AB31)+01_指標庫!$H$11*ISNUMBER($AC31)+01_指標庫!$H$12*ISNUMBER($AD31)+01_指標庫!$H$13*ISNUMBER($AE31)+01_指標庫!$H$14*ISNUMBER($I31)+01_指標庫!$H$15*ISNUMBER($AH31)+01_指標庫!$H$16*ISNUMBER($K31)+01_指標庫!$H$17*ISNUMBER($AI31)+01_指標庫!$H$18*ISNUMBER($AJ31)+01_指標庫!$H$19*ISNUMBER($AK31)+01_指標庫!$H$20*ISNUMBER($BB31)+01_指標庫!$H$21*ISNUMBER($BC31) -> 49 | AX31: =IF(AW31=0,50,ROUND((01_指標庫!$H$4*IF(ISNUMBER($F31),L31,0)+01_指標庫!$H$5*IF(ISNUMBER($AA31),AL31,0)+01_指標庫!$H$6*IF(ISNUMBER($G31),M31,0)+01_指標庫!$H$7*IF(ISNUMBER($H31),N31,0)+01_指標庫!$H$8*IF(ISNUMBER($AF31),AQ31,0)+01_指標庫!$H$9*IF(ISNUMBER($AG31),AR31,0)+01_指標庫!$H$10*IF(ISNUMBER($AB31),AM31,0)+01_指標庫!$H$11*IF(ISNUMBER($AC31),AN31,0)+01_指標庫!$H$12*IF(ISNUMBER($AD31),AO31,0)+01_指標庫!$H$13*IF(ISNUMBER($AE31),AP31,0)+01_指標庫!$H$14*IF(ISNUMBER($I31),O31,0)+01_指標庫!$H$15*IF(ISNUMBER($AH31),AS31,0)+01_指標庫!$H$16*IF(ISNUMBER($K31),P31,0)+01_指標庫!$H$17*IF(ISNUMBER($AI31),AT31,0)+01_指標庫!$H$18*IF(ISNUMBER($AJ31),AU31,0)+01_指標庫!$H$19*IF(ISNUMBER($AK31),AV31,0)+01_指標庫!$H$20*IF(ISNUMBER($BB31),BB31,0)+01_指標庫!$H$21*IF(ISNUMBER($BC31),BC31,0))/AW31,1)) -> 72.4 | BA31: =AVERAGE($E27:$E31)/AVERAGE($E22:$E31)-1 -> 0.0050920748 | BB31: =IF(ISNUMBER($BA31),IF(OR($S31<=-0.03,$BA31<-0.003),0,IF(OR($S31<=-0.02,$BA31<0.01),50,100)),"") -> 50 | BC31: =IF(OR(COUNT($AZ31)=0,COUNT($AZ30)=0),"",IF(OR($AY31/$AZ30-1<=-0.03,$AZ31/$AZ30-1<=-0.045,IF(COUNT($AZ22:$AZ31)=10,AVERAGE($AZ27:$AZ31)/AVERAGE($AZ22:$AZ31)-1<-0.01,FALSE())),0,IF(OR($AZ31/$AZ30-1<=-0.02,IF(COUNT($AZ22:$AZ31)=10,AVERAGE($AZ27:$AZ31)/AVERAGE($AZ22:$AZ31)-1<0.005,FALSE())),50,100)))
A32: 28 | B32: 42598 | C32: 2016 | D32: 二 | E32: 4797.19 | F32: 0.07533 | G32: -0.0062 | H32: 0.898 | I32: 517 | J32: real | K32: 12.64 | L32: =IF(COUNT(F32)=0,50,IF(F32>=0,100,IF(F32>=-0.02,50,0))) -> 100 | M32: =IF(COUNT(G32)=0,50,IF(G32>-0.06,100,IF(G32>-0.15,50,0))) -> 100 | N32: =IF(COUNT(H32)=0,50,IF(H32>=0.6,100,IF(H32>=0.4,50,0))) -> 100 | O32: =IF(COUNT(I32)=0,50,IF(J32="proxy_vix",50,IF(I32<350,100,IF(I32<=450,50,0)))) -> 0 | P32: =IF(COUNT(K32)=0,50,IF(K32<20,100,IF(K32<=25,50,0))) -> 100 | S32: =$E32/$E31-1 -> -0.0062003845 | T32: =$K32/$K31-1 -> 0.070279424 | Y32: =IF(AX32>=70,"EASY",IF(AX32>40,"UNCERTAIN","HARD")) -> EASY | AA32: =IF($A32<200,"",AVERAGE($E5:$E32)/AVERAGE($E5:$E32)-1) | AB32: =LOOKUP($B32,07_L1政策步階!$A$4:$A$14,07_L1政策步階!$C$4:$C$14) -> 0 | AL32: =IF(ISNUMBER($AA32),IF($AA32>=0.005,100,IF($AA32>=-0.015,50,0)),"") | AM32: =IF(ISNUMBER($AB32),IF($AB32=1,100,IF($AB32=0,50,0)),"") -> 50 | AN32: =IF(ISNUMBER($AC32),IF($AC32>=0.001,100,IF($AC32>=-0.003,50,0)),"") | AO32: =IF(ISNUMBER($AD32),IF($AD32>=0.04,100,IF($AD32>=0,50,0)),"") | AP32: =IF(ISNUMBER($AE32),IF($AE32>=25,100,IF($AE32>=-75,50,0)),"") | AQ32: =IF(ISNUMBER($AF32),IF($AF32>0,100,IF($AF32>=-50,50,0)),"") | AR32: =IF(ISNUMBER($AG32),IF($AG32=1,100,IF($AG32=0,50,0)),"") | AS32: =IF(ISNUMBER($AH32),IF($AH32<0,100,IF($AH32<=20,50,0)),"") | AT32: =IF(ISNUMBER($AI32),IF($AI32<0.95,100,IF($AI32<=1,50,0)),"") | AU32: =IF(ISNUMBER($AJ32),IF($AJ32<30,0,IF($AJ32<40,50,IF($AJ32<=90,100,50))),"") | AV32: =IF(ISNUMBER($AK32),IF($AK32>-0.2,100,IF($AK32>=-0.4,50,0)),"") | AW32: =01_指標庫!$H$4*ISNUMBER($F32)+01_指標庫!$H$5*ISNUMBER($AA32)+01_指標庫!$H$6*ISNUMBER($G32)+01_指標庫!$H$7*ISNUMBER($H32)+01_指標庫!$H$8*ISNUMBER($AF32)+01_指標庫!$H$9*ISNUMBER($AG32)+01_指標庫!$H$10*ISNUMBER($AB32)+01_指標庫!$H$11*ISNUMBER($AC32)+01_指標庫!$H$12*ISNUMBER($AD32)+01_指標庫!$H$13*ISNUMBER($AE32)+01_指標庫!$H$14*ISNUMBER($I32)+01_指標庫!$H$15*ISNUMBER($AH32)+01_指標庫!$H$16*ISNUMBER($K32)+01_指標庫!$H$17*ISNUMBER($AI32)+01_指標庫!$H$18*ISNUMBER($AJ32)+01_指標庫!$H$19*ISNUMBER($AK32)+01_指標庫!$H$20*ISNUMBER($BB32)+01_指標庫!$H$21*ISNUMBER($BC32) -> 49 | AX32: =IF(AW32=0,50,ROUND((01_指標庫!$H$4*IF(ISNUMBER($F32),L32,0)+01_指標庫!$H$5*IF(ISNUMBER($AA32),AL32,0)+01_指標庫!$H$6*IF(ISNUMBER($G32),M32,0)+01_指標庫!$H$7*IF(ISNUMBER($H32),N32,0)+01_指標庫!$H$8*IF(ISNUMBER($AF32),AQ32,0)+01_指標庫!$H$9*IF(ISNUMBER($AG32),AR32,0)+01_指標庫!$H$10*IF(ISNUMBER($AB32),AM32,0)+01_指標庫!$H$11*IF(ISNUMBER($AC32),AN32,0)+01_指標庫!$H$12*IF(ISNUMBER($AD32),AO32,0)+01_指標庫!$H$13*IF(ISNUMBER($AE32),AP32,0)+01_指標庫!$H$14*IF(ISNUMBER($I32),O32,0)+01_指標庫!$H$15*IF(ISNUMBER($AH32),AS32,0)+01_指標庫!$H$16*IF(ISNUMBER($K32),P32,0)+01_指標庫!$H$17*IF(ISNUMBER($AI32),AT32,0)+01_指標庫!$H$18*IF(ISNUMBER($AJ32),AU32,0)+01_指標庫!$H$19*IF(ISNUMBER($AK32),AV32,0)+01_指標庫!$H$20*IF(ISNUMBER($BB32),BB32,0)+01_指標庫!$H$21*IF(ISNUMBER($BC32),BC32,0))/AW32,1)) -> 72.4 | BA32: =AVERAGE($E28:$E32)/AVERAGE($E23:$E32)-1 -> 0.0035148794 | BB32: =IF(ISNUMBER($BA32),IF(OR($S32<=-0.03,$BA32<-0.003),0,IF(OR($S32<=-0.02,$BA32<0.01),50,100)),"") -> 50 | BC32: =IF(OR(COUNT($AZ32)=0,COUNT($AZ31)=0),"",IF(OR($AY32/$AZ31-1<=-0.03,$AZ32/$AZ31-1<=-0.045,IF(COUNT($AZ23:$AZ32)=10,AVERAGE($AZ28:$AZ32)/AVERAGE($AZ23:$AZ32)-1<-0.01,FALSE())),0,IF(OR($AZ32/$AZ31-1<=-0.02,IF(COUNT($AZ23:$AZ32)=10,AVERAGE($AZ28:$AZ32)/AVERAGE($AZ23:$AZ32)-1<0.005,FALSE())),50,100)))
A33: 29 | B33: 42599 | C33: 2016 | D33: 三 | E33: 4805.45 | F33: 0.076992 | G33: -0.004489 | H33: 0.898 | I33: 519 | J33: real | K33: 12.19 | L33: =IF(COUNT(F33)=0,50,IF(F33>=0,100,IF(F33>=-0.02,50,0))) -> 100 | M33: =IF(COUNT(G33)=0,50,IF(G33>-0.06,100,IF(G33>-0.15,50,0))) -> 100 | N33: =IF(COUNT(H33)=0,50,IF(H33>=0.6,100,IF(H33>=0.4,50,0))) -> 100 | O33: =IF(COUNT(I33)=0,50,IF(J33="proxy_vix",50,IF(I33<350,100,IF(I33<=450,50,0)))) -> 0 | P33: =IF(COUNT(K33)=0,50,IF(K33<20,100,IF(K33<=25,50,0))) -> 100 | S33: =$E33/$E32-1 -> 0.0017218413 | T33: =$K33/$K32-1 -> -0.035601266 | Y33: =IF(AX33>=70,"EASY",IF(AX33>40,"UNCERTAIN","HARD")) -> EASY | AA33: =IF($A33<200,"",AVERAGE($E5:$E33)/AVERAGE($E5:$E33)-1) | AB33: =LOOKUP($B33,07_L1政策步階!$A$4:$A$14,07_L1政策步階!$C$4:$C$14) -> 0 | AL33: =IF(ISNUMBER($AA33),IF($AA33>=0.005,100,IF($AA33>=-0.015,50,0)),"") | AM33: =IF(ISNUMBER($AB33),IF($AB33=1,100,IF($AB33=0,50,0)),"") -> 50 | AN33: =IF(ISNUMBER($AC33),IF($AC33>=0.001,100,IF($AC33>=-0.003,50,0)),"") | AO33: =IF(ISNUMBER($AD33),IF($AD33>=0.04,100,IF($AD33>=0,50,0)),"") | AP33: =IF(ISNUMBER($AE33),IF($AE33>=25,100,IF($AE33>=-75,50,0)),"") | AQ33: =IF(ISNUMBER($AF33),IF($AF33>0,100,IF($AF33>=-50,50,0)),"") | AR33: =IF(ISNUMBER($AG33),IF($AG33=1,100,IF($AG33=0,50,0)),"") | AS33: =IF(ISNUMBER($AH33),IF($AH33<0,100,IF($AH33<=20,50,0)),"") | AT33: =IF(ISNUMBER($AI33),IF($AI33<0.95,100,IF($AI33<=1,50,0)),"") | AU33: =IF(ISNUMBER($AJ33),IF($AJ33<30,0,IF($AJ33<40,50,IF($AJ33<=90,100,50))),"") | AV33: =IF(ISNUMBER($AK33),IF($AK33>-0.2,100,IF($AK33>=-0.4,50,0)),"") | AW33: =01_指標庫!$H$4*ISNUMBER($F33)+01_指標庫!$H$5*ISNUMBER($AA33)+01_指標庫!$H$6*ISNUMBER($G33)+01_指標庫!$H$7*ISNUMBER($H33)+01_指標庫!$H$8*ISNUMBER($AF33)+01_指標庫!$H$9*ISNUMBER($AG33)+01_指標庫!$H$10*ISNUMBER($AB33)+01_指標庫!$H$11*ISNUMBER($AC33)+01_指標庫!$H$12*ISNUMBER($AD33)+01_指標庫!$H$13*ISNUMBER($AE33)+01_指標庫!$H$14*ISNUMBER($I33)+01_指標庫!$H$15*ISNUMBER($AH33)+01_指標庫!$H$16*ISNUMBER($K33)+01_指標庫!$H$17*ISNUMBER($AI33)+01_指標庫!$H$18*ISNUMBER($AJ33)+01_指標庫!$H$19*ISNUMBER($AK33)+01_指標庫!$H$20*ISNUMBER($BB33)+01_指標庫!$H$21*ISNUMBER($BC33) -> 49 | AX33: =IF(AW33=0,50,ROUND((01_指標庫!$H$4*IF(ISNUMBER($F33),L33,0)+01_指標庫!$H$5*IF(ISNUMBER($AA33),AL33,0)+01_指標庫!$H$6*IF(ISNUMBER($G33),M33,0)+01_指標庫!$H$7*IF(ISNUMBER($H33),N33,0)+01_指標庫!$H$8*IF(ISNUMBER($AF33),AQ33,0)+01_指標庫!$H$9*IF(ISNUMBER($AG33),AR33,0)+01_指標庫!$H$10*IF(ISNUMBER($AB33),AM33,0)+01_指標庫!$H$11*IF(ISNUMBER($AC33),AN33,0)+01_指標庫!$H$12*IF(ISNUMBER($AD33),AO33,0)+01_指標庫!$H$13*IF(ISNUMBER($AE33),AP33,0)+01_指標庫!$H$14*IF(ISNUMBER($I33),O33,0)+01_指標庫!$H$15*IF(ISNUMBER($AH33),AS33,0)+01_指標庫!$H$16*IF(ISNUMBER($K33),P33,0)+01_指標庫!$H$17*IF(ISNUMBER($AI33),AT33,0)+01_指標庫!$H$18*IF(ISNUMBER($AJ33),AU33,0)+01_指標庫!$H$19*IF(ISNUMBER($AK33),AV33,0)+01_指標庫!$H$20*IF(ISNUMBER($BB33),BB33,0)+01_指標庫!$H$21*IF(ISNUMBER($BC33),BC33,0))/AW33,1)) -> 72.4 | BA33: =AVERAGE($E29:$E33)/AVERAGE($E24:$E33)-1 -> 0.0029464497 | BB33: =IF(ISNUMBER($BA33),IF(OR($S33<=-0.03,$BA33<-0.003),0,IF(OR($S33<=-0.02,$BA33<0.01),50,100)),"") -> 50 | BC33: =IF(OR(COUNT($AZ33)=0,COUNT($AZ32)=0),"",IF(OR($AY33/$AZ32-1<=-0.03,$AZ33/$AZ32-1<=-0.045,IF(COUNT($AZ24:$AZ33)=10,AVERAGE($AZ29:$AZ33)/AVERAGE($AZ24:$AZ33)-1<-0.01,FALSE())),0,IF(OR($AZ33/$AZ32-1<=-0.02,IF(COUNT($AZ24:$AZ33)=10,AVERAGE($AZ29:$AZ33)/AVERAGE($AZ24:$AZ33)-1<0.005,FALSE())),50,100)))
A34: 30 | B34: 42600 | C34: 2016 | D34: 四 | E34: 4808.68 | F34: 0.07759 | G34: -0.00382 | H34: 0.898 | I34: 520 | J34: real | K34: 11.43 | L34: =IF(COUNT(F34)=0,50,IF(F34>=0,100,IF(F34>=-0.02,50,0))) -> 100 | M34: =IF(COUNT(G34)=0,50,IF(G34>-0.06,100,IF(G34>-0.15,50,0))) -> 100 | N34: =IF(COUNT(H34)=0,50,IF(H34>=0.6,100,IF(H34>=0.4,50,0))) -> 100 | O34: =IF(COUNT(I34)=0,50,IF(J34="proxy_vix",50,IF(I34<350,100,IF(I34<=450,50,0)))) -> 0 | P34: =IF(COUNT(K34)=0,50,IF(K34<20,100,IF(K34<=25,50,0))) -> 100 | S34: =$E34/$E33-1 -> 0.00067215349 | T34: =$K34/$K33-1 -> -0.062346185 | Y34: =IF(AX34>=70,"EASY",IF(AX34>40,"UNCERTAIN","HARD")) -> EASY | AA34: =IF($A34<200,"",AVERAGE($E5:$E34)/AVERAGE($E5:$E34)-1) | AB34: =LOOKUP($B34,07_L1政策步階!$A$4:$A$14,07_L1政策步階!$C$4:$C$14) -> 0 | AL34: =IF(ISNUMBER($AA34),IF($AA34>=0.005,100,IF($AA34>=-0.015,50,0)),"") | AM34: =IF(ISNUMBER($AB34),IF($AB34=1,100,IF($AB34=0,50,0)),"") -> 50 | AN34: =IF(ISNUMBER($AC34),IF($AC34>=0.001,100,IF($AC34>=-0.003,50,0)),"") | AO34: =IF(ISNUMBER($AD34),IF($AD34>=0.04,100,IF($AD34>=0,50,0)),"") | AP34: =IF(ISNUMBER($AE34),IF($AE34>=25,100,IF($AE34>=-75,50,0)),"") | AQ34: =IF(ISNUMBER($AF34),IF($AF34>0,100,IF($AF34>=-50,50,0)),"") | AR34: =IF(ISNUMBER($AG34),IF($AG34=1,100,IF($AG34=0,50,0)),"") | AS34: =IF(ISNUMBER($AH34),IF($AH34<0,100,IF($AH34<=20,50,0)),"") | AT34: =IF(ISNUMBER($AI34),IF($AI34<0.95,100,IF($AI34<=1,50,0)),"") | AU34: =IF(ISNUMBER($AJ34),IF($AJ34<30,0,IF($AJ34<40,50,IF($AJ34<=90,100,50))),"") | AV34: =IF(ISNUMBER($AK34),IF($AK34>-0.2,100,IF($AK34>=-0.4,50,0)),"") | AW34: =01_指標庫!$H$4*ISNUMBER($F34)+01_指標庫!$H$5*ISNUMBER($AA34)+01_指標庫!$H$6*ISNUMBER($G34)+01_指標庫!$H$7*ISNUMBER($H34)+01_指標庫!$H$8*ISNUMBER($AF34)+01_指標庫!$H$9*ISNUMBER($AG34)+01_指標庫!$H$10*ISNUMBER($AB34)+01_指標庫!$H$11*ISNUMBER($AC34)+01_指標庫!$H$12*ISNUMBER($AD34)+01_指標庫!$H$13*ISNUMBER($AE34)+01_指標庫!$H$14*ISNUMBER($I34)+01_指標庫!$H$15*ISNUMBER($AH34)+01_指標庫!$H$16*ISNUMBER($K34)+01_指標庫!$H$17*ISNUMBER($AI34)+01_指標庫!$H$18*ISNUMBER($AJ34)+01_指標庫!$H$19*ISNUMBER($AK34)+01_指標庫!$H$20*ISNUMBER($BB34)+01_指標庫!$H$21*ISNUMBER($BC34) -> 49 | AX34: =IF(AW34=0,50,ROUND((01_指標庫!$H$4*IF(ISNUMBER($F34),L34,0)+01_指標庫!$H$5*IF(ISNUMBER($AA34),AL34,0)+01_指標庫!$H$6*IF(ISNUMBER($G34),M34,0)+01_指標庫!$H$7*IF(ISNUMBER($H34),N34,0)+01_指標庫!$H$8*IF(ISNUMBER($AF34),AQ34,0)+01_指標庫!$H$9*IF(ISNUMBER($AG34),AR34,0)+01_指標庫!$H$10*IF(ISNUMBER($AB34),AM34,0)+01_指標庫!$H$11*IF(ISNUMBER($AC34),AN34,0)+01_指標庫!$H$12*IF(ISNUMBER($AD34),AO34,0)+01_指標庫!$H$13*IF(ISNUMBER($AE34),AP34,0)+01_指標庫!$H$14*IF(ISNUMBER($I34),O34,0)+01_指標庫!$H$15*IF(ISNUMBER($AH34),AS34,0)+01_指標庫!$H$16*IF(ISNUMBER($K34),P34,0)+01_指標庫!$H$17*IF(ISNUMBER($AI34),AT34,0)+01_指標庫!$H$18*IF(ISNUMBER($AJ34),AU34,0)+01_指標庫!$H$19*IF(ISNUMBER($AK34),AV34,0)+01_指標庫!$H$20*IF(ISNUMBER($BB34),BB34,0)+01_指標庫!$H$21*IF(ISNUMBER($BC34),BC34,0))/AW34,1)) -> 72.4 | BA34: =AVERAGE($E30:$E34)/AVERAGE($E25:$E34)-1 -> 0.0018148518 | BB34: =IF(ISNUMBER($BA34),IF(OR($S34<=-0.03,$BA34<-0.003),0,IF(OR($S34<=-0.02,$BA34<0.01),50,100)),"") -> 50 | BC34: =IF(OR(COUNT($AZ34)=0,COUNT($AZ33)=0),"",IF(OR($AY34/$AZ33-1<=-0.03,$AZ34/$AZ33-1<=-0.045,IF(COUNT($AZ25:$AZ34)=10,AVERAGE($AZ30:$AZ34)/AVERAGE($AZ25:$AZ34)-1<-0.01,FALSE())),0,IF(OR($AZ34/$AZ33-1<=-0.02,IF(COUNT($AZ25:$AZ34)=10,AVERAGE($AZ30:$AZ34)/AVERAGE($AZ25:$AZ34)-1<0.005,FALSE())),50,100)))
A35: 31 | B35: 42601 | C35: 2016 | D35: 五 | E35: 4806.14 | F35: 0.076915 | G35: -0.004346 | H35: 0.898 | I35: 515 | J35: real | K35: 11.34 | L35: =IF(COUNT(F35)=0,50,IF(F35>=0,100,IF(F35>=-0.02,50,0))) -> 100 | M35: =IF(COUNT(G35)=0,50,IF(G35>-0.06,100,IF(G35>-0.15,50,0))) -> 100 | N35: =IF(COUNT(H35)=0,50,IF(H35>=0.6,100,IF(H35>=0.4,50,0))) -> 100 | O35: =IF(COUNT(I35)=0,50,IF(J35="proxy_vix",50,IF(I35<350,100,IF(I35<=450,50,0)))) -> 0 | P35: =IF(COUNT(K35)=0,50,IF(K35<20,100,IF(K35<=25,50,0))) -> 100 | S35: =$E35/$E34-1 -> -0.00052821148 | T35: =$K35/$K34-1 -> -0.0078740157 | Y35: =IF(AX35>=70,"EASY",IF(AX35>40,"UNCERTAIN","HARD")) -> EASY | AA35: =IF($A35<200,"",AVERAGE($E5:$E35)/AVERAGE($E5:$E35)-1) | AB35: =LOOKUP($B35,07_L1政策步階!$A$4:$A$14,07_L1政策步階!$C$4:$C$14) -> 0 | AL35: =IF(ISNUMBER($AA35),IF($AA35>=0.005,100,IF($AA35>=-0.015,50,0)),"") | AM35: =IF(ISNUMBER($AB35),IF($AB35=1,100,IF($AB35=0,50,0)),"") -> 50 | AN35: =IF(ISNUMBER($AC35),IF($AC35>=0.001,100,IF($AC35>=-0.003,50,0)),"") | AO35: =IF(ISNUMBER($AD35),IF($AD35>=0.04,100,IF($AD35>=0,50,0)),"") | AP35: =IF(ISNUMBER($AE35),IF($AE35>=25,100,IF($AE35>=-75,50,0)),"") | AQ35: =IF(ISNUMBER($AF35),IF($AF35>0,100,IF($AF35>=-50,50,0)),"") | AR35: =IF(ISNUMBER($AG35),IF($AG35=1,100,IF($AG35=0,50,0)),"") | AS35: =IF(ISNUMBER($AH35),IF($AH35<0,100,IF($AH35<=20,50,0)),"") | AT35: =IF(ISNUMBER($AI35),IF($AI35<0.95,100,IF($AI35<=1,50,0)),"") | AU35: =IF(ISNUMBER($AJ35),IF($AJ35<30,0,IF($AJ35<40,50,IF($AJ35<=90,100,50))),"") | AV35: =IF(ISNUMBER($AK35),IF($AK35>-0.2,100,IF($AK35>=-0.4,50,0)),"") | AW35: =01_指標庫!$H$4*ISNUMBER($F35)+01_指標庫!$H$5*ISNUMBER($AA35)+01_指標庫!$H$6*ISNUMBER($G35)+01_指標庫!$H$7*ISNUMBER($H35)+01_指標庫!$H$8*ISNUMBER($AF35)+01_指標庫!$H$9*ISNUMBER($AG35)+01_指標庫!$H$10*ISNUMBER($AB35)+01_指標庫!$H$11*ISNUMBER($AC35)+01_指標庫!$H$12*ISNUMBER($AD35)+01_指標庫!$H$13*ISNUMBER($AE35)+01_指標庫!$H$14*ISNUMBER($I35)+01_指標庫!$H$15*ISNUMBER($AH35)+01_指標庫!$H$16*ISNUMBER($K35)+01_指標庫!$H$17*ISNUMBER($AI35)+01_指標庫!$H$18*ISNUMBER($AJ35)+01_指標庫!$H$19*ISNUMBER($AK35)+01_指標庫!$H$20*ISNUMBER($BB35)+01_指標庫!$H$21*ISNUMBER($BC35) -> 49 | AX35: =IF(AW35=0,50,ROUND((01_指標庫!$H$4*IF(ISNUMBER($F35),L35,0)+01_指標庫!$H$5*IF(ISNUMBER($AA35),AL35,0)+01_指標庫!$H$6*IF(ISNUMBER($G35),M35,0)+01_指標庫!$H$7*IF(ISNUMBER($H35),N35,0)+01_指標庫!$H$8*IF(ISNUMBER($AF35),AQ35,0)+01_指標庫!$H$9*IF(ISNUMBER($AG35),AR35,0)+01_指標庫!$H$10*IF(ISNUMBER($AB35),AM35,0)+01_指標庫!$H$11*IF(ISNUMBER($AC35),AN35,0)+01_指標庫!$H$12*IF(ISNUMBER($AD35),AO35,0)+01_指標庫!$H$13*IF(ISNUMBER($AE35),AP35,0)+01_指標庫!$H$14*IF(ISNUMBER($I35),O35,0)+01_指標庫!$H$15*IF(ISNUMBER($AH35),AS35,0)+01_指標庫!$H$16*IF(ISNUMBER($K35),P35,0)+01_指標庫!$H$17*IF(ISNUMBER($AI35),AT35,0)+01_指標庫!$H$18*IF(ISNUMBER($AJ35),AU35,0)+01_指標庫!$H$19*IF(ISNUMBER($AK35),AV35,0)+01_指標庫!$H$20*IF(ISNUMBER($BB35),BB35,0)+01_指標庫!$H$21*IF(ISNUMBER($BC35),BC35,0))/AW35,1)) -> 72.4 | BA35: =AVERAGE($E31:$E35)/AVERAGE($E26:$E35)-1 -> 0.0014642167 | BB35: =IF(ISNUMBER($BA35),IF(OR($S35<=-0.03,$BA35<-0.003),0,IF(OR($S35<=-0.02,$BA35<0.01),50,100)),"") -> 50 | BC35: =IF(OR(COUNT($AZ35)=0,COUNT($AZ34)=0),"",IF(OR($AY35/$AZ34-1<=-0.03,$AZ35/$AZ34-1<=-0.045,IF(COUNT($AZ26:$AZ35)=10,AVERAGE($AZ31:$AZ35)/AVERAGE($AZ26:$AZ35)-1<-0.01,FALSE())),0,IF(OR($AZ35/$AZ34-1<=-0.02,IF(COUNT($AZ26:$AZ35)=10,AVERAGE($AZ31:$AZ35)/AVERAGE($AZ26:$AZ35)-1<0.005,FALSE())),50,100)))
A36: 32 | B36: 42604 | C36: 2016 | D36: 一 | E36: 4808.56 | F36: 0.077348 | G36: -0.003845 | H36: 0.898 | I36: 518 | J36: real | K36: 12.27 | L36: =IF(COUNT(F36)=0,50,IF(F36>=0,100,IF(F36>=-0.02,50,0))) -> 100 | M36: =IF(COUNT(G36)=0,50,IF(G36>-0.06,100,IF(G36>-0.15,50,0))) -> 100 | N36: =IF(COUNT(H36)=0,50,IF(H36>=0.6,100,IF(H36>=0.4,50,0))) -> 100 | O36: =IF(COUNT(I36)=0,50,IF(J36="proxy_vix",50,IF(I36<350,100,IF(I36<=450,50,0)))) -> 0 | P36: =IF(COUNT(K36)=0,50,IF(K36<20,100,IF(K36<=25,50,0))) -> 100 | S36: =$E36/$E35-1 -> 0.00050352258 | T36: =$K36/$K35-1 -> 0.082010582 | Y36: =IF(AX36>=70,"EASY",IF(AX36>40,"UNCERTAIN","HARD")) -> EASY | AA36: =IF($A36<200,"",AVERAGE($E5:$E36)/AVERAGE($E5:$E36)-1) | AB36: =LOOKUP($B36,07_L1政策步階!$A$4:$A$14,07_L1政策步階!$C$4:$C$14) -> 0 | AL36: =IF(ISNUMBER($AA36),IF($AA36>=0.005,100,IF($AA36>=-0.015,50,0)),"") | AM36: =IF(ISNUMBER($AB36),IF($AB36=1,100,IF($AB36=0,50,0)),"") -> 50 | AN36: =IF(ISNUMBER($AC36),IF($AC36>=0.001,100,IF($AC36>=-0.003,50,0)),"") | AO36: =IF(ISNUMBER($AD36),IF($AD36>=0.04,100,IF($AD36>=0,50,0)),"") | AP36: =IF(ISNUMBER($AE36),IF($AE36>=25,100,IF($AE36>=-75,50,0)),"") | AQ36: =IF(ISNUMBER($AF36),IF($AF36>0,100,IF($AF36>=-50,50,0)),"") | AR36: =IF(ISNUMBER($AG36),IF($AG36=1,100,IF($AG36=0,50,0)),"") | AS36: =IF(ISNUMBER($AH36),IF($AH36<0,100,IF($AH36<=20,50,0)),"") | AT36: =IF(ISNUMBER($AI36),IF($AI36<0.95,100,IF($AI36<=1,50,0)),"") | AU36: =IF(ISNUMBER($AJ36),IF($AJ36<30,0,IF($AJ36<40,50,IF($AJ36<=90,100,50))),"") | AV36: =IF(ISNUMBER($AK36),IF($AK36>-0.2,100,IF($AK36>=-0.4,50,0)),"") | AW36: =01_指標庫!$H$4*ISNUMBER($F36)+01_指標庫!$H$5*ISNUMBER($AA36)+01_指標庫!$H$6*ISNUMBER($G36)+01_指標庫!$H$7*ISNUMBER($H36)+01_指標庫!$H$8*ISNUMBER($AF36)+01_指標庫!$H$9*ISNUMBER($AG36)+01_指標庫!$H$10*ISNUMBER($AB36)+01_指標庫!$H$11*ISNUMBER($AC36)+01_指標庫!$H$12*ISNUMBER($AD36)+01_指標庫!$H$13*ISNUMBER($AE36)+01_指標庫!$H$14*ISNUMBER($I36)+01_指標庫!$H$15*ISNUMBER($AH36)+01_指標庫!$H$16*ISNUMBER($K36)+01_指標庫!$H$17*ISNUMBER($AI36)+01_指標庫!$H$18*ISNUMBER($AJ36)+01_指標庫!$H$19*ISNUMBER($AK36)+01_指標庫!$H$20*ISNUMBER($BB36)+01_指標庫!$H$21*ISNUMBER($BC36) -> 49 | AX36: =IF(AW36=0,50,ROUND((01_指標庫!$H$4*IF(ISNUMBER($F36),L36,0)+01_指標庫!$H$5*IF(ISNUMBER($AA36),AL36,0)+01_指標庫!$H$6*IF(ISNUMBER($G36),M36,0)+01_指標庫!$H$7*IF(ISNUMBER($H36),N36,0)+01_指標庫!$H$8*IF(ISNUMBER($AF36),AQ36,0)+01_指標庫!$H$9*IF(ISNUMBER($AG36),AR36,0)+01_指標庫!$H$10*IF(ISNUMBER($AB36),AM36,0)+01_指標庫!$H$11*IF(ISNUMBER($AC36),AN36,0)+01_指標庫!$H$12*IF(ISNUMBER($AD36),AO36,0)+01_指標庫!$H$13*IF(ISNUMBER($AE36),AP36,0)+01_指標庫!$H$14*IF(ISNUMBER($I36),O36,0)+01_指標庫!$H$15*IF(ISNUMBER($AH36),AS36,0)+01_指標庫!$H$16*IF(ISNUMBER($K36),P36,0)+01_指標庫!$H$17*IF(ISNUMBER($AI36),AT36,0)+01_指標庫!$H$18*IF(ISNUMBER($AJ36),AU36,0)+01_指標庫!$H$19*IF(ISNUMBER($AK36),AV36,0)+01_指標庫!$H$20*IF(ISNUMBER($BB36),BB36,0)+01_指標庫!$H$21*IF(ISNUMBER($BC36),BC36,0))/AW36,1)) -> 72.4 | BA36: =AVERAGE($E32:$E36)/AVERAGE($E27:$E36)-1 -> 0.00019503496 | BB36: =IF(ISNUMBER($BA36),IF(OR($S36<=-0.03,$BA36<-0.003),0,IF(OR($S36<=-0.02,$BA36<0.01),50,100)),"") -> 50 | BC36: =IF(OR(COUNT($AZ36)=0,COUNT($AZ35)=0),"",IF(OR($AY36/$AZ35-1<=-0.03,$AZ36/$AZ35-1<=-0.045,IF(COUNT($AZ27:$AZ36)=10,AVERAGE($AZ32:$AZ36)/AVERAGE($AZ27:$AZ36)-1<-0.01,FALSE())),0,IF(OR($AZ36/$AZ35-1<=-0.02,IF(COUNT($AZ27:$AZ36)=10,AVERAGE($AZ32:$AZ36)/AVERAGE($AZ27:$AZ36)-1<0.005,FALSE())),50,100)))
A37: 33 | B37: 42605 | C37: 2016 | D37: 二 | E37: 4818.48 | F37: 0.079431 | G37: -0.00179 | H37: 0.8776 | I37: 514 | J37: real | K37: 12.38 | L37: =IF(COUNT(F37)=0,50,IF(F37>=0,100,IF(F37>=-0.02,50,0))) -> 100 | M37: =IF(COUNT(G37)=0,50,IF(G37>-0.06,100,IF(G37>-0.15,50,0))) -> 100 | N37: =IF(COUNT(H37)=0,50,IF(H37>=0.6,100,IF(H37>=0.4,50,0))) -> 100 | O37: =IF(COUNT(I37)=0,50,IF(J37="proxy_vix",50,IF(I37<350,100,IF(I37<=450,50,0)))) -> 0 | P37: =IF(COUNT(K37)=0,50,IF(K37<20,100,IF(K37<=25,50,0))) -> 100 | S37: =$E37/$E36-1 -> 0.0020629877 | T37: =$K37/$K36-1 -> 0.0089649552 | Y37: =IF(AX37>=70,"EASY",IF(AX37>40,"UNCERTAIN","HARD")) -> EASY | AA37: =IF($A37<200,"",AVERAGE($E5:$E37)/AVERAGE($E5:$E37)-1) | AB37: =LOOKUP($B37,07_L1政策步階!$A$4:$A$14,07_L1政策步階!$C$4:$C$14) -> 0 | AL37: =IF(ISNUMBER($AA37),IF($AA37>=0.005,100,IF($AA37>=-0.015,50,0)),"") | AM37: =IF(ISNUMBER($AB37),IF($AB37=1,100,IF($AB37=0,50,0)),"") -> 50 | AN37: =IF(ISNUMBER($AC37),IF($AC37>=0.001,100,IF($AC37>=-0.003,50,0)),"") | AO37: =IF(ISNUMBER($AD37),IF($AD37>=0.04,100,IF($AD37>=0,50,0)),"") | AP37: =IF(ISNUMBER($AE37),IF($AE37>=25,100,IF($AE37>=-75,50,0)),"") | AQ37: =IF(ISNUMBER($AF37),IF($AF37>0,100,IF($AF37>=-50,50,0)),"") | AR37: =IF(ISNUMBER($AG37),IF($AG37=1,100,IF($AG37=0,50,0)),"") | AS37: =IF(ISNUMBER($AH37),IF($AH37<0,100,IF($AH37<=20,50,0)),"") | AT37: =IF(ISNUMBER($AI37),IF($AI37<0.95,100,IF($AI37<=1,50,0)),"") | AU37: =IF(ISNUMBER($AJ37),IF($AJ37<30,0,IF($AJ37<40,50,IF($AJ37<=90,100,50))),"") | AV37: =IF(ISNUMBER($AK37),IF($AK37>-0.2,100,IF($AK37>=-0.4,50,0)),"") | AW37: =01_指標庫!$H$4*ISNUMBER($F37)+01_指標庫!$H$5*ISNUMBER($AA37)+01_指標庫!$H$6*ISNUMBER($G37)+01_指標庫!$H$7*ISNUMBER($H37)+01_指標庫!$H$8*ISNUMBER($AF37)+01_指標庫!$H$9*ISNUMBER($AG37)+01_指標庫!$H$10*ISNUMBER($AB37)+01_指標庫!$H$11*ISNUMBER($AC37)+01_指標庫!$H$12*ISNUMBER($AD37)+01_指標庫!$H$13*ISNUMBER($AE37)+01_指標庫!$H$14*ISNUMBER($I37)+01_指標庫!$H$15*ISNUMBER($AH37)+01_指標庫!$H$16*ISNUMBER($K37)+01_指標庫!$H$17*ISNUMBER($AI37)+01_指標庫!$H$18*ISNUMBER($AJ37)+01_指標庫!$H$19*ISNUMBER($AK37)+01_指標庫!$H$20*ISNUMBER($BB37)+01_指標庫!$H$21*ISNUMBER($BC37) -> 49 | AX37: =IF(AW37=0,50,ROUND((01_指標庫!$H$4*IF(ISNUMBER($F37),L37,0)+01_指標庫!$H$5*IF(ISNUMBER($AA37),AL37,0)+01_指標庫!$H$6*IF(ISNUMBER($G37),M37,0)+01_指標庫!$H$7*IF(ISNUMBER($H37),N37,0)+01_指標庫!$H$8*IF(ISNUMBER($AF37),AQ37,0)+01_指標庫!$H$9*IF(ISNUMBER($AG37),AR37,0)+01_指標庫!$H$10*IF(ISNUMBER($AB37),AM37,0)+01_指標庫!$H$11*IF(ISNUMBER($AC37),AN37,0)+01_指標庫!$H$12*IF(ISNUMBER($AD37),AO37,0)+01_指標庫!$H$13*IF(ISNUMBER($AE37),AP37,0)+01_指標庫!$H$14*IF(ISNUMBER($I37),O37,0)+01_指標庫!$H$15*IF(ISNUMBER($AH37),AS37,0)+01_指標庫!$H$16*IF(ISNUMBER($K37),P37,0)+01_指標庫!$H$17*IF(ISNUMBER($AI37),AT37,0)+01_指標庫!$H$18*IF(ISNUMBER($AJ37),AU37,0)+01_指標庫!$H$19*IF(ISNUMBER($AK37),AV37,0)+01_指標庫!$H$20*IF(ISNUMBER($BB37),BB37,0)+01_指標庫!$H$21*IF(ISNUMBER($BC37),BC37,0))/AW37,1)) -> 72.4 | BA37: =AVERAGE($E33:$E37)/AVERAGE($E28:$E37)-1 -> 0.00060792171 | BB37: =IF(ISNUMBER($BA37),IF(OR($S37<=-0.03,$BA37<-0.003),0,IF(OR($S37<=-0.02,$BA37<0.01),50,100)),"") -> 50 | BC37: =IF(OR(COUNT($AZ37)=0,COUNT($AZ36)=0),"",IF(OR($AY37/$AZ36-1<=-0.03,$AZ37/$AZ36-1<=-0.045,IF(COUNT($AZ28:$AZ37)=10,AVERAGE($AZ33:$AZ37)/AVERAGE($AZ28:$AZ37)-1<-0.01,FALSE())),0,IF(OR($AZ37/$AZ36-1<=-0.02,IF(COUNT($AZ28:$AZ37)=10,AVERAGE($AZ33:$AZ37)/AVERAGE($AZ28:$AZ37)-1<0.005,FALSE())),50,100)))
A38: 34 | B38: 42606 | C38: 2016 | D38: 三 | E38: 4783.49 | F38: 0.071501 | G38: -0.009038 | H38: 0.8776 | I38: 513 | J38: real | K38: 13.45 | L38: =IF(COUNT(F38)=0,50,IF(F38>=0,100,IF(F38>=-0.02,50,0))) -> 100 | M38: =IF(COUNT(G38)=0,50,IF(G38>-0.06,100,IF(G38>-0.15,50,0))) -> 100 | N38: =IF(COUNT(H38)=0,50,IF(H38>=0.6,100,IF(H38>=0.4,50,0))) -> 100 | O38: =IF(COUNT(I38)=0,50,IF(J38="proxy_vix",50,IF(I38<350,100,IF(I38<=450,50,0)))) -> 0 | P38: =IF(COUNT(K38)=0,50,IF(K38<20,100,IF(K38<=25,50,0))) -> 100 | S38: =$E38/$E37-1 -> -0.0072616261 | T38: =$K38/$K37-1 -> 0.086429725 | Y38: =IF(AX38>=70,"EASY",IF(AX38>40,"UNCERTAIN","HARD")) -> EASY | AA38: =IF($A38<200,"",AVERAGE($E5:$E38)/AVERAGE($E5:$E38)-1) | AB38: =LOOKUP($B38,07_L1政策步階!$A$4:$A$14,07_L1政策步階!$C$4:$C$14) -> 0 | AL38: =IF(ISNUMBER($AA38),IF($AA38>=0.005,100,IF($AA38>=-0.015,50,0)),"") | AM38: =IF(ISNUMBER($AB38),IF($AB38=1,100,IF($AB38=0,50,0)),"") -> 50 | AN38: =IF(ISNUMBER($AC38),IF($AC38>=0.001,100,IF($AC38>=-0.003,50,0)),"") | AO38: =IF(ISNUMBER($AD38),IF($AD38>=0.04,100,IF($AD38>=0,50,0)),"") | AP38: =IF(ISNUMBER($AE38),IF($AE38>=25,100,IF($AE38>=-75,50,0)),"") | AQ38: =IF(ISNUMBER($AF38),IF($AF38>0,100,IF($AF38>=-50,50,0)),"") | AR38: =IF(ISNUMBER($AG38),IF($AG38=1,100,IF($AG38=0,50,0)),"") | AS38: =IF(ISNUMBER($AH38),IF($AH38<0,100,IF($AH38<=20,50,0)),"") | AT38: =IF(ISNUMBER($AI38),IF($AI38<0.95,100,IF($AI38<=1,50,0)),"") | AU38: =IF(ISNUMBER($AJ38),IF($AJ38<30,0,IF($AJ38<40,50,IF($AJ38<=90,100,50))),"") | AV38: =IF(ISNUMBER($AK38),IF($AK38>-0.2,100,IF($AK38>=-0.4,50,0)),"") | AW38: =01_指標庫!$H$4*ISNUMBER($F38)+01_指標庫!$H$5*ISNUMBER($AA38)+01_指標庫!$H$6*ISNUMBER($G38)+01_指標庫!$H$7*ISNUMBER($H38)+01_指標庫!$H$8*ISNUMBER($AF38)+01_指標庫!$H$9*ISNUMBER($AG38)+01_指標庫!$H$10*ISNUMBER($AB38)+01_指標庫!$H$11*ISNUMBER($AC38)+01_指標庫!$H$12*ISNUMBER($AD38)+01_指標庫!$H$13*ISNUMBER($AE38)+01_指標庫!$H$14*ISNUMBER($I38)+01_指標庫!$H$15*ISNUMBER($AH38)+01_指標庫!$H$16*ISNUMBER($K38)+01_指標庫!$H$17*ISNUMBER($AI38)+01_指標庫!$H$18*ISNUMBER($AJ38)+01_指標庫!$H$19*ISNUMBER($AK38)+01_指標庫!$H$20*ISNUMBER($BB38)+01_指標庫!$H$21*ISNUMBER($BC38) -> 49 | AX38: =IF(AW38=0,50,ROUND((01_指標庫!$H$4*IF(ISNUMBER($F38),L38,0)+01_指標庫!$H$5*IF(ISNUMBER($AA38),AL38,0)+01_指標庫!$H$6*IF(ISNUMBER($G38),M38,0)+01_指標庫!$H$7*IF(ISNUMBER($H38),N38,0)+01_指標庫!$H$8*IF(ISNUMBER($AF38),AQ38,0)+01_指標庫!$H$9*IF(ISNUMBER($AG38),AR38,0)+01_指標庫!$H$10*IF(ISNUMBER($AB38),AM38,0)+01_指標庫!$H$11*IF(ISNUMBER($AC38),AN38,0)+01_指標庫!$H$12*IF(ISNUMBER($AD38),AO38,0)+01_指標庫!$H$13*IF(ISNUMBER($AE38),AP38,0)+01_指標庫!$H$14*IF(ISNUMBER($I38),O38,0)+01_指標庫!$H$15*IF(ISNUMBER($AH38),AS38,0)+01_指標庫!$H$16*IF(ISNUMBER($K38),P38,0)+01_指標庫!$H$17*IF(ISNUMBER($AI38),AT38,0)+01_指標庫!$H$18*IF(ISNUMBER($AJ38),AU38,0)+01_指標庫!$H$19*IF(ISNUMBER($AK38),AV38,0)+01_指標庫!$H$20*IF(ISNUMBER($BB38),BB38,0)+01_指標庫!$H$21*IF(ISNUMBER($BC38),BC38,0))/AW38,1)) -> 72.4 | BA38: =AVERAGE($E34:$E38)/AVERAGE($E29:$E38)-1 -> -0.00030791316 | BB38: =IF(ISNUMBER($BA38),IF(OR($S38<=-0.03,$BA38<-0.003),0,IF(OR($S38<=-0.02,$BA38<0.01),50,100)),"") -> 50 | BC38: =IF(OR(COUNT($AZ38)=0,COUNT($AZ37)=0),"",IF(OR($AY38/$AZ37-1<=-0.03,$AZ38/$AZ37-1<=-0.045,IF(COUNT($AZ29:$AZ38)=10,AVERAGE($AZ34:$AZ38)/AVERAGE($AZ29:$AZ38)-1<-0.01,FALSE())),0,IF(OR($AZ38/$AZ37-1<=-0.02,IF(COUNT($AZ29:$AZ38)=10,AVERAGE($AZ34:$AZ38)/AVERAGE($AZ29:$AZ38)-1<0.005,FALSE())),50,100)))
A39: 35 | B39: 42607 | C39: 2016 | D39: 四 | E39: 4775.43 | F39: 0.069552 | G39: -0.010708 | H39: 0.8776 | I39: 514 | J39: real | K39: 13.63 | L39: =IF(COUNT(F39)=0,50,IF(F39>=0,100,IF(F39>=-0.02,50,0))) -> 100 | M39: =IF(COUNT(G39)=0,50,IF(G39>-0.06,100,IF(G39>-0.15,50,0))) -> 100 | N39: =IF(COUNT(H39)=0,50,IF(H39>=0.6,100,IF(H39>=0.4,50,0))) -> 100 | O39: =IF(COUNT(I39)=0,50,IF(J39="proxy_vix",50,IF(I39<350,100,IF(I39<=450,50,0)))) -> 0 | P39: =IF(COUNT(K39)=0,50,IF(K39<20,100,IF(K39<=25,50,0))) -> 100 | S39: =$E39/$E38-1 -> -0.0016849622 | T39: =$K39/$K38-1 -> 0.0133829 | Y39: =IF(AX39>=70,"EASY",IF(AX39>40,"UNCERTAIN","HARD")) -> EASY | AA39: =IF($A39<200,"",AVERAGE($E5:$E39)/AVERAGE($E5:$E39)-1) | AB39: =LOOKUP($B39,07_L1政策步階!$A$4:$A$14,07_L1政策步階!$C$4:$C$14) -> 0 | AL39: =IF(ISNUMBER($AA39),IF($AA39>=0.005,100,IF($AA39>=-0.015,50,0)),"") | AM39: =IF(ISNUMBER($AB39),IF($AB39=1,100,IF($AB39=0,50,0)),"") -> 50 | AN39: =IF(ISNUMBER($AC39),IF($AC39>=0.001,100,IF($AC39>=-0.003,50,0)),"") | AO39: =IF(ISNUMBER($AD39),IF($AD39>=0.04,100,IF($AD39>=0,50,0)),"") | AP39: =IF(ISNUMBER($AE39),IF($AE39>=25,100,IF($AE39>=-75,50,0)),"") | AQ39: =IF(ISNUMBER($AF39),IF($AF39>0,100,IF($AF39>=-50,50,0)),"") | AR39: =IF(ISNUMBER($AG39),IF($AG39=1,100,IF($AG39=0,50,0)),"") | AS39: =IF(ISNUMBER($AH39),IF($AH39<0,100,IF($AH39<=20,50,0)),"") | AT39: =IF(ISNUMBER($AI39),IF($AI39<0.95,100,IF($AI39<=1,50,0)),"") | AU39: =IF(ISNUMBER($AJ39),IF($AJ39<30,0,IF($AJ39<40,50,IF($AJ39<=90,100,50))),"") | AV39: =IF(ISNUMBER($AK39),IF($AK39>-0.2,100,IF($AK39>=-0.4,50,0)),"") | AW39: =01_指標庫!$H$4*ISNUMBER($F39)+01_指標庫!$H$5*ISNUMBER($AA39)+01_指標庫!$H$6*ISNUMBER($G39)+01_指標庫!$H$7*ISNUMBER($H39)+01_指標庫!$H$8*ISNUMBER($AF39)+01_指標庫!$H$9*ISNUMBER($AG39)+01_指標庫!$H$10*ISNUMBER($AB39)+01_指標庫!$H$11*ISNUMBER($AC39)+01_指標庫!$H$12*ISNUMBER($AD39)+01_指標庫!$H$13*ISNUMBER($AE39)+01_指標庫!$H$14*ISNUMBER($I39)+01_指標庫!$H$15*ISNUMBER($AH39)+01_指標庫!$H$16*ISNUMBER($K39)+01_指標庫!$H$17*ISNUMBER($AI39)+01_指標庫!$H$18*ISNUMBER($AJ39)+01_指標庫!$H$19*ISNUMBER($AK39)+01_指標庫!$H$20*ISNUMBER($BB39)+01_指標庫!$H$21*ISNUMBER($BC39) -> 49 | AX39: =IF(AW39=0,50,ROUND((01_指標庫!$H$4*IF(ISNUMBER($F39),L39,0)+01_指標庫!$H$5*IF(ISNUMBER($AA39),AL39,0)+01_指標庫!$H$6*IF(ISNUMBER($G39),M39,0)+01_指標庫!$H$7*IF(ISNUMBER($H39),N39,0)+01_指標庫!$H$8*IF(ISNUMBER($AF39),AQ39,0)+01_指標庫!$H$9*IF(ISNUMBER($AG39),AR39,0)+01_指標庫!$H$10*IF(ISNUMBER($AB39),AM39,0)+01_指標庫!$H$11*IF(ISNUMBER($AC39),AN39,0)+01_指標庫!$H$12*IF(ISNUMBER($AD39),AO39,0)+01_指標庫!$H$13*IF(ISNUMBER($AE39),AP39,0)+01_指標庫!$H$14*IF(ISNUMBER($I39),O39,0)+01_指標庫!$H$15*IF(ISNUMBER($AH39),AS39,0)+01_指標庫!$H$16*IF(ISNUMBER($K39),P39,0)+01_指標庫!$H$17*IF(ISNUMBER($AI39),AT39,0)+01_指標庫!$H$18*IF(ISNUMBER($AJ39),AU39,0)+01_指標庫!$H$19*IF(ISNUMBER($AK39),AV39,0)+01_指標庫!$H$20*IF(ISNUMBER($BB39),BB39,0)+01_指標庫!$H$21*IF(ISNUMBER($BC39),BC39,0))/AW39,1)) -> 72.4 | BA39: =AVERAGE($E35:$E39)/AVERAGE($E30:$E39)-1 -> -0.0011120451 | BB39: =IF(ISNUMBER($BA39),IF(OR($S39<=-0.03,$BA39<-0.003),0,IF(OR($S39<=-0.02,$BA39<0.01),50,100)),"") -> 50 | BC39: =IF(OR(COUNT($AZ39)=0,COUNT($AZ38)=0),"",IF(OR($AY39/$AZ38-1<=-0.03,$AZ39/$AZ38-1<=-0.045,IF(COUNT($AZ30:$AZ39)=10,AVERAGE($AZ35:$AZ39)/AVERAGE($AZ30:$AZ39)-1<-0.01,FALSE())),0,IF(OR($AZ39/$AZ38-1<=-0.02,IF(COUNT($AZ30:$AZ39)=10,AVERAGE($AZ35:$AZ39)/AVERAGE($AZ30:$AZ39)-1<0.005,FALSE())),50,100)))
A40: 36 | B40: 42608 | C40: 2016 | D40: 五 | E40: 4783.69 | F40: 0.071231 | G40: -0.008997 | H40: 0.8776 | I40: 504 | J40: real | K40: 13.65 | L40: =IF(COUNT(F40)=0,50,IF(F40>=0,100,IF(F40>=-0.02,50,0))) -> 100 | M40: =IF(COUNT(G40)=0,50,IF(G40>-0.06,100,IF(G40>-0.15,50,0))) -> 100 | N40: =IF(COUNT(H40)=0,50,IF(H40>=0.6,100,IF(H40>=0.4,50,0))) -> 100 | O40: =IF(COUNT(I40)=0,50,IF(J40="proxy_vix",50,IF(I40<350,100,IF(I40<=450,50,0)))) -> 0 | P40: =IF(COUNT(K40)=0,50,IF(K40<20,100,IF(K40<=25,50,0))) -> 100 | S40: =$E40/$E39-1 -> 0.0017296872 | T40: =$K40/$K39-1 -> 0.0014673514 | Y40: =IF(AX40>=70,"EASY",IF(AX40>40,"UNCERTAIN","HARD")) -> EASY | AA40: =IF($A40<200,"",AVERAGE($E5:$E40)/AVERAGE($E5:$E40)-1) | AB40: =LOOKUP($B40,07_L1政策步階!$A$4:$A$14,07_L1政策步階!$C$4:$C$14) -> 0 | AL40: =IF(ISNUMBER($AA40),IF($AA40>=0.005,100,IF($AA40>=-0.015,50,0)),"") | AM40: =IF(ISNUMBER($AB40),IF($AB40=1,100,IF($AB40=0,50,0)),"") -> 50 | AN40: =IF(ISNUMBER($AC40),IF($AC40>=0.001,100,IF($AC40>=-0.003,50,0)),"") | AO40: =IF(ISNUMBER($AD40),IF($AD40>=0.04,100,IF($AD40>=0,50,0)),"") | AP40: =IF(ISNUMBER($AE40),IF($AE40>=25,100,IF($AE40>=-75,50,0)),"") | AQ40: =IF(ISNUMBER($AF40),IF($AF40>0,100,IF($AF40>=-50,50,0)),"") | AR40: =IF(ISNUMBER($AG40),IF($AG40=1,100,IF($AG40=0,50,0)),"") | AS40: =IF(ISNUMBER($AH40),IF($AH40<0,100,IF($AH40<=20,50,0)),"") | AT40: =IF(ISNUMBER($AI40),IF($AI40<0.95,100,IF($AI40<=1,50,0)),"") | AU40: =IF(ISNUMBER($AJ40),IF($AJ40<30,0,IF($AJ40<40,50,IF($AJ40<=90,100,50))),"") | AV40: =IF(ISNUMBER($AK40),IF($AK40>-0.2,100,IF($AK40>=-0.4,50,0)),"") | AW40: =01_指標庫!$H$4*ISNUMBER($F40)+01_指標庫!$H$5*ISNUMBER($AA40)+01_指標庫!$H$6*ISNUMBER($G40)+01_指標庫!$H$7*ISNUMBER($H40)+01_指標庫!$H$8*ISNUMBER($AF40)+01_指標庫!$H$9*ISNUMBER($AG40)+01_指標庫!$H$10*ISNUMBER($AB40)+01_指標庫!$H$11*ISNUMBER($AC40)+01_指標庫!$H$12*ISNUMBER($AD40)+01_指標庫!$H$13*ISNUMBER($AE40)+01_指標庫!$H$14*ISNUMBER($I40)+01_指標庫!$H$15*ISNUMBER($AH40)+01_指標庫!$H$16*ISNUMBER($K40)+01_指標庫!$H$17*ISNUMBER($AI40)+01_指標庫!$H$18*ISNUMBER($AJ40)+01_指標庫!$H$19*ISNUMBER($AK40)+01_指標庫!$H$20*ISNUMBER($BB40)+01_指標庫!$H$21*ISNUMBER($BC40) -> 49 | AX40: =IF(AW40=0,50,ROUND((01_指標庫!$H$4*IF(ISNUMBER($F40),L40,0)+01_指標庫!$H$5*IF(ISNUMBER($AA40),AL40,0)+01_指標庫!$H$6*IF(ISNUMBER($G40),M40,0)+01_指標庫!$H$7*IF(ISNUMBER($H40),N40,0)+01_指標庫!$H$8*IF(ISNUMBER($AF40),AQ40,0)+01_指標庫!$H$9*IF(ISNUMBER($AG40),AR40,0)+01_指標庫!$H$10*IF(ISNUMBER($AB40),AM40,0)+01_指標庫!$H$11*IF(ISNUMBER($AC40),AN40,0)+01_指標庫!$H$12*IF(ISNUMBER($AD40),AO40,0)+01_指標庫!$H$13*IF(ISNUMBER($AE40),AP40,0)+01_指標庫!$H$14*IF(ISNUMBER($I40),O40,0)+01_指標庫!$H$15*IF(ISNUMBER($AH40),AS40,0)+01_指標庫!$H$16*IF(ISNUMBER($K40),P40,0)+01_指標庫!$H$17*IF(ISNUMBER($AI40),AT40,0)+01_指標庫!$H$18*IF(ISNUMBER($AJ40),AU40,0)+01_指標庫!$H$19*IF(ISNUMBER($AK40),AV40,0)+01_指標庫!$H$20*IF(ISNUMBER($BB40),BB40,0)+01_指標庫!$H$21*IF(ISNUMBER($BC40),BC40,0))/AW40,1)) -> 72.4 | BA40: =AVERAGE($E36:$E40)/AVERAGE($E31:$E40)-1 -> -0.001560579 | BB40: =IF(ISNUMBER($BA40),IF(OR($S40<=-0.03,$BA40<-0.003),0,IF(OR($S40<=-0.02,$BA40<0.01),50,100)),"") -> 50 | BC40: =IF(OR(COUNT($AZ40)=0,COUNT($AZ39)=0),"",IF(OR($AY40/$AZ39-1<=-0.03,$AZ40/$AZ39-1<=-0.045,IF(COUNT($AZ31:$AZ40)=10,AVERAGE($AZ36:$AZ40)/AVERAGE($AZ31:$AZ40)-1<-0.01,FALSE())),0,IF(OR($AZ40/$AZ39-1<=-0.02,IF(COUNT($AZ31:$AZ40)=10,AVERAGE($AZ36:$AZ40)/AVERAGE($AZ31:$AZ40)-1<0.005,FALSE())),50,100)))
A41: 37 | B41: 42611 | C41: 2016 | D41: 一 | E41: 4791.09 | F41: 0.072703 | G41: -0.007464 | H41: 0.8571 | I41: 510 | J41: real | K41: 12.94 | L41: =IF(COUNT(F41)=0,50,IF(F41>=0,100,IF(F41>=-0.02,50,0))) -> 100 | M41: =IF(COUNT(G41)=0,50,IF(G41>-0.06,100,IF(G41>-0.15,50,0))) -> 100 | N41: =IF(COUNT(H41)=0,50,IF(H41>=0.6,100,IF(H41>=0.4,50,0))) -> 100 | O41: =IF(COUNT(I41)=0,50,IF(J41="proxy_vix",50,IF(I41<350,100,IF(I41<=450,50,0)))) -> 0 | P41: =IF(COUNT(K41)=0,50,IF(K41<20,100,IF(K41<=25,50,0))) -> 100 | S41: =$E41/$E40-1 -> 0.001546923 | T41: =$K41/$K40-1 -> -0.052014652 | Y41: =IF(AX41>=70,"EASY",IF(AX41>40,"UNCERTAIN","HARD")) -> EASY | AA41: =IF($A41<200,"",AVERAGE($E5:$E41)/AVERAGE($E5:$E41)-1) | AB41: =LOOKUP($B41,07_L1政策步階!$A$4:$A$14,07_L1政策步階!$C$4:$C$14) -> 0 | AL41: =IF(ISNUMBER($AA41),IF($AA41>=0.005,100,IF($AA41>=-0.015,50,0)),"") | AM41: =IF(ISNUMBER($AB41),IF($AB41=1,100,IF($AB41=0,50,0)),"") -> 50 | AN41: =IF(ISNUMBER($AC41),IF($AC41>=0.001,100,IF($AC41>=-0.003,50,0)),"") | AO41: =IF(ISNUMBER($AD41),IF($AD41>=0.04,100,IF($AD41>=0,50,0)),"") | AP41: =IF(ISNUMBER($AE41),IF($AE41>=25,100,IF($AE41>=-75,50,0)),"") | AQ41: =IF(ISNUMBER($AF41),IF($AF41>0,100,IF($AF41>=-50,50,0)),"") | AR41: =IF(ISNUMBER($AG41),IF($AG41=1,100,IF($AG41=0,50,0)),"") | AS41: =IF(ISNUMBER($AH41),IF($AH41<0,100,IF($AH41<=20,50,0)),"") | AT41: =IF(ISNUMBER($AI41),IF($AI41<0.95,100,IF($AI41<=1,50,0)),"") | AU41: =IF(ISNUMBER($AJ41),IF($AJ41<30,0,IF($AJ41<40,50,IF($AJ41<=90,100,50))),"") | AV41: =IF(ISNUMBER($AK41),IF($AK41>-0.2,100,IF($AK41>=-0.4,50,0)),"") | AW41: =01_指標庫!$H$4*ISNUMBER($F41)+01_指標庫!$H$5*ISNUMBER($AA41)+01_指標庫!$H$6*ISNUMBER($G41)+01_指標庫!$H$7*ISNUMBER($H41)+01_指標庫!$H$8*ISNUMBER($AF41)+01_指標庫!$H$9*ISNUMBER($AG41)+01_指標庫!$H$10*ISNUMBER($AB41)+01_指標庫!$H$11*ISNUMBER($AC41)+01_指標庫!$H$12*ISNUMBER($AD41)+01_指標庫!$H$13*ISNUMBER($AE41)+01_指標庫!$H$14*ISNUMBER($I41)+01_指標庫!$H$15*ISNUMBER($AH41)+01_指標庫!$H$16*ISNUMBER($K41)+01_指標庫!$H$17*ISNUMBER($AI41)+01_指標庫!$H$18*ISNUMBER($AJ41)+01_指標庫!$H$19*ISNUMBER($AK41)+01_指標庫!$H$20*ISNUMBER($BB41)+01_指標庫!$H$21*ISNUMBER($BC41) -> 49 | AX41: =IF(AW41=0,50,ROUND((01_指標庫!$H$4*IF(ISNUMBER($F41),L41,0)+01_指標庫!$H$5*IF(ISNUMBER($AA41),AL41,0)+01_指標庫!$H$6*IF(ISNUMBER($G41),M41,0)+01_指標庫!$H$7*IF(ISNUMBER($H41),N41,0)+01_指標庫!$H$8*IF(ISNUMBER($AF41),AQ41,0)+01_指標庫!$H$9*IF(ISNUMBER($AG41),AR41,0)+01_指標庫!$H$10*IF(ISNUMBER($AB41),AM41,0)+01_指標庫!$H$11*IF(ISNUMBER($AC41),AN41,0)+01_指標庫!$H$12*IF(ISNUMBER($AD41),AO41,0)+01_指標庫!$H$13*IF(ISNUMBER($AE41),AP41,0)+01_指標庫!$H$14*IF(ISNUMBER($I41),O41,0)+01_指標庫!$H$15*IF(ISNUMBER($AH41),AS41,0)+01_指標庫!$H$16*IF(ISNUMBER($K41),P41,0)+01_指標庫!$H$17*IF(ISNUMBER($AI41),AT41,0)+01_指標庫!$H$18*IF(ISNUMBER($AJ41),AU41,0)+01_指標庫!$H$19*IF(ISNUMBER($AK41),AV41,0)+01_指標庫!$H$20*IF(ISNUMBER($BB41),BB41,0)+01_指標庫!$H$21*IF(ISNUMBER($BC41),BC41,0))/AW41,1)) -> 72.4 | BA41: =AVERAGE($E37:$E41)/AVERAGE($E32:$E41)-1 -> -0.0015390323 | BB41: =IF(ISNUMBER($BA41),IF(OR($S41<=-0.03,$BA41<-0.003),0,IF(OR($S41<=-0.02,$BA41<0.01),50,100)),"") -> 50 | BC41: =IF(OR(COUNT($AZ41)=0,COUNT($AZ40)=0),"",IF(OR($AY41/$AZ40-1<=-0.03,$AZ41/$AZ40-1<=-0.045,IF(COUNT($AZ32:$AZ41)=10,AVERAGE($AZ37:$AZ41)/AVERAGE($AZ32:$AZ41)-1<-0.01,FALSE())),0,IF(OR($AZ41/$AZ40-1<=-0.02,IF(COUNT($AZ32:$AZ41)=10,AVERAGE($AZ37:$AZ41)/AVERAGE($AZ32:$AZ41)-1<0.005,FALSE())),50,100)))
A42: 38 | B42: 42612 | C42: 2016 | D42: 二 | E42: 4775.99 | F42: 0.069099 | G42: -0.010592 | H42: 0.8367 | I42: 507 | J42: real | K42: 13.12 | L42: =IF(COUNT(F42)=0,50,IF(F42>=0,100,IF(F42>=-0.02,50,0))) -> 100 | M42: =IF(COUNT(G42)=0,50,IF(G42>-0.06,100,IF(G42>-0.15,50,0))) -> 100 | N42: =IF(COUNT(H42)=0,50,IF(H42>=0.6,100,IF(H42>=0.4,50,0))) -> 100 | O42: =IF(COUNT(I42)=0,50,IF(J42="proxy_vix",50,IF(I42<350,100,IF(I42<=450,50,0)))) -> 0 | P42: =IF(COUNT(K42)=0,50,IF(K42<20,100,IF(K42<=25,50,0))) -> 100 | S42: =$E42/$E41-1 -> -0.0031516836 | T42: =$K42/$K41-1 -> 0.013910355 | Y42: =IF(AX42>=70,"EASY",IF(AX42>40,"UNCERTAIN","HARD")) -> EASY | AA42: =IF($A42<200,"",AVERAGE($E5:$E42)/AVERAGE($E5:$E42)-1) | AB42: =LOOKUP($B42,07_L1政策步階!$A$4:$A$14,07_L1政策步階!$C$4:$C$14) -> 0 | AL42: =IF(ISNUMBER($AA42),IF($AA42>=0.005,100,IF($AA42>=-0.015,50,0)),"") | AM42: =IF(ISNUMBER($AB42),IF($AB42=1,100,IF($AB42=0,50,0)),"") -> 50 | AN42: =IF(ISNUMBER($AC42),IF($AC42>=0.001,100,IF($AC42>=-0.003,50,0)),"") | AO42: =IF(ISNUMBER($AD42),IF($AD42>=0.04,100,IF($AD42>=0,50,0)),"") | AP42: =IF(ISNUMBER($AE42),IF($AE42>=25,100,IF($AE42>=-75,50,0)),"") | AQ42: =IF(ISNUMBER($AF42),IF($AF42>0,100,IF($AF42>=-50,50,0)),"") | AR42: =IF(ISNUMBER($AG42),IF($AG42=1,100,IF($AG42=0,50,0)),"") | AS42: =IF(ISNUMBER($AH42),IF($AH42<0,100,IF($AH42<=20,50,0)),"") | AT42: =IF(ISNUMBER($AI42),IF($AI42<0.95,100,IF($AI42<=1,50,0)),"") | AU42: =IF(ISNUMBER($AJ42),IF($AJ42<30,0,IF($AJ42<40,50,IF($AJ42<=90,100,50))),"") | AV42: =IF(ISNUMBER($AK42),IF($AK42>-0.2,100,IF($AK42>=-0.4,50,0)),"") | AW42: =01_指標庫!$H$4*ISNUMBER($F42)+01_指標庫!$H$5*ISNUMBER($AA42)+01_指標庫!$H$6*ISNUMBER($G42)+01_指標庫!$H$7*ISNUMBER($H42)+01_指標庫!$H$8*ISNUMBER($AF42)+01_指標庫!$H$9*ISNUMBER($AG42)+01_指標庫!$H$10*ISNUMBER($AB42)+01_指標庫!$H$11*ISNUMBER($AC42)+01_指標庫!$H$12*ISNUMBER($AD42)+01_指標庫!$H$13*ISNUMBER($AE42)+01_指標庫!$H$14*ISNUMBER($I42)+01_指標庫!$H$15*ISNUMBER($AH42)+01_指標庫!$H$16*ISNUMBER($K42)+01_指標庫!$H$17*ISNUMBER($AI42)+01_指標庫!$H$18*ISNUMBER($AJ42)+01_指標庫!$H$19*ISNUMBER($AK42)+01_指標庫!$H$20*ISNUMBER($BB42)+01_指標庫!$H$21*ISNUMBER($BC42) -> 49 | AX42: =IF(AW42=0,50,ROUND((01_指標庫!$H$4*IF(ISNUMBER($F42),L42,0)+01_指標庫!$H$5*IF(ISNUMBER($AA42),AL42,0)+01_指標庫!$H$6*IF(ISNUMBER($G42),M42,0)+01_指標庫!$H$7*IF(ISNUMBER($H42),N42,0)+01_指標庫!$H$8*IF(ISNUMBER($AF42),AQ42,0)+01_指標庫!$H$9*IF(ISNUMBER($AG42),AR42,0)+01_指標庫!$H$10*IF(ISNUMBER($AB42),AM42,0)+01_指標庫!$H$11*IF(ISNUMBER($AC42),AN42,0)+01_指標庫!$H$12*IF(ISNUMBER($AD42),AO42,0)+01_指標庫!$H$13*IF(ISNUMBER($AE42),AP42,0)+01_指標庫!$H$14*IF(ISNUMBER($I42),O42,0)+01_指標庫!$H$15*IF(ISNUMBER($AH42),AS42,0)+01_指標庫!$H$16*IF(ISNUMBER($K42),P42,0)+01_指標庫!$H$17*IF(ISNUMBER($AI42),AT42,0)+01_指標庫!$H$18*IF(ISNUMBER($AJ42),AU42,0)+01_指標庫!$H$19*IF(ISNUMBER($AK42),AV42,0)+01_指標庫!$H$20*IF(ISNUMBER($BB42),BB42,0)+01_指標庫!$H$21*IF(ISNUMBER($BC42),BC42,0))/AW42,1)) -> 72.4 | BA42: =AVERAGE($E38:$E42)/AVERAGE($E33:$E42)-1 -> -0.0028696541 | BB42: =IF(ISNUMBER($BA42),IF(OR($S42<=-0.03,$BA42<-0.003),0,IF(OR($S42<=-0.02,$BA42<0.01),50,100)),"") -> 50 | BC42: =IF(OR(COUNT($AZ42)=0,COUNT($AZ41)=0),"",IF(OR($AY42/$AZ41-1<=-0.03,$AZ42/$AZ41-1<=-0.045,IF(COUNT($AZ33:$AZ42)=10,AVERAGE($AZ38:$AZ42)/AVERAGE($AZ33:$AZ42)-1<-0.01,FALSE())),0,IF(OR($AZ42/$AZ41-1<=-0.02,IF(COUNT($AZ33:$AZ42)=10,AVERAGE($AZ38:$AZ42)/AVERAGE($AZ33:$AZ42)-1<0.005,FALSE())),50,100)))
A43: 39 | B43: 42613 | C43: 2016 | D43: 三 | E43: 4771.05 | F43: 0.067671 | G43: -0.011616 | H43: 0.8571 | I43: 510 | J43: real | K43: 13.42 | L43: =IF(COUNT(F43)=0,50,IF(F43>=0,100,IF(F43>=-0.02,50,0))) -> 100 | M43: =IF(COUNT(G43)=0,50,IF(G43>-0.06,100,IF(G43>-0.15,50,0))) -> 100 | N43: =IF(COUNT(H43)=0,50,IF(H43>=0.6,100,IF(H43>=0.4,50,0))) -> 100 | O43: =IF(COUNT(I43)=0,50,IF(J43="proxy_vix",50,IF(I43<350,100,IF(I43<=450,50,0)))) -> 0 | P43: =IF(COUNT(K43)=0,50,IF(K43<20,100,IF(K43<=25,50,0))) -> 100 | S43: =$E43/$E42-1 -> -0.0010343405 | T43: =$K43/$K42-1 -> 0.022865854 | Y43: =IF(AX43>=70,"EASY",IF(AX43>40,"UNCERTAIN","HARD")) -> EASY | AA43: =IF($A43<200,"",AVERAGE($E5:$E43)/AVERAGE($E5:$E43)-1) | AB43: =LOOKUP($B43,07_L1政策步階!$A$4:$A$14,07_L1政策步階!$C$4:$C$14) -> 0 | AL43: =IF(ISNUMBER($AA43),IF($AA43>=0.005,100,IF($AA43>=-0.015,50,0)),"") | AM43: =IF(ISNUMBER($AB43),IF($AB43=1,100,IF($AB43=0,50,0)),"") -> 50 | AN43: =IF(ISNUMBER($AC43),IF($AC43>=0.001,100,IF($AC43>=-0.003,50,0)),"") | AO43: =IF(ISNUMBER($AD43),IF($AD43>=0.04,100,IF($AD43>=0,50,0)),"") | AP43: =IF(ISNUMBER($AE43),IF($AE43>=25,100,IF($AE43>=-75,50,0)),"") | AQ43: =IF(ISNUMBER($AF43),IF($AF43>0,100,IF($AF43>=-50,50,0)),"") | AR43: =IF(ISNUMBER($AG43),IF($AG43=1,100,IF($AG43=0,50,0)),"") | AS43: =IF(ISNUMBER($AH43),IF($AH43<0,100,IF($AH43<=20,50,0)),"") | AT43: =IF(ISNUMBER($AI43),IF($AI43<0.95,100,IF($AI43<=1,50,0)),"") | AU43: =IF(ISNUMBER($AJ43),IF($AJ43<30,0,IF($AJ43<40,50,IF($AJ43<=90,100,50))),"") | AV43: =IF(ISNUMBER($AK43),IF($AK43>-0.2,100,IF($AK43>=-0.4,50,0)),"") | AW43: =01_指標庫!$H$4*ISNUMBER($F43)+01_指標庫!$H$5*ISNUMBER($AA43)+01_指標庫!$H$6*ISNUMBER($G43)+01_指標庫!$H$7*ISNUMBER($H43)+01_指標庫!$H$8*ISNUMBER($AF43)+01_指標庫!$H$9*ISNUMBER($AG43)+01_指標庫!$H$10*ISNUMBER($AB43)+01_指標庫!$H$11*ISNUMBER($AC43)+01_指標庫!$H$12*ISNUMBER($AD43)+01_指標庫!$H$13*ISNUMBER($AE43)+01_指標庫!$H$14*ISNUMBER($I43)+01_指標庫!$H$15*ISNUMBER($AH43)+01_指標庫!$H$16*ISNUMBER($K43)+01_指標庫!$H$17*ISNUMBER($AI43)+01_指標庫!$H$18*ISNUMBER($AJ43)+01_指標庫!$H$19*ISNUMBER($AK43)+01_指標庫!$H$20*ISNUMBER($BB43)+01_指標庫!$H$21*ISNUMBER($BC43) -> 49 | AX43: =IF(AW43=0,50,ROUND((01_指標庫!$H$4*IF(ISNUMBER($F43),L43,0)+01_指標庫!$H$5*IF(ISNUMBER($AA43),AL43,0)+01_指標庫!$H$6*IF(ISNUMBER($G43),M43,0)+01_指標庫!$H$7*IF(ISNUMBER($H43),N43,0)+01_指標庫!$H$8*IF(ISNUMBER($AF43),AQ43,0)+01_指標庫!$H$9*IF(ISNUMBER($AG43),AR43,0)+01_指標庫!$H$10*IF(ISNUMBER($AB43),AM43,0)+01_指標庫!$H$11*IF(ISNUMBER($AC43),AN43,0)+01_指標庫!$H$12*IF(ISNUMBER($AD43),AO43,0)+01_指標庫!$H$13*IF(ISNUMBER($AE43),AP43,0)+01_指標庫!$H$14*IF(ISNUMBER($I43),O43,0)+01_指標庫!$H$15*IF(ISNUMBER($AH43),AS43,0)+01_指標庫!$H$16*IF(ISNUMBER($K43),P43,0)+01_指標庫!$H$17*IF(ISNUMBER($AI43),AT43,0)+01_指標庫!$H$18*IF(ISNUMBER($AJ43),AU43,0)+01_指標庫!$H$19*IF(ISNUMBER($AK43),AV43,0)+01_指標庫!$H$20*IF(ISNUMBER($BB43),BB43,0)+01_指標庫!$H$21*IF(ISNUMBER($BC43),BC43,0))/AW43,1)) -> 72.4 | BA43: =AVERAGE($E39:$E43)/AVERAGE($E34:$E43)-1 -> -0.0026730603 | BB43: =IF(ISNUMBER($BA43),IF(OR($S43<=-0.03,$BA43<-0.003),0,IF(OR($S43<=-0.02,$BA43<0.01),50,100)),"") -> 50 | BC43: =IF(OR(COUNT($AZ43)=0,COUNT($AZ42)=0),"",IF(OR($AY43/$AZ42-1<=-0.03,$AZ43/$AZ42-1<=-0.045,IF(COUNT($AZ34:$AZ43)=10,AVERAGE($AZ39:$AZ43)/AVERAGE($AZ34:$AZ43)-1<-0.01,FALSE())),0,IF(OR($AZ43/$AZ42-1<=-0.02,IF(COUNT($AZ34:$AZ43)=10,AVERAGE($AZ39:$AZ43)/AVERAGE($AZ34:$AZ43)-1<0.005,FALSE())),50,100)))
A44: 40 | B44: 42614 | C44: 2016 | D44: 四 | E44: 4783.94 | F44: 0.070294 | G44: -0.008945 | H44: 0.8571 | I44: 512 | J44: real | K44: 13.48 | L44: =IF(COUNT(F44)=0,50,IF(F44>=0,100,IF(F44>=-0.02,50,0))) -> 100 | M44: =IF(COUNT(G44)=0,50,IF(G44>-0.06,100,IF(G44>-0.15,50,0))) -> 100 | N44: =IF(COUNT(H44)=0,50,IF(H44>=0.6,100,IF(H44>=0.4,50,0))) -> 100 | O44: =IF(COUNT(I44)=0,50,IF(J44="proxy_vix",50,IF(I44<350,100,IF(I44<=450,50,0)))) -> 0 | P44: =IF(COUNT(K44)=0,50,IF(K44<20,100,IF(K44<=25,50,0))) -> 100 | S44: =$E44/$E43-1 -> 0.0027017114 | T44: =$K44/$K43-1 -> 0.0044709389 | Y44: =IF(AX44>=70,"EASY",IF(AX44>40,"UNCERTAIN","HARD")) -> EASY | AA44: =IF($A44<200,"",AVERAGE($E5:$E44)/AVERAGE($E5:$E44)-1) | AB44: =LOOKUP($B44,07_L1政策步階!$A$4:$A$14,07_L1政策步階!$C$4:$C$14) -> 0 | AL44: =IF(ISNUMBER($AA44),IF($AA44>=0.005,100,IF($AA44>=-0.015,50,0)),"") | AM44: =IF(ISNUMBER($AB44),IF($AB44=1,100,IF($AB44=0,50,0)),"") -> 50 | AN44: =IF(ISNUMBER($AC44),IF($AC44>=0.001,100,IF($AC44>=-0.003,50,0)),"") | AO44: =IF(ISNUMBER($AD44),IF($AD44>=0.04,100,IF($AD44>=0,50,0)),"") | AP44: =IF(ISNUMBER($AE44),IF($AE44>=25,100,IF($AE44>=-75,50,0)),"") | AQ44: =IF(ISNUMBER($AF44),IF($AF44>0,100,IF($AF44>=-50,50,0)),"") | AR44: =IF(ISNUMBER($AG44),IF($AG44=1,100,IF($AG44=0,50,0)),"") | AS44: =IF(ISNUMBER($AH44),IF($AH44<0,100,IF($AH44<=20,50,0)),"") | AT44: =IF(ISNUMBER($AI44),IF($AI44<0.95,100,IF($AI44<=1,50,0)),"") | AU44: =IF(ISNUMBER($AJ44),IF($AJ44<30,0,IF($AJ44<40,50,IF($AJ44<=90,100,50))),"") | AV44: =IF(ISNUMBER($AK44),IF($AK44>-0.2,100,IF($AK44>=-0.4,50,0)),"") | AW44: =01_指標庫!$H$4*ISNUMBER($F44)+01_指標庫!$H$5*ISNUMBER($AA44)+01_指標庫!$H$6*ISNUMBER($G44)+01_指標庫!$H$7*ISNUMBER($H44)+01_指標庫!$H$8*ISNUMBER($AF44)+01_指標庫!$H$9*ISNUMBER($AG44)+01_指標庫!$H$10*ISNUMBER($AB44)+01_指標庫!$H$11*ISNUMBER($AC44)+01_指標庫!$H$12*ISNUMBER($AD44)+01_指標庫!$H$13*ISNUMBER($AE44)+01_指標庫!$H$14*ISNUMBER($I44)+01_指標庫!$H$15*ISNUMBER($AH44)+01_指標庫!$H$16*ISNUMBER($K44)+01_指標庫!$H$17*ISNUMBER($AI44)+01_指標庫!$H$18*ISNUMBER($AJ44)+01_指標庫!$H$19*ISNUMBER($AK44)+01_指標庫!$H$20*ISNUMBER($BB44)+01_指標庫!$H$21*ISNUMBER($BC44) -> 49 | AX44: =IF(AW44=0,50,ROUND((01_指標庫!$H$4*IF(ISNUMBER($F44),L44,0)+01_指標庫!$H$5*IF(ISNUMBER($AA44),AL44,0)+01_指標庫!$H$6*IF(ISNUMBER($G44),M44,0)+01_指標庫!$H$7*IF(ISNUMBER($H44),N44,0)+01_指標庫!$H$8*IF(ISNUMBER($AF44),AQ44,0)+01_指標庫!$H$9*IF(ISNUMBER($AG44),AR44,0)+01_指標庫!$H$10*IF(ISNUMBER($AB44),AM44,0)+01_指標庫!$H$11*IF(ISNUMBER($AC44),AN44,0)+01_指標庫!$H$12*IF(ISNUMBER($AD44),AO44,0)+01_指標庫!$H$13*IF(ISNUMBER($AE44),AP44,0)+01_指標庫!$H$14*IF(ISNUMBER($I44),O44,0)+01_指標庫!$H$15*IF(ISNUMBER($AH44),AS44,0)+01_指標庫!$H$16*IF(ISNUMBER($K44),P44,0)+01_指標庫!$H$17*IF(ISNUMBER($AI44),AT44,0)+01_指標庫!$H$18*IF(ISNUMBER($AJ44),AU44,0)+01_指標庫!$H$19*IF(ISNUMBER($AK44),AV44,0)+01_指標庫!$H$20*IF(ISNUMBER($BB44),BB44,0)+01_指標庫!$H$21*IF(ISNUMBER($BC44),BC44,0))/AW44,1)) -> 72.4 | BA44: =AVERAGE($E40:$E44)/AVERAGE($E35:$E44)-1 -> -0.0018025858 | BB44: =IF(ISNUMBER($BA44),IF(OR($S44<=-0.03,$BA44<-0.003),0,IF(OR($S44<=-0.02,$BA44<0.01),50,100)),"") -> 50 | BC44: =IF(OR(COUNT($AZ44)=0,COUNT($AZ43)=0),"",IF(OR($AY44/$AZ43-1<=-0.03,$AZ44/$AZ43-1<=-0.045,IF(COUNT($AZ35:$AZ44)=10,AVERAGE($AZ40:$AZ44)/AVERAGE($AZ35:$AZ44)-1<-0.01,FALSE())),0,IF(OR($AZ44/$AZ43-1<=-0.02,IF(COUNT($AZ35:$AZ44)=10,AVERAGE($AZ40:$AZ44)/AVERAGE($AZ35:$AZ44)-1<0.005,FALSE())),50,100)))
A45: 41 | B45: 42615 | C45: 2016 | D45: 五 | E45: 4798.74 | F45: 0.073326 | G45: -0.005879 | H45: 0.8571 | I45: 509 | J45: real | K45: 11.98 | L45: =IF(COUNT(F45)=0,50,IF(F45>=0,100,IF(F45>=-0.02,50,0))) -> 100 | M45: =IF(COUNT(G45)=0,50,IF(G45>-0.06,100,IF(G45>-0.15,50,0))) -> 100 | N45: =IF(COUNT(H45)=0,50,IF(H45>=0.6,100,IF(H45>=0.4,50,0))) -> 100 | O45: =IF(COUNT(I45)=0,50,IF(J45="proxy_vix",50,IF(I45<350,100,IF(I45<=450,50,0)))) -> 0 | P45: =IF(COUNT(K45)=0,50,IF(K45<20,100,IF(K45<=25,50,0))) -> 100 | S45: =$E45/$E44-1 -> 0.0030936843 | T45: =$K45/$K44-1 -> -0.11127596 | Y45: =IF(AX45>=70,"EASY",IF(AX45>40,"UNCERTAIN","HARD")) -> EASY | AA45: =IF($A45<200,"",AVERAGE($E5:$E45)/AVERAGE($E5:$E45)-1) | AB45: =LOOKUP($B45,07_L1政策步階!$A$4:$A$14,07_L1政策步階!$C$4:$C$14) -> 0 | AL45: =IF(ISNUMBER($AA45),IF($AA45>=0.005,100,IF($AA45>=-0.015,50,0)),"") | AM45: =IF(ISNUMBER($AB45),IF($AB45=1,100,IF($AB45=0,50,0)),"") -> 50 | AN45: =IF(ISNUMBER($AC45),IF($AC45>=0.001,100,IF($AC45>=-0.003,50,0)),"") | AO45: =IF(ISNUMBER($AD45),IF($AD45>=0.04,100,IF($AD45>=0,50,0)),"") | AP45: =IF(ISNUMBER($AE45),IF($AE45>=25,100,IF($AE45>=-75,50,0)),"") | AQ45: =IF(ISNUMBER($AF45),IF($AF45>0,100,IF($AF45>=-50,50,0)),"") | AR45: =IF(ISNUMBER($AG45),IF($AG45=1,100,IF($AG45=0,50,0)),"") | AS45: =IF(ISNUMBER($AH45),IF($AH45<0,100,IF($AH45<=20,50,0)),"") | AT45: =IF(ISNUMBER($AI45),IF($AI45<0.95,100,IF($AI45<=1,50,0)),"") | AU45: =IF(ISNUMBER($AJ45),IF($AJ45<30,0,IF($AJ45<40,50,IF($AJ45<=90,100,50))),"") | AV45: =IF(ISNUMBER($AK45),IF($AK45>-0.2,100,IF($AK45>=-0.4,50,0)),"") | AW45: =01_指標庫!$H$4*ISNUMBER($F45)+01_指標庫!$H$5*ISNUMBER($AA45)+01_指標庫!$H$6*ISNUMBER($G45)+01_指標庫!$H$7*ISNUMBER($H45)+01_指標庫!$H$8*ISNUMBER($AF45)+01_指標庫!$H$9*ISNUMBER($AG45)+01_指標庫!$H$10*ISNUMBER($AB45)+01_指標庫!$H$11*ISNUMBER($AC45)+01_指標庫!$H$12*ISNUMBER($AD45)+01_指標庫!$H$13*ISNUMBER($AE45)+01_指標庫!$H$14*ISNUMBER($I45)+01_指標庫!$H$15*ISNUMBER($AH45)+01_指標庫!$H$16*ISNUMBER($K45)+01_指標庫!$H$17*ISNUMBER($AI45)+01_指標庫!$H$18*ISNUMBER($AJ45)+01_指標庫!$H$19*ISNUMBER($AK45)+01_指標庫!$H$20*ISNUMBER($BB45)+01_指標庫!$H$21*ISNUMBER($BC45) -> 49 | AX45: =IF(AW45=0,50,ROUND((01_指標庫!$H$4*IF(ISNUMBER($F45),L45,0)+01_指標庫!$H$5*IF(ISNUMBER($AA45),AL45,0)+01_指標庫!$H$6*IF(ISNUMBER($G45),M45,0)+01_指標庫!$H$7*IF(ISNUMBER($H45),N45,0)+01_指標庫!$H$8*IF(ISNUMBER($AF45),AQ45,0)+01_指標庫!$H$9*IF(ISNUMBER($AG45),AR45,0)+01_指標庫!$H$10*IF(ISNUMBER($AB45),AM45,0)+01_指標庫!$H$11*IF(ISNUMBER($AC45),AN45,0)+01_指標庫!$H$12*IF(ISNUMBER($AD45),AO45,0)+01_指標庫!$H$13*IF(ISNUMBER($AE45),AP45,0)+01_指標庫!$H$14*IF(ISNUMBER($I45),O45,0)+01_指標庫!$H$15*IF(ISNUMBER($AH45),AS45,0)+01_指標庫!$H$16*IF(ISNUMBER($K45),P45,0)+01_指標庫!$H$17*IF(ISNUMBER($AI45),AT45,0)+01_指標庫!$H$18*IF(ISNUMBER($AJ45),AU45,0)+01_指標庫!$H$19*IF(ISNUMBER($AK45),AV45,0)+01_指標庫!$H$20*IF(ISNUMBER($BB45),BB45,0)+01_指標庫!$H$21*IF(ISNUMBER($BC45),BC45,0))/AW45,1)) -> 72.4 | BA45: =AVERAGE($E41:$E45)/AVERAGE($E36:$E45)-1 -> -0.0010198273 | BB45: =IF(ISNUMBER($BA45),IF(OR($S45<=-0.03,$BA45<-0.003),0,IF(OR($S45<=-0.02,$BA45<0.01),50,100)),"") -> 50 | BC45: =IF(OR(COUNT($AZ45)=0,COUNT($AZ44)=0),"",IF(OR($AY45/$AZ44-1<=-0.03,$AZ45/$AZ44-1<=-0.045,IF(COUNT($AZ36:$AZ45)=10,AVERAGE($AZ41:$AZ45)/AVERAGE($AZ36:$AZ45)-1<-0.01,FALSE())),0,IF(OR($AZ45/$AZ44-1<=-0.02,IF(COUNT($AZ36:$AZ45)=10,AVERAGE($AZ41:$AZ45)/AVERAGE($AZ36:$AZ45)-1<0.005,FALSE())),50,100)))
A46: 42 | B46: 42619 | C46: 2016 | D46: 二 | E46: 4829.51 | F46: 0.079995 | G46: 0 | H46: 0.8776 | I46: 509 | J46: real | K46: 12.02 | L46: =IF(COUNT(F46)=0,50,IF(F46>=0,100,IF(F46>=-0.02,50,0))) -> 100 | M46: =IF(COUNT(G46)=0,50,IF(G46>-0.06,100,IF(G46>-0.15,50,0))) -> 100 | N46: =IF(COUNT(H46)=0,50,IF(H46>=0.6,100,IF(H46>=0.4,50,0))) -> 100 | O46: =IF(COUNT(I46)=0,50,IF(J46="proxy_vix",50,IF(I46<350,100,IF(I46<=450,50,0)))) -> 0 | P46: =IF(COUNT(K46)=0,50,IF(K46<20,100,IF(K46<=25,50,0))) -> 100 | S46: =$E46/$E45-1 -> 0.0064120998 | T46: =$K46/$K45-1 -> 0.0033388982 | Y46: =IF(AX46>=70,"EASY",IF(AX46>40,"UNCERTAIN","HARD")) -> EASY | AA46: =IF($A46<200,"",AVERAGE($E5:$E46)/AVERAGE($E5:$E46)-1) | AB46: =LOOKUP($B46,07_L1政策步階!$A$4:$A$14,07_L1政策步階!$C$4:$C$14) -> 0 | AL46: =IF(ISNUMBER($AA46),IF($AA46>=0.005,100,IF($AA46>=-0.015,50,0)),"") | AM46: =IF(ISNUMBER($AB46),IF($AB46=1,100,IF($AB46=0,50,0)),"") -> 50 | AN46: =IF(ISNUMBER($AC46),IF($AC46>=0.001,100,IF($AC46>=-0.003,50,0)),"") | AO46: =IF(ISNUMBER($AD46),IF($AD46>=0.04,100,IF($AD46>=0,50,0)),"") | AP46: =IF(ISNUMBER($AE46),IF($AE46>=25,100,IF($AE46>=-75,50,0)),"") | AQ46: =IF(ISNUMBER($AF46),IF($AF46>0,100,IF($AF46>=-50,50,0)),"") | AR46: =IF(ISNUMBER($AG46),IF($AG46=1,100,IF($AG46=0,50,0)),"") | AS46: =IF(ISNUMBER($AH46),IF($AH46<0,100,IF($AH46<=20,50,0)),"") | AT46: =IF(ISNUMBER($AI46),IF($AI46<0.95,100,IF($AI46<=1,50,0)),"") | AU46: =IF(ISNUMBER($AJ46),IF($AJ46<30,0,IF($AJ46<40,50,IF($AJ46<=90,100,50))),"") | AV46: =IF(ISNUMBER($AK46),IF($AK46>-0.2,100,IF($AK46>=-0.4,50,0)),"") | AW46: =01_指標庫!$H$4*ISNUMBER($F46)+01_指標庫!$H$5*ISNUMBER($AA46)+01_指標庫!$H$6*ISNUMBER($G46)+01_指標庫!$H$7*ISNUMBER($H46)+01_指標庫!$H$8*ISNUMBER($AF46)+01_指標庫!$H$9*ISNUMBER($AG46)+01_指標庫!$H$10*ISNUMBER($AB46)+01_指標庫!$H$11*ISNUMBER($AC46)+01_指標庫!$H$12*ISNUMBER($AD46)+01_指標庫!$H$13*ISNUMBER($AE46)+01_指標庫!$H$14*ISNUMBER($I46)+01_指標庫!$H$15*ISNUMBER($AH46)+01_指標庫!$H$16*ISNUMBER($K46)+01_指標庫!$H$17*ISNUMBER($AI46)+01_指標庫!$H$18*ISNUMBER($AJ46)+01_指標庫!$H$19*ISNUMBER($AK46)+01_指標庫!$H$20*ISNUMBER($BB46)+01_指標庫!$H$21*ISNUMBER($BC46) -> 49 | AX46: =IF(AW46=0,50,ROUND((01_指標庫!$H$4*IF(ISNUMBER($F46),L46,0)+01_指標庫!$H$5*IF(ISNUMBER($AA46),AL46,0)+01_指標庫!$H$6*IF(ISNUMBER($G46),M46,0)+01_指標庫!$H$7*IF(ISNUMBER($H46),N46,0)+01_指標庫!$H$8*IF(ISNUMBER($AF46),AQ46,0)+01_指標庫!$H$9*IF(ISNUMBER($AG46),AR46,0)+01_指標庫!$H$10*IF(ISNUMBER($AB46),AM46,0)+01_指標庫!$H$11*IF(ISNUMBER($AC46),AN46,0)+01_指標庫!$H$12*IF(ISNUMBER($AD46),AO46,0)+01_指標庫!$H$13*IF(ISNUMBER($AE46),AP46,0)+01_指標庫!$H$14*IF(ISNUMBER($I46),O46,0)+01_指標庫!$H$15*IF(ISNUMBER($AH46),AS46,0)+01_指標庫!$H$16*IF(ISNUMBER($K46),P46,0)+01_指標庫!$H$17*IF(ISNUMBER($AI46),AT46,0)+01_指標庫!$H$18*IF(ISNUMBER($AJ46),AU46,0)+01_指標庫!$H$19*IF(ISNUMBER($AK46),AV46,0)+01_指標庫!$H$20*IF(ISNUMBER($BB46),BB46,0)+01_指標庫!$H$21*IF(ISNUMBER($BC46),BC46,0))/AW46,1)) -> 72.4 | BA46: =AVERAGE($E42:$E46)/AVERAGE($E37:$E46)-1 -> 0.00014714658 | BB46: =IF(ISNUMBER($BA46),IF(OR($S46<=-0.03,$BA46<-0.003),0,IF(OR($S46<=-0.02,$BA46<0.01),50,100)),"") -> 50 | BC46: =IF(OR(COUNT($AZ46)=0,COUNT($AZ45)=0),"",IF(OR($AY46/$AZ45-1<=-0.03,$AZ46/$AZ45-1<=-0.045,IF(COUNT($AZ37:$AZ46)=10,AVERAGE($AZ42:$AZ46)/AVERAGE($AZ37:$AZ46)-1<-0.01,FALSE())),0,IF(OR($AZ46/$AZ45-1<=-0.02,IF(COUNT($AZ37:$AZ46)=10,AVERAGE($AZ42:$AZ46)/AVERAGE($AZ37:$AZ46)-1<0.005,FALSE())),50,100)))
A47: 43 | B47: 42620 | C47: 2016 | D47: 三 | E47: 4831.86 | F47: 0.080308 | G47: 0 | H47: 0.898 | I47: 507 | J47: real | K47: 11.94 | L47: =IF(COUNT(F47)=0,50,IF(F47>=0,100,IF(F47>=-0.02,50,0))) -> 100 | M47: =IF(COUNT(G47)=0,50,IF(G47>-0.06,100,IF(G47>-0.15,50,0))) -> 100 | N47: =IF(COUNT(H47)=0,50,IF(H47>=0.6,100,IF(H47>=0.4,50,0))) -> 100 | O47: =IF(COUNT(I47)=0,50,IF(J47="proxy_vix",50,IF(I47<350,100,IF(I47<=450,50,0)))) -> 0 | P47: =IF(COUNT(K47)=0,50,IF(K47<20,100,IF(K47<=25,50,0))) -> 100 | S47: =$E47/$E46-1 -> 0.00048659181 | T47: =$K47/$K46-1 -> -0.006655574 | Y47: =IF(AX47>=70,"EASY",IF(AX47>40,"UNCERTAIN","HARD")) -> EASY | AA47: =IF($A47<200,"",AVERAGE($E5:$E47)/AVERAGE($E5:$E47)-1) | AB47: =LOOKUP($B47,07_L1政策步階!$A$4:$A$14,07_L1政策步階!$C$4:$C$14) -> 0 | AL47: =IF(ISNUMBER($AA47),IF($AA47>=0.005,100,IF($AA47>=-0.015,50,0)),"") | AM47: =IF(ISNUMBER($AB47),IF($AB47=1,100,IF($AB47=0,50,0)),"") -> 50 | AN47: =IF(ISNUMBER($AC47),IF($AC47>=0.001,100,IF($AC47>=-0.003,50,0)),"") | AO47: =IF(ISNUMBER($AD47),IF($AD47>=0.04,100,IF($AD47>=0,50,0)),"") | AP47: =IF(ISNUMBER($AE47),IF($AE47>=25,100,IF($AE47>=-75,50,0)),"") | AQ47: =IF(ISNUMBER($AF47),IF($AF47>0,100,IF($AF47>=-50,50,0)),"") | AR47: =IF(ISNUMBER($AG47),IF($AG47=1,100,IF($AG47=0,50,0)),"") | AS47: =IF(ISNUMBER($AH47),IF($AH47<0,100,IF($AH47<=20,50,0)),"") | AT47: =IF(ISNUMBER($AI47),IF($AI47<0.95,100,IF($AI47<=1,50,0)),"") | AU47: =IF(ISNUMBER($AJ47),IF($AJ47<30,0,IF($AJ47<40,50,IF($AJ47<=90,100,50))),"") | AV47: =IF(ISNUMBER($AK47),IF($AK47>-0.2,100,IF($AK47>=-0.4,50,0)),"") | AW47: =01_指標庫!$H$4*ISNUMBER($F47)+01_指標庫!$H$5*ISNUMBER($AA47)+01_指標庫!$H$6*ISNUMBER($G47)+01_指標庫!$H$7*ISNUMBER($H47)+01_指標庫!$H$8*ISNUMBER($AF47)+01_指標庫!$H$9*ISNUMBER($AG47)+01_指標庫!$H$10*ISNUMBER($AB47)+01_指標庫!$H$11*ISNUMBER($AC47)+01_指標庫!$H$12*ISNUMBER($AD47)+01_指標庫!$H$13*ISNUMBER($AE47)+01_指標庫!$H$14*ISNUMBER($I47)+01_指標庫!$H$15*ISNUMBER($AH47)+01_指標庫!$H$16*ISNUMBER($K47)+01_指標庫!$H$17*ISNUMBER($AI47)+01_指標庫!$H$18*ISNUMBER($AJ47)+01_指標庫!$H$19*ISNUMBER($AK47)+01_指標庫!$H$20*ISNUMBER($BB47)+01_指標庫!$H$21*ISNUMBER($BC47) -> 49 | AX47: =IF(AW47=0,50,ROUND((01_指標庫!$H$4*IF(ISNUMBER($F47),L47,0)+01_指標庫!$H$5*IF(ISNUMBER($AA47),AL47,0)+01_指標庫!$H$6*IF(ISNUMBER($G47),M47,0)+01_指標庫!$H$7*IF(ISNUMBER($H47),N47,0)+01_指標庫!$H$8*IF(ISNUMBER($AF47),AQ47,0)+01_指標庫!$H$9*IF(ISNUMBER($AG47),AR47,0)+01_指標庫!$H$10*IF(ISNUMBER($AB47),AM47,0)+01_指標庫!$H$11*IF(ISNUMBER($AC47),AN47,0)+01_指標庫!$H$12*IF(ISNUMBER($AD47),AO47,0)+01_指標庫!$H$13*IF(ISNUMBER($AE47),AP47,0)+01_指標庫!$H$14*IF(ISNUMBER($I47),O47,0)+01_指標庫!$H$15*IF(ISNUMBER($AH47),AS47,0)+01_指標庫!$H$16*IF(ISNUMBER($K47),P47,0)+01_指標庫!$H$17*IF(ISNUMBER($AI47),AT47,0)+01_指標庫!$H$18*IF(ISNUMBER($AJ47),AU47,0)+01_指標庫!$H$19*IF(ISNUMBER($AK47),AV47,0)+01_指標庫!$H$20*IF(ISNUMBER($BB47),BB47,0)+01_指標庫!$H$21*IF(ISNUMBER($BC47),BC47,0))/AW47,1)) -> 72.4 | BA47: =AVERAGE($E43:$E47)/AVERAGE($E38:$E47)-1 -> 0.002199488 | BB47: =IF(ISNUMBER($BA47),IF(OR($S47<=-0.03,$BA47<-0.003),0,IF(OR($S47<=-0.02,$BA47<0.01),50,100)),"") -> 50 | BC47: =IF(OR(COUNT($AZ47)=0,COUNT($AZ46)=0),"",IF(OR($AY47/$AZ46-1<=-0.03,$AZ47/$AZ46-1<=-0.045,IF(COUNT($AZ38:$AZ47)=10,AVERAGE($AZ43:$AZ47)/AVERAGE($AZ38:$AZ47)-1<-0.01,FALSE())),0,IF(OR($AZ47/$AZ46-1<=-0.02,IF(COUNT($AZ38:$AZ47)=10,AVERAGE($AZ43:$AZ47)/AVERAGE($AZ38:$AZ47)-1<0.005,FALSE())),50,100)))
A48: 44 | B48: 42621 | C48: 2016 | D48: 四 | E48: 4804 | F48: 0.073937 | G48: -0.005766 | H48: 0.8776 | I48: 499 | J48: real | K48: 12.51 | L48: =IF(COUNT(F48)=0,50,IF(F48>=0,100,IF(F48>=-0.02,50,0))) -> 100 | M48: =IF(COUNT(G48)=0,50,IF(G48>-0.06,100,IF(G48>-0.15,50,0))) -> 100 | N48: =IF(COUNT(H48)=0,50,IF(H48>=0.6,100,IF(H48>=0.4,50,0))) -> 100 | O48: =IF(COUNT(I48)=0,50,IF(J48="proxy_vix",50,IF(I48<350,100,IF(I48<=450,50,0)))) -> 0 | P48: =IF(COUNT(K48)=0,50,IF(K48<20,100,IF(K48<=25,50,0))) -> 100 | S48: =$E48/$E47-1 -> -0.0057658955 | T48: =$K48/$K47-1 -> 0.047738693 | Y48: =IF(AX48>=70,"EASY",IF(AX48>40,"UNCERTAIN","HARD")) -> EASY | AA48: =IF($A48<200,"",AVERAGE($E5:$E48)/AVERAGE($E5:$E48)-1) | AB48: =LOOKUP($B48,07_L1政策步階!$A$4:$A$14,07_L1政策步階!$C$4:$C$14) -> 0 | AL48: =IF(ISNUMBER($AA48),IF($AA48>=0.005,100,IF($AA48>=-0.015,50,0)),"") | AM48: =IF(ISNUMBER($AB48),IF($AB48=1,100,IF($AB48=0,50,0)),"") -> 50 | AN48: =IF(ISNUMBER($AC48),IF($AC48>=0.001,100,IF($AC48>=-0.003,50,0)),"") | AO48: =IF(ISNUMBER($AD48),IF($AD48>=0.04,100,IF($AD48>=0,50,0)),"") | AP48: =IF(ISNUMBER($AE48),IF($AE48>=25,100,IF($AE48>=-75,50,0)),"") | AQ48: =IF(ISNUMBER($AF48),IF($AF48>0,100,IF($AF48>=-50,50,0)),"") | AR48: =IF(ISNUMBER($AG48),IF($AG48=1,100,IF($AG48=0,50,0)),"") | AS48: =IF(ISNUMBER($AH48),IF($AH48<0,100,IF($AH48<=20,50,0)),"") | AT48: =IF(ISNUMBER($AI48),IF($AI48<0.95,100,IF($AI48<=1,50,0)),"") | AU48: =IF(ISNUMBER($AJ48),IF($AJ48<30,0,IF($AJ48<40,50,IF($AJ48<=90,100,50))),"") | AV48: =IF(ISNUMBER($AK48),IF($AK48>-0.2,100,IF($AK48>=-0.4,50,0)),"") | AW48: =01_指標庫!$H$4*ISNUMBER($F48)+01_指標庫!$H$5*ISNUMBER($AA48)+01_指標庫!$H$6*ISNUMBER($G48)+01_指標庫!$H$7*ISNUMBER($H48)+01_指標庫!$H$8*ISNUMBER($AF48)+01_指標庫!$H$9*ISNUMBER($AG48)+01_指標庫!$H$10*ISNUMBER($AB48)+01_指標庫!$H$11*ISNUMBER($AC48)+01_指標庫!$H$12*ISNUMBER($AD48)+01_指標庫!$H$13*ISNUMBER($AE48)+01_指標庫!$H$14*ISNUMBER($I48)+01_指標庫!$H$15*ISNUMBER($AH48)+01_指標庫!$H$16*ISNUMBER($K48)+01_指標庫!$H$17*ISNUMBER($AI48)+01_指標庫!$H$18*ISNUMBER($AJ48)+01_指標庫!$H$19*ISNUMBER($AK48)+01_指標庫!$H$20*ISNUMBER($BB48)+01_指標庫!$H$21*ISNUMBER($BC48) -> 49 | AX48: =IF(AW48=0,50,ROUND((01_指標庫!$H$4*IF(ISNUMBER($F48),L48,0)+01_指標庫!$H$5*IF(ISNUMBER($AA48),AL48,0)+01_指標庫!$H$6*IF(ISNUMBER($G48),M48,0)+01_指標庫!$H$7*IF(ISNUMBER($H48),N48,0)+01_指標庫!$H$8*IF(ISNUMBER($AF48),AQ48,0)+01_指標庫!$H$9*IF(ISNUMBER($AG48),AR48,0)+01_指標庫!$H$10*IF(ISNUMBER($AB48),AM48,0)+01_指標庫!$H$11*IF(ISNUMBER($AC48),AN48,0)+01_指標庫!$H$12*IF(ISNUMBER($AD48),AO48,0)+01_指標庫!$H$13*IF(ISNUMBER($AE48),AP48,0)+01_指標庫!$H$14*IF(ISNUMBER($I48),O48,0)+01_指標庫!$H$15*IF(ISNUMBER($AH48),AS48,0)+01_指標庫!$H$16*IF(ISNUMBER($K48),P48,0)+01_指標庫!$H$17*IF(ISNUMBER($AI48),AT48,0)+01_指標庫!$H$18*IF(ISNUMBER($AJ48),AU48,0)+01_指標庫!$H$19*IF(ISNUMBER($AK48),AV48,0)+01_指標庫!$H$20*IF(ISNUMBER($BB48),BB48,0)+01_指標庫!$H$21*IF(ISNUMBER($BC48),BC48,0))/AW48,1)) -> 72.4 | BA48: =AVERAGE($E44:$E48)/AVERAGE($E39:$E48)-1 -> 0.0031452509 | BB48: =IF(ISNUMBER($BA48),IF(OR($S48<=-0.03,$BA48<-0.003),0,IF(OR($S48<=-0.02,$BA48<0.01),50,100)),"") -> 50 | BC48: =IF(OR(COUNT($AZ48)=0,COUNT($AZ47)=0),"",IF(OR($AY48/$AZ47-1<=-0.03,$AZ48/$AZ47-1<=-0.045,IF(COUNT($AZ39:$AZ48)=10,AVERAGE($AZ44:$AZ48)/AVERAGE($AZ39:$AZ48)-1<-0.01,FALSE())),0,IF(OR($AZ48/$AZ47-1<=-0.02,IF(COUNT($AZ39:$AZ48)=10,AVERAGE($AZ44:$AZ48)/AVERAGE($AZ39:$AZ48)-1<0.005,FALSE())),50,100)))
A49: 45 | B49: 42622 | C49: 2016 | D49: 五 | E49: 4681.54 | F49: 0.046554 | G49: -0.03111 | H49: 0.7959 | I49: 510 | J49: real | K49: 17.5 | L49: =IF(COUNT(F49)=0,50,IF(F49>=0,100,IF(F49>=-0.02,50,0))) -> 100 | M49: =IF(COUNT(G49)=0,50,IF(G49>-0.06,100,IF(G49>-0.15,50,0))) -> 100 | N49: =IF(COUNT(H49)=0,50,IF(H49>=0.6,100,IF(H49>=0.4,50,0))) -> 100 | O49: =IF(COUNT(I49)=0,50,IF(J49="proxy_vix",50,IF(I49<350,100,IF(I49<=450,50,0)))) -> 0 | P49: =IF(COUNT(K49)=0,50,IF(K49<20,100,IF(K49<=25,50,0))) -> 100 | S49: =$E49/$E48-1 -> -0.025491257 | T49: =$K49/$K48-1 -> 0.3988809 | Y49: =IF(AX49>=70,"EASY",IF(AX49>40,"UNCERTAIN","HARD")) -> EASY | AA49: =IF($A49<200,"",AVERAGE($E5:$E49)/AVERAGE($E5:$E49)-1) | AB49: =LOOKUP($B49,07_L1政策步階!$A$4:$A$14,07_L1政策步階!$C$4:$C$14) -> 0 | AL49: =IF(ISNUMBER($AA49),IF($AA49>=0.005,100,IF($AA49>=-0.015,50,0)),"") | AM49: =IF(ISNUMBER($AB49),IF($AB49=1,100,IF($AB49=0,50,0)),"") -> 50 | AN49: =IF(ISNUMBER($AC49),IF($AC49>=0.001,100,IF($AC49>=-0.003,50,0)),"") | AO49: =IF(ISNUMBER($AD49),IF($AD49>=0.04,100,IF($AD49>=0,50,0)),"") | AP49: =IF(ISNUMBER($AE49),IF($AE49>=25,100,IF($AE49>=-75,50,0)),"") | AQ49: =IF(ISNUMBER($AF49),IF($AF49>0,100,IF($AF49>=-50,50,0)),"") | AR49: =IF(ISNUMBER($AG49),IF($AG49=1,100,IF($AG49=0,50,0)),"") | AS49: =IF(ISNUMBER($AH49),IF($AH49<0,100,IF($AH49<=20,50,0)),"") | AT49: =IF(ISNUMBER($AI49),IF($AI49<0.95,100,IF($AI49<=1,50,0)),"") | AU49: =IF(ISNUMBER($AJ49),IF($AJ49<30,0,IF($AJ49<40,50,IF($AJ49<=90,100,50))),"") | AV49: =IF(ISNUMBER($AK49),IF($AK49>-0.2,100,IF($AK49>=-0.4,50,0)),"") | AW49: =01_指標庫!$H$4*ISNUMBER($F49)+01_指標庫!$H$5*ISNUMBER($AA49)+01_指標庫!$H$6*ISNUMBER($G49)+01_指標庫!$H$7*ISNUMBER($H49)+01_指標庫!$H$8*ISNUMBER($AF49)+01_指標庫!$H$9*ISNUMBER($AG49)+01_指標庫!$H$10*ISNUMBER($AB49)+01_指標庫!$H$11*ISNUMBER($AC49)+01_指標庫!$H$12*ISNUMBER($AD49)+01_指標庫!$H$13*ISNUMBER($AE49)+01_指標庫!$H$14*ISNUMBER($I49)+01_指標庫!$H$15*ISNUMBER($AH49)+01_指標庫!$H$16*ISNUMBER($K49)+01_指標庫!$H$17*ISNUMBER($AI49)+01_指標庫!$H$18*ISNUMBER($AJ49)+01_指標庫!$H$19*ISNUMBER($AK49)+01_指標庫!$H$20*ISNUMBER($BB49)+01_指標庫!$H$21*ISNUMBER($BC49) -> 49 | AX49: =IF(AW49=0,50,ROUND((01_指標庫!$H$4*IF(ISNUMBER($F49),L49,0)+01_指標庫!$H$5*IF(ISNUMBER($AA49),AL49,0)+01_指標庫!$H$6*IF(ISNUMBER($G49),M49,0)+01_指標庫!$H$7*IF(ISNUMBER($H49),N49,0)+01_指標庫!$H$8*IF(ISNUMBER($AF49),AQ49,0)+01_指標庫!$H$9*IF(ISNUMBER($AG49),AR49,0)+01_指標庫!$H$10*IF(ISNUMBER($AB49),AM49,0)+01_指標庫!$H$11*IF(ISNUMBER($AC49),AN49,0)+01_指標庫!$H$12*IF(ISNUMBER($AD49),AO49,0)+01_指標庫!$H$13*IF(ISNUMBER($AE49),AP49,0)+01_指標庫!$H$14*IF(ISNUMBER($I49),O49,0)+01_指標庫!$H$15*IF(ISNUMBER($AH49),AS49,0)+01_指標庫!$H$16*IF(ISNUMBER($K49),P49,0)+01_指標庫!$H$17*IF(ISNUMBER($AI49),AT49,0)+01_指標庫!$H$18*IF(ISNUMBER($AJ49),AU49,0)+01_指標庫!$H$19*IF(ISNUMBER($AK49),AV49,0)+01_指標庫!$H$20*IF(ISNUMBER($BB49),BB49,0)+01_指標庫!$H$21*IF(ISNUMBER($BC49),BC49,0))/AW49,1)) -> 72.4 | BA49: =AVERAGE($E45:$E49)/AVERAGE($E40:$E49)-1 -> 0.00083362225 | BB49: =IF(ISNUMBER($BA49),IF(OR($S49<=-0.03,$BA49<-0.003),0,IF(OR($S49<=-0.02,$BA49<0.01),50,100)),"") -> 50 | BC49: =IF(OR(COUNT($AZ49)=0,COUNT($AZ48)=0),"",IF(OR($AY49/$AZ48-1<=-0.03,$AZ49/$AZ48-1<=-0.045,IF(COUNT($AZ40:$AZ49)=10,AVERAGE($AZ45:$AZ49)/AVERAGE($AZ40:$AZ49)-1<-0.01,FALSE())),0,IF(OR($AZ49/$AZ48-1<=-0.02,IF(COUNT($AZ40:$AZ49)=10,AVERAGE($AZ45:$AZ49)/AVERAGE($AZ40:$AZ49)-1<0.005,FALSE())),50,100)))
A50: 46 | B50: 42625 | C50: 2016 | D50: 一 | E50: 4764.65 | F50: 0.065019 | G50: -0.01391 | H50: 0.8776 | I50: 518 | J50: real | K50: 15.16 | L50: =IF(COUNT(F50)=0,50,IF(F50>=0,100,IF(F50>=-0.02,50,0))) -> 100 | M50: =IF(COUNT(G50)=0,50,IF(G50>-0.06,100,IF(G50>-0.15,50,0))) -> 100 | N50: =IF(COUNT(H50)=0,50,IF(H50>=0.6,100,IF(H50>=0.4,50,0))) -> 100 | O50: =IF(COUNT(I50)=0,50,IF(J50="proxy_vix",50,IF(I50<350,100,IF(I50<=450,50,0)))) -> 0 | P50: =IF(COUNT(K50)=0,50,IF(K50<20,100,IF(K50<=25,50,0))) -> 100 | S50: =$E50/$E49-1 -> 0.017752705 | T50: =$K50/$K49-1 -> -0.13371429 | Y50: =IF(AX50>=70,"EASY",IF(AX50>40,"UNCERTAIN","HARD")) -> EASY | AA50: =IF($A50<200,"",AVERAGE($E5:$E50)/AVERAGE($E5:$E50)-1) | AB50: =LOOKUP($B50,07_L1政策步階!$A$4:$A$14,07_L1政策步階!$C$4:$C$14) -> 0 | AL50: =IF(ISNUMBER($AA50),IF($AA50>=0.005,100,IF($AA50>=-0.015,50,0)),"") | AM50: =IF(ISNUMBER($AB50),IF($AB50=1,100,IF($AB50=0,50,0)),"") -> 50 | AN50: =IF(ISNUMBER($AC50),IF($AC50>=0.001,100,IF($AC50>=-0.003,50,0)),"") | AO50: =IF(ISNUMBER($AD50),IF($AD50>=0.04,100,IF($AD50>=0,50,0)),"") | AP50: =IF(ISNUMBER($AE50),IF($AE50>=25,100,IF($AE50>=-75,50,0)),"") | AQ50: =IF(ISNUMBER($AF50),IF($AF50>0,100,IF($AF50>=-50,50,0)),"") | AR50: =IF(ISNUMBER($AG50),IF($AG50=1,100,IF($AG50=0,50,0)),"") | AS50: =IF(ISNUMBER($AH50),IF($AH50<0,100,IF($AH50<=20,50,0)),"") | AT50: =IF(ISNUMBER($AI50),IF($AI50<0.95,100,IF($AI50<=1,50,0)),"") | AU50: =IF(ISNUMBER($AJ50),IF($AJ50<30,0,IF($AJ50<40,50,IF($AJ50<=90,100,50))),"") | AV50: =IF(ISNUMBER($AK50),IF($AK50>-0.2,100,IF($AK50>=-0.4,50,0)),"") | AW50: =01_指標庫!$H$4*ISNUMBER($F50)+01_指標庫!$H$5*ISNUMBER($AA50)+01_指標庫!$H$6*ISNUMBER($G50)+01_指標庫!$H$7*ISNUMBER($H50)+01_指標庫!$H$8*ISNUMBER($AF50)+01_指標庫!$H$9*ISNUMBER($AG50)+01_指標庫!$H$10*ISNUMBER($AB50)+01_指標庫!$H$11*ISNUMBER($AC50)+01_指標庫!$H$12*ISNUMBER($AD50)+01_指標庫!$H$13*ISNUMBER($AE50)+01_指標庫!$H$14*ISNUMBER($I50)+01_指標庫!$H$15*ISNUMBER($AH50)+01_指標庫!$H$16*ISNUMBER($K50)+01_指標庫!$H$17*ISNUMBER($AI50)+01_指標庫!$H$18*ISNUMBER($AJ50)+01_指標庫!$H$19*ISNUMBER($AK50)+01_指標庫!$H$20*ISNUMBER($BB50)+01_指標庫!$H$21*ISNUMBER($BC50) -> 49 | AX50: =IF(AW50=0,50,ROUND((01_指標庫!$H$4*IF(ISNUMBER($F50),L50,0)+01_指標庫!$H$5*IF(ISNUMBER($AA50),AL50,0)+01_指標庫!$H$6*IF(ISNUMBER($G50),M50,0)+01_指標庫!$H$7*IF(ISNUMBER($H50),N50,0)+01_指標庫!$H$8*IF(ISNUMBER($AF50),AQ50,0)+01_指標庫!$H$9*IF(ISNUMBER($AG50),AR50,0)+01_指標庫!$H$10*IF(ISNUMBER($AB50),AM50,0)+01_指標庫!$H$11*IF(ISNUMBER($AC50),AN50,0)+01_指標庫!$H$12*IF(ISNUMBER($AD50),AO50,0)+01_指標庫!$H$13*IF(ISNUMBER($AE50),AP50,0)+01_指標庫!$H$14*IF(ISNUMBER($I50),O50,0)+01_指標庫!$H$15*IF(ISNUMBER($AH50),AS50,0)+01_指標庫!$H$16*IF(ISNUMBER($K50),P50,0)+01_指標庫!$H$17*IF(ISNUMBER($AI50),AT50,0)+01_指標庫!$H$18*IF(ISNUMBER($AJ50),AU50,0)+01_指標庫!$H$19*IF(ISNUMBER($AK50),AV50,0)+01_指標庫!$H$20*IF(ISNUMBER($BB50),BB50,0)+01_指標庫!$H$21*IF(ISNUMBER($BC50),BC50,0))/AW50,1)) -> 72.4 | BA50: =AVERAGE($E46:$E50)/AVERAGE($E41:$E50)-1 -> -0.00019338369 | BB50: =IF(ISNUMBER($BA50),IF(OR($S50<=-0.03,$BA50<-0.003),0,IF(OR($S50<=-0.02,$BA50<0.01),50,100)),"") -> 50 | BC50: =IF(OR(COUNT($AZ50)=0,COUNT($AZ49)=0),"",IF(OR($AY50/$AZ49-1<=-0.03,$AZ50/$AZ49-1<=-0.045,IF(COUNT($AZ41:$AZ50)=10,AVERAGE($AZ46:$AZ50)/AVERAGE($AZ41:$AZ50)-1<-0.01,FALSE())),0,IF(OR($AZ50/$AZ49-1<=-0.02,IF(COUNT($AZ41:$AZ50)=10,AVERAGE($AZ46:$AZ50)/AVERAGE($AZ41:$AZ50)-1<0.005,FALSE())),50,100)))
A51: 47 | B51: 42626 | C51: 2016 | D51: 二 | E51: 4722.85 | F51: 0.055617 | G51: -0.022561 | H51: 0.8571 | I51: 524 | J51: real | K51: 17.85 | L51: =IF(COUNT(F51)=0,50,IF(F51>=0,100,IF(F51>=-0.02,50,0))) -> 100 | M51: =IF(COUNT(G51)=0,50,IF(G51>-0.06,100,IF(G51>-0.15,50,0))) -> 100 | N51: =IF(COUNT(H51)=0,50,IF(H51>=0.6,100,IF(H51>=0.4,50,0))) -> 100 | O51: =IF(COUNT(I51)=0,50,IF(J51="proxy_vix",50,IF(I51<350,100,IF(I51<=450,50,0)))) -> 0 | P51: =IF(COUNT(K51)=0,50,IF(K51<20,100,IF(K51<=25,50,0))) -> 100 | S51: =$E51/$E50-1 -> -0.0087729424 | T51: =$K51/$K50-1 -> 0.17744063 | Y51: =IF(AX51>=70,"EASY",IF(AX51>40,"UNCERTAIN","HARD")) -> UNCERTAIN | AA51: =IF($A51<200,"",AVERAGE($E5:$E51)/AVERAGE($E5:$E51)-1) | AB51: =LOOKUP($B51,07_L1政策步階!$A$4:$A$14,07_L1政策步階!$C$4:$C$14) -> 0 | AL51: =IF(ISNUMBER($AA51),IF($AA51>=0.005,100,IF($AA51>=-0.015,50,0)),"") | AM51: =IF(ISNUMBER($AB51),IF($AB51=1,100,IF($AB51=0,50,0)),"") -> 50 | AN51: =IF(ISNUMBER($AC51),IF($AC51>=0.001,100,IF($AC51>=-0.003,50,0)),"") | AO51: =IF(ISNUMBER($AD51),IF($AD51>=0.04,100,IF($AD51>=0,50,0)),"") | AP51: =IF(ISNUMBER($AE51),IF($AE51>=25,100,IF($AE51>=-75,50,0)),"") | AQ51: =IF(ISNUMBER($AF51),IF($AF51>0,100,IF($AF51>=-50,50,0)),"") | AR51: =IF(ISNUMBER($AG51),IF($AG51=1,100,IF($AG51=0,50,0)),"") | AS51: =IF(ISNUMBER($AH51),IF($AH51<0,100,IF($AH51<=20,50,0)),"") | AT51: =IF(ISNUMBER($AI51),IF($AI51<0.95,100,IF($AI51<=1,50,0)),"") | AU51: =IF(ISNUMBER($AJ51),IF($AJ51<30,0,IF($AJ51<40,50,IF($AJ51<=90,100,50))),"") | AV51: =IF(ISNUMBER($AK51),IF($AK51>-0.2,100,IF($AK51>=-0.4,50,0)),"") | AW51: =01_指標庫!$H$4*ISNUMBER($F51)+01_指標庫!$H$5*ISNUMBER($AA51)+01_指標庫!$H$6*ISNUMBER($G51)+01_指標庫!$H$7*ISNUMBER($H51)+01_指標庫!$H$8*ISNUMBER($AF51)+01_指標庫!$H$9*ISNUMBER($AG51)+01_指標庫!$H$10*ISNUMBER($AB51)+01_指標庫!$H$11*ISNUMBER($AC51)+01_指標庫!$H$12*ISNUMBER($AD51)+01_指標庫!$H$13*ISNUMBER($AE51)+01_指標庫!$H$14*ISNUMBER($I51)+01_指標庫!$H$15*ISNUMBER($AH51)+01_指標庫!$H$16*ISNUMBER($K51)+01_指標庫!$H$17*ISNUMBER($AI51)+01_指標庫!$H$18*ISNUMBER($AJ51)+01_指標庫!$H$19*ISNUMBER($AK51)+01_指標庫!$H$20*ISNUMBER($BB51)+01_指標庫!$H$21*ISNUMBER($BC51) -> 49 | AX51: =IF(AW51=0,50,ROUND((01_指標庫!$H$4*IF(ISNUMBER($F51),L51,0)+01_指標庫!$H$5*IF(ISNUMBER($AA51),AL51,0)+01_指標庫!$H$6*IF(ISNUMBER($G51),M51,0)+01_指標庫!$H$7*IF(ISNUMBER($H51),N51,0)+01_指標庫!$H$8*IF(ISNUMBER($AF51),AQ51,0)+01_指標庫!$H$9*IF(ISNUMBER($AG51),AR51,0)+01_指標庫!$H$10*IF(ISNUMBER($AB51),AM51,0)+01_指標庫!$H$11*IF(ISNUMBER($AC51),AN51,0)+01_指標庫!$H$12*IF(ISNUMBER($AD51),AO51,0)+01_指標庫!$H$13*IF(ISNUMBER($AE51),AP51,0)+01_指標庫!$H$14*IF(ISNUMBER($I51),O51,0)+01_指標庫!$H$15*IF(ISNUMBER($AH51),AS51,0)+01_指標庫!$H$16*IF(ISNUMBER($K51),P51,0)+01_指標庫!$H$17*IF(ISNUMBER($AI51),AT51,0)+01_指標庫!$H$18*IF(ISNUMBER($AJ51),AU51,0)+01_指標庫!$H$19*IF(ISNUMBER($AK51),AV51,0)+01_指標庫!$H$20*IF(ISNUMBER($BB51),BB51,0)+01_指標庫!$H$21*IF(ISNUMBER($BC51),BC51,0))/AW51,1)) -> 66.3 | BA51: =AVERAGE($E47:$E51)/AVERAGE($E42:$E51)-1 -> -0.0032310858 | BB51: =IF(ISNUMBER($BA51),IF(OR($S51<=-0.03,$BA51<-0.003),0,IF(OR($S51<=-0.02,$BA51<0.01),50,100)),"") -> 0 | BC51: =IF(OR(COUNT($AZ51)=0,COUNT($AZ50)=0),"",IF(OR($AY51/$AZ50-1<=-0.03,$AZ51/$AZ50-1<=-0.045,IF(COUNT($AZ42:$AZ51)=10,AVERAGE($AZ47:$AZ51)/AVERAGE($AZ42:$AZ51)-1<-0.01,FALSE())),0,IF(OR($AZ51/$AZ50-1<=-0.02,IF(COUNT($AZ42:$AZ51)=10,AVERAGE($AZ47:$AZ51)/AVERAGE($AZ42:$AZ51)-1<0.005,FALSE())),50,100)))
A52: 48 | B52: 42627 | C52: 2016 | D52: 三 | E52: 4746.06 | F52: 0.060727 | G52: -0.017757 | H52: 0.8367 | I52: 526 | J52: real | K52: 18.14 | L52: =IF(COUNT(F52)=0,50,IF(F52>=0,100,IF(F52>=-0.02,50,0))) -> 100 | M52: =IF(COUNT(G52)=0,50,IF(G52>-0.06,100,IF(G52>-0.15,50,0))) -> 100 | N52: =IF(COUNT(H52)=0,50,IF(H52>=0.6,100,IF(H52>=0.4,50,0))) -> 100 | O52: =IF(COUNT(I52)=0,50,IF(J52="proxy_vix",50,IF(I52<350,100,IF(I52<=450,50,0)))) -> 0 | P52: =IF(COUNT(K52)=0,50,IF(K52<20,100,IF(K52<=25,50,0))) -> 100 | S52: =$E52/$E51-1 -> 0.0049144055 | T52: =$K52/$K51-1 -> 0.016246499 | Y52: =IF(AX52>=70,"EASY",IF(AX52>40,"UNCERTAIN","HARD")) -> UNCERTAIN | AA52: =IF($A52<200,"",AVERAGE($E5:$E52)/AVERAGE($E5:$E52)-1) | AB52: =LOOKUP($B52,07_L1政策步階!$A$4:$A$14,07_L1政策步階!$C$4:$C$14) -> 0 | AL52: =IF(ISNUMBER($AA52),IF($AA52>=0.005,100,IF($AA52>=-0.015,50,0)),"") | AM52: =IF(ISNUMBER($AB52),IF($AB52=1,100,IF($AB52=0,50,0)),"") -> 50 | AN52: =IF(ISNUMBER($AC52),IF($AC52>=0.001,100,IF($AC52>=-0.003,50,0)),"") | AO52: =IF(ISNUMBER($AD52),IF($AD52>=0.04,100,IF($AD52>=0,50,0)),"") | AP52: =IF(ISNUMBER($AE52),IF($AE52>=25,100,IF($AE52>=-75,50,0)),"") | AQ52: =IF(ISNUMBER($AF52),IF($AF52>0,100,IF($AF52>=-50,50,0)),"") | AR52: =IF(ISNUMBER($AG52),IF($AG52=1,100,IF($AG52=0,50,0)),"") | AS52: =IF(ISNUMBER($AH52),IF($AH52<0,100,IF($AH52<=20,50,0)),"") | AT52: =IF(ISNUMBER($AI52),IF($AI52<0.95,100,IF($AI52<=1,50,0)),"") | AU52: =IF(ISNUMBER($AJ52),IF($AJ52<30,0,IF($AJ52<40,50,IF($AJ52<=90,100,50))),"") | AV52: =IF(ISNUMBER($AK52),IF($AK52>-0.2,100,IF($AK52>=-0.4,50,0)),"") | AW52: =01_指標庫!$H$4*ISNUMBER($F52)+01_指標庫!$H$5*ISNUMBER($AA52)+01_指標庫!$H$6*ISNUMBER($G52)+01_指標庫!$H$7*ISNUMBER($H52)+01_指標庫!$H$8*ISNUMBER($AF52)+01_指標庫!$H$9*ISNUMBER($AG52)+01_指標庫!$H$10*ISNUMBER($AB52)+01_指標庫!$H$11*ISNUMBER($AC52)+01_指標庫!$H$12*ISNUMBER($AD52)+01_指標庫!$H$13*ISNUMBER($AE52)+01_指標庫!$H$14*ISNUMBER($I52)+01_指標庫!$H$15*ISNUMBER($AH52)+01_指標庫!$H$16*ISNUMBER($K52)+01_指標庫!$H$17*ISNUMBER($AI52)+01_指標庫!$H$18*ISNUMBER($AJ52)+01_指標庫!$H$19*ISNUMBER($AK52)+01_指標庫!$H$20*ISNUMBER($BB52)+01_指標庫!$H$21*ISNUMBER($BC52) -> 49 | AX52: =IF(AW52=0,50,ROUND((01_指標庫!$H$4*IF(ISNUMBER($F52),L52,0)+01_指標庫!$H$5*IF(ISNUMBER($AA52),AL52,0)+01_指標庫!$H$6*IF(ISNUMBER($G52),M52,0)+01_指標庫!$H$7*IF(ISNUMBER($H52),N52,0)+01_指標庫!$H$8*IF(ISNUMBER($AF52),AQ52,0)+01_指標庫!$H$9*IF(ISNUMBER($AG52),AR52,0)+01_指標庫!$H$10*IF(ISNUMBER($AB52),AM52,0)+01_指標庫!$H$11*IF(ISNUMBER($AC52),AN52,0)+01_指標庫!$H$12*IF(ISNUMBER($AD52),AO52,0)+01_指標庫!$H$13*IF(ISNUMBER($AE52),AP52,0)+01_指標庫!$H$14*IF(ISNUMBER($I52),O52,0)+01_指標庫!$H$15*IF(ISNUMBER($AH52),AS52,0)+01_指標庫!$H$16*IF(ISNUMBER($K52),P52,0)+01_指標庫!$H$17*IF(ISNUMBER($AI52),AT52,0)+01_指標庫!$H$18*IF(ISNUMBER($AJ52),AU52,0)+01_指標庫!$H$19*IF(ISNUMBER($AK52),AV52,0)+01_指標庫!$H$20*IF(ISNUMBER($BB52),BB52,0)+01_指標庫!$H$21*IF(ISNUMBER($BC52),BC52,0))/AW52,1)) -> 66.3 | BA52: =AVERAGE($E48:$E52)/AVERAGE($E43:$E52)-1 -> -0.0062010047 | BB52: =IF(ISNUMBER($BA52),IF(OR($S52<=-0.03,$BA52<-0.003),0,IF(OR($S52<=-0.02,$BA52<0.01),50,100)),"") -> 0 | BC52: =IF(OR(COUNT($AZ52)=0,COUNT($AZ51)=0),"",IF(OR($AY52/$AZ51-1<=-0.03,$AZ52/$AZ51-1<=-0.045,IF(COUNT($AZ43:$AZ52)=10,AVERAGE($AZ48:$AZ52)/AVERAGE($AZ43:$AZ52)-1<-0.01,FALSE())),0,IF(OR($AZ52/$AZ51-1<=-0.02,IF(COUNT($AZ43:$AZ52)=10,AVERAGE($AZ48:$AZ52)/AVERAGE($AZ43:$AZ52)-1<0.005,FALSE())),50,100)))
A53: 49 | B53: 42628 | C53: 2016 | D53: 四 | E53: 4819.9 | F53: 0.077043 | G53: -0.002475 | H53: 0.8571 | I53: 526 | J53: real | K53: 16.3 | L53: =IF(COUNT(F53)=0,50,IF(F53>=0,100,IF(F53>=-0.02,50,0))) -> 100 | M53: =IF(COUNT(G53)=0,50,IF(G53>-0.06,100,IF(G53>-0.15,50,0))) -> 100 | N53: =IF(COUNT(H53)=0,50,IF(H53>=0.6,100,IF(H53>=0.4,50,0))) -> 100 | O53: =IF(COUNT(I53)=0,50,IF(J53="proxy_vix",50,IF(I53<350,100,IF(I53<=450,50,0)))) -> 0 | P53: =IF(COUNT(K53)=0,50,IF(K53<20,100,IF(K53<=25,50,0))) -> 100 | S53: =$E53/$E52-1 -> 0.015558168 | T53: =$K53/$K52-1 -> -0.1014333 | Y53: =IF(AX53>=70,"EASY",IF(AX53>40,"UNCERTAIN","HARD")) -> UNCERTAIN | AA53: =IF($A53<200,"",AVERAGE($E5:$E53)/AVERAGE($E5:$E53)-1) | AB53: =LOOKUP($B53,07_L1政策步階!$A$4:$A$14,07_L1政策步階!$C$4:$C$14) -> 0 | AL53: =IF(ISNUMBER($AA53),IF($AA53>=0.005,100,IF($AA53>=-0.015,50,0)),"") | AM53: =IF(ISNUMBER($AB53),IF($AB53=1,100,IF($AB53=0,50,0)),"") -> 50 | AN53: =IF(ISNUMBER($AC53),IF($AC53>=0.001,100,IF($AC53>=-0.003,50,0)),"") | AO53: =IF(ISNUMBER($AD53),IF($AD53>=0.04,100,IF($AD53>=0,50,0)),"") | AP53: =IF(ISNUMBER($AE53),IF($AE53>=25,100,IF($AE53>=-75,50,0)),"") | AQ53: =IF(ISNUMBER($AF53),IF($AF53>0,100,IF($AF53>=-50,50,0)),"") | AR53: =IF(ISNUMBER($AG53),IF($AG53=1,100,IF($AG53=0,50,0)),"") | AS53: =IF(ISNUMBER($AH53),IF($AH53<0,100,IF($AH53<=20,50,0)),"") | AT53: =IF(ISNUMBER($AI53),IF($AI53<0.95,100,IF($AI53<=1,50,0)),"") | AU53: =IF(ISNUMBER($AJ53),IF($AJ53<30,0,IF($AJ53<40,50,IF($AJ53<=90,100,50))),"") | AV53: =IF(ISNUMBER($AK53),IF($AK53>-0.2,100,IF($AK53>=-0.4,50,0)),"") | AW53: =01_指標庫!$H$4*ISNUMBER($F53)+01_指標庫!$H$5*ISNUMBER($AA53)+01_指標庫!$H$6*ISNUMBER($G53)+01_指標庫!$H$7*ISNUMBER($H53)+01_指標庫!$H$8*ISNUMBER($AF53)+01_指標庫!$H$9*ISNUMBER($AG53)+01_指標庫!$H$10*ISNUMBER($AB53)+01_指標庫!$H$11*ISNUMBER($AC53)+01_指標庫!$H$12*ISNUMBER($AD53)+01_指標庫!$H$13*ISNUMBER($AE53)+01_指標庫!$H$14*ISNUMBER($I53)+01_指標庫!$H$15*ISNUMBER($AH53)+01_指標庫!$H$16*ISNUMBER($K53)+01_指標庫!$H$17*ISNUMBER($AI53)+01_指標庫!$H$18*ISNUMBER($AJ53)+01_指標庫!$H$19*ISNUMBER($AK53)+01_指標庫!$H$20*ISNUMBER($BB53)+01_指標庫!$H$21*ISNUMBER($BC53) -> 49 | AX53: =IF(AW53=0,50,ROUND((01_指標庫!$H$4*IF(ISNUMBER($F53),L53,0)+01_指標庫!$H$5*IF(ISNUMBER($AA53),AL53,0)+01_指標庫!$H$6*IF(ISNUMBER($G53),M53,0)+01_指標庫!$H$7*IF(ISNUMBER($H53),N53,0)+01_指標庫!$H$8*IF(ISNUMBER($AF53),AQ53,0)+01_指標庫!$H$9*IF(ISNUMBER($AG53),AR53,0)+01_指標庫!$H$10*IF(ISNUMBER($AB53),AM53,0)+01_指標庫!$H$11*IF(ISNUMBER($AC53),AN53,0)+01_指標庫!$H$12*IF(ISNUMBER($AD53),AO53,0)+01_指標庫!$H$13*IF(ISNUMBER($AE53),AP53,0)+01_指標庫!$H$14*IF(ISNUMBER($I53),O53,0)+01_指標庫!$H$15*IF(ISNUMBER($AH53),AS53,0)+01_指標庫!$H$16*IF(ISNUMBER($K53),P53,0)+01_指標庫!$H$17*IF(ISNUMBER($AI53),AT53,0)+01_指標庫!$H$18*IF(ISNUMBER($AJ53),AU53,0)+01_指標庫!$H$19*IF(ISNUMBER($AK53),AV53,0)+01_指標庫!$H$20*IF(ISNUMBER($BB53),BB53,0)+01_指標庫!$H$21*IF(ISNUMBER($BC53),BC53,0))/AW53,1)) -> 66.3 | BA53: =AVERAGE($E49:$E53)/AVERAGE($E44:$E53)-1 -> -0.0065514864 | BB53: =IF(ISNUMBER($BA53),IF(OR($S53<=-0.03,$BA53<-0.003),0,IF(OR($S53<=-0.02,$BA53<0.01),50,100)),"") -> 0 | BC53: =IF(OR(COUNT($AZ53)=0,COUNT($AZ52)=0),"",IF(OR($AY53/$AZ52-1<=-0.03,$AZ53/$AZ52-1<=-0.045,IF(COUNT($AZ44:$AZ53)=10,AVERAGE($AZ49:$AZ53)/AVERAGE($AZ44:$AZ53)-1<-0.01,FALSE())),0,IF(OR($AZ53/$AZ52-1<=-0.02,IF(COUNT($AZ44:$AZ53)=10,AVERAGE($AZ49:$AZ53)/AVERAGE($AZ44:$AZ53)-1<0.005,FALSE())),50,100)))
A54: 50 | B54: 42629 | C54: 2016 | D54: 五 | E54: 4818.05 | F54: 0.076507 | G54: -0.002858 | H54: 0.8776 | I54: 527 | J54: real | K54: 15.37 | L54: =IF(COUNT(F54)=0,50,IF(F54>=0,100,IF(F54>=-0.02,50,0))) -> 100 | M54: =IF(COUNT(G54)=0,50,IF(G54>-0.06,100,IF(G54>-0.15,50,0))) -> 100 | N54: =IF(COUNT(H54)=0,50,IF(H54>=0.6,100,IF(H54>=0.4,50,0))) -> 100 | O54: =IF(COUNT(I54)=0,50,IF(J54="proxy_vix",50,IF(I54<350,100,IF(I54<=450,50,0)))) -> 0 | P54: =IF(COUNT(K54)=0,50,IF(K54<20,100,IF(K54<=25,50,0))) -> 100 | S54: =$E54/$E53-1 -> -0.00038382539 | T54: =$K54/$K53-1 -> -0.057055215 | Y54: =IF(AX54>=70,"EASY",IF(AX54>40,"UNCERTAIN","HARD")) -> EASY | AA54: =IF($A54<200,"",AVERAGE($E5:$E54)/AVERAGE($E5:$E54)-1) | AB54: =LOOKUP($B54,07_L1政策步階!$A$4:$A$14,07_L1政策步階!$C$4:$C$14) -> 0 | AL54: =IF(ISNUMBER($AA54),IF($AA54>=0.005,100,IF($AA54>=-0.015,50,0)),"") | AM54: =IF(ISNUMBER($AB54),IF($AB54=1,100,IF($AB54=0,50,0)),"") -> 50 | AN54: =IF(ISNUMBER($AC54),IF($AC54>=0.001,100,IF($AC54>=-0.003,50,0)),"") | AO54: =IF(ISNUMBER($AD54),IF($AD54>=0.04,100,IF($AD54>=0,50,0)),"") | AP54: =IF(ISNUMBER($AE54),IF($AE54>=25,100,IF($AE54>=-75,50,0)),"") | AQ54: =IF(ISNUMBER($AF54),IF($AF54>0,100,IF($AF54>=-50,50,0)),"") | AR54: =IF(ISNUMBER($AG54),IF($AG54=1,100,IF($AG54=0,50,0)),"") | AS54: =IF(ISNUMBER($AH54),IF($AH54<0,100,IF($AH54<=20,50,0)),"") | AT54: =IF(ISNUMBER($AI54),IF($AI54<0.95,100,IF($AI54<=1,50,0)),"") | AU54: =IF(ISNUMBER($AJ54),IF($AJ54<30,0,IF($AJ54<40,50,IF($AJ54<=90,100,50))),"") | AV54: =IF(ISNUMBER($AK54),IF($AK54>-0.2,100,IF($AK54>=-0.4,50,0)),"") | AW54: =01_指標庫!$H$4*ISNUMBER($F54)+01_指標庫!$H$5*ISNUMBER($AA54)+01_指標庫!$H$6*ISNUMBER($G54)+01_指標庫!$H$7*ISNUMBER($H54)+01_指標庫!$H$8*ISNUMBER($AF54)+01_指標庫!$H$9*ISNUMBER($AG54)+01_指標庫!$H$10*ISNUMBER($AB54)+01_指標庫!$H$11*ISNUMBER($AC54)+01_指標庫!$H$12*ISNUMBER($AD54)+01_指標庫!$H$13*ISNUMBER($AE54)+01_指標庫!$H$14*ISNUMBER($I54)+01_指標庫!$H$15*ISNUMBER($AH54)+01_指標庫!$H$16*ISNUMBER($K54)+01_指標庫!$H$17*ISNUMBER($AI54)+01_指標庫!$H$18*ISNUMBER($AJ54)+01_指標庫!$H$19*ISNUMBER($AK54)+01_指標庫!$H$20*ISNUMBER($BB54)+01_指標庫!$H$21*ISNUMBER($BC54) -> 49 | AX54: =IF(AW54=0,50,ROUND((01_指標庫!$H$4*IF(ISNUMBER($F54),L54,0)+01_指標庫!$H$5*IF(ISNUMBER($AA54),AL54,0)+01_指標庫!$H$6*IF(ISNUMBER($G54),M54,0)+01_指標庫!$H$7*IF(ISNUMBER($H54),N54,0)+01_指標庫!$H$8*IF(ISNUMBER($AF54),AQ54,0)+01_指標庫!$H$9*IF(ISNUMBER($AG54),AR54,0)+01_指標庫!$H$10*IF(ISNUMBER($AB54),AM54,0)+01_指標庫!$H$11*IF(ISNUMBER($AC54),AN54,0)+01_指標庫!$H$12*IF(ISNUMBER($AD54),AO54,0)+01_指標庫!$H$13*IF(ISNUMBER($AE54),AP54,0)+01_指標庫!$H$14*IF(ISNUMBER($I54),O54,0)+01_指標庫!$H$15*IF(ISNUMBER($AH54),AS54,0)+01_指標庫!$H$16*IF(ISNUMBER($K54),P54,0)+01_指標庫!$H$17*IF(ISNUMBER($AI54),AT54,0)+01_指標庫!$H$18*IF(ISNUMBER($AJ54),AU54,0)+01_指標庫!$H$19*IF(ISNUMBER($AK54),AV54,0)+01_指標庫!$H$20*IF(ISNUMBER($BB54),BB54,0)+01_指標庫!$H$21*IF(ISNUMBER($BC54),BC54,0))/AW54,1)) -> 72.4 | BA54: =AVERAGE($E50:$E54)/AVERAGE($E45:$E54)-1 -> -0.0015504894 | BB54: =IF(ISNUMBER($BA54),IF(OR($S54<=-0.03,$BA54<-0.003),0,IF(OR($S54<=-0.02,$BA54<0.01),50,100)),"") -> 50 | BC54: =IF(OR(COUNT($AZ54)=0,COUNT($AZ53)=0),"",IF(OR($AY54/$AZ53-1<=-0.03,$AZ54/$AZ53-1<=-0.045,IF(COUNT($AZ45:$AZ54)=10,AVERAGE($AZ50:$AZ54)/AVERAGE($AZ45:$AZ54)-1<-0.01,FALSE())),0,IF(OR($AZ54/$AZ53-1<=-0.02,IF(COUNT($AZ45:$AZ54)=10,AVERAGE($AZ50:$AZ54)/AVERAGE($AZ45:$AZ54)-1<0.005,FALSE())),50,100)))
A55: 51 | B55: 42632 | C55: 2016 | D55: 一 | E55: 4796.07 | F55: 0.071464 | G55: -0.007407 | H55: 0.8571 | I55: 525 | J55: real | K55: 15.53 | L55: =IF(COUNT(F55)=0,50,IF(F55>=0,100,IF(F55>=-0.02,50,0))) -> 100 | M55: =IF(COUNT(G55)=0,50,IF(G55>-0.06,100,IF(G55>-0.15,50,0))) -> 100 | N55: =IF(COUNT(H55)=0,50,IF(H55>=0.6,100,IF(H55>=0.4,50,0))) -> 100 | O55: =IF(COUNT(I55)=0,50,IF(J55="proxy_vix",50,IF(I55<350,100,IF(I55<=450,50,0)))) -> 0 | P55: =IF(COUNT(K55)=0,50,IF(K55<20,100,IF(K55<=25,50,0))) -> 100 | S55: =$E55/$E54-1 -> -0.0045620116 | T55: =$K55/$K54-1 -> 0.010409889 | Y55: =IF(AX55>=70,"EASY",IF(AX55>40,"UNCERTAIN","HARD")) -> EASY | AA55: =IF($A55<200,"",AVERAGE($E6:$E55)/AVERAGE($E5:$E55)-1) | AB55: =LOOKUP($B55,07_L1政策步階!$A$4:$A$14,07_L1政策步階!$C$4:$C$14) -> 0 | AL55: =IF(ISNUMBER($AA55),IF($AA55>=0.005,100,IF($AA55>=-0.015,50,0)),"") | AM55: =IF(ISNUMBER($AB55),IF($AB55=1,100,IF($AB55=0,50,0)),"") -> 50 | AN55: =IF(ISNUMBER($AC55),IF($AC55>=0.001,100,IF($AC55>=-0.003,50,0)),"") | AO55: =IF(ISNUMBER($AD55),IF($AD55>=0.04,100,IF($AD55>=0,50,0)),"") | AP55: =IF(ISNUMBER($AE55),IF($AE55>=25,100,IF($AE55>=-75,50,0)),"") | AQ55: =IF(ISNUMBER($AF55),IF($AF55>0,100,IF($AF55>=-50,50,0)),"") | AR55: =IF(ISNUMBER($AG55),IF($AG55=1,100,IF($AG55=0,50,0)),"") | AS55: =IF(ISNUMBER($AH55),IF($AH55<0,100,IF($AH55<=20,50,0)),"") | AT55: =IF(ISNUMBER($AI55),IF($AI55<0.95,100,IF($AI55<=1,50,0)),"") | AU55: =IF(ISNUMBER($AJ55),IF($AJ55<30,0,IF($AJ55<40,50,IF($AJ55<=90,100,50))),"") | AV55: =IF(ISNUMBER($AK55),IF($AK55>-0.2,100,IF($AK55>=-0.4,50,0)),"") | AW55: =01_指標庫!$H$4*ISNUMBER($F55)+01_指標庫!$H$5*ISNUMBER($AA55)+01_指標庫!$H$6*ISNUMBER($G55)+01_指標庫!$H$7*ISNUMBER($H55)+01_指標庫!$H$8*ISNUMBER($AF55)+01_指標庫!$H$9*ISNUMBER($AG55)+01_指標庫!$H$10*ISNUMBER($AB55)+01_指標庫!$H$11*ISNUMBER($AC55)+01_指標庫!$H$12*ISNUMBER($AD55)+01_指標庫!$H$13*ISNUMBER($AE55)+01_指標庫!$H$14*ISNUMBER($I55)+01_指標庫!$H$15*ISNUMBER($AH55)+01_指標庫!$H$16*ISNUMBER($K55)+01_指標庫!$H$17*ISNUMBER($AI55)+01_指標庫!$H$18*ISNUMBER($AJ55)+01_指標庫!$H$19*ISNUMBER($AK55)+01_指標庫!$H$20*ISNUMBER($BB55)+01_指標庫!$H$21*ISNUMBER($BC55) -> 49 | AX55: =IF(AW55=0,50,ROUND((01_指標庫!$H$4*IF(ISNUMBER($F55),L55,0)+01_指標庫!$H$5*IF(ISNUMBER($AA55),AL55,0)+01_指標庫!$H$6*IF(ISNUMBER($G55),M55,0)+01_指標庫!$H$7*IF(ISNUMBER($H55),N55,0)+01_指標庫!$H$8*IF(ISNUMBER($AF55),AQ55,0)+01_指標庫!$H$9*IF(ISNUMBER($AG55),AR55,0)+01_指標庫!$H$10*IF(ISNUMBER($AB55),AM55,0)+01_指標庫!$H$11*IF(ISNUMBER($AC55),AN55,0)+01_指標庫!$H$12*IF(ISNUMBER($AD55),AO55,0)+01_指標庫!$H$13*IF(ISNUMBER($AE55),AP55,0)+01_指標庫!$H$14*IF(ISNUMBER($I55),O55,0)+01_指標庫!$H$15*IF(ISNUMBER($AH55),AS55,0)+01_指標庫!$H$16*IF(ISNUMBER($K55),P55,0)+01_指標庫!$H$17*IF(ISNUMBER($AI55),AT55,0)+01_指標庫!$H$18*IF(ISNUMBER($AJ55),AU55,0)+01_指標庫!$H$19*IF(ISNUMBER($AK55),AV55,0)+01_指標庫!$H$20*IF(ISNUMBER($BB55),BB55,0)+01_指標庫!$H$21*IF(ISNUMBER($BC55),BC55,0))/AW55,1)) -> 72.4 | BA55: =AVERAGE($E51:$E55)/AVERAGE($E46:$E55)-1 -> -0.00018048922 | BB55: =IF(ISNUMBER($BA55),IF(OR($S55<=-0.03,$BA55<-0.003),0,IF(OR($S55<=-0.02,$BA55<0.01),50,100)),"") -> 50 | BC55: =IF(OR(COUNT($AZ55)=0,COUNT($AZ54)=0),"",IF(OR($AY55/$AZ54-1<=-0.03,$AZ55/$AZ54-1<=-0.045,IF(COUNT($AZ46:$AZ55)=10,AVERAGE($AZ51:$AZ55)/AVERAGE($AZ46:$AZ55)-1<-0.01,FALSE())),0,IF(OR($AZ55/$AZ54-1<=-0.02,IF(COUNT($AZ46:$AZ55)=10,AVERAGE($AZ51:$AZ55)/AVERAGE($AZ46:$AZ55)-1<0.005,FALSE())),50,100)))
A56: 52 | B56: 42633 | C56: 2016 | D56: 二 | E56: 4805.22 | F56: 0.073271 | G56: -0.005513 | H56: 0.8367 | I56: 524 | J56: real | K56: 15.92 | L56: =IF(COUNT(F56)=0,50,IF(F56>=0,100,IF(F56>=-0.02,50,0))) -> 100 | M56: =IF(COUNT(G56)=0,50,IF(G56>-0.06,100,IF(G56>-0.15,50,0))) -> 100 | N56: =IF(COUNT(H56)=0,50,IF(H56>=0.6,100,IF(H56>=0.4,50,0))) -> 100 | O56: =IF(COUNT(I56)=0,50,IF(J56="proxy_vix",50,IF(I56<350,100,IF(I56<=450,50,0)))) -> 0 | P56: =IF(COUNT(K56)=0,50,IF(K56<20,100,IF(K56<=25,50,0))) -> 100 | S56: =$E56/$E55-1 -> 0.001907812 | T56: =$K56/$K55-1 -> 0.025112685 | Y56: =IF(AX56>=70,"EASY",IF(AX56>40,"UNCERTAIN","HARD")) -> EASY | AA56: =IF($A56<200,"",AVERAGE($E7:$E56)/AVERAGE($E5:$E56)-1) | AB56: =LOOKUP($B56,07_L1政策步階!$A$4:$A$14,07_L1政策步階!$C$4:$C$14) -> 0 | AL56: =IF(ISNUMBER($AA56),IF($AA56>=0.005,100,IF($AA56>=-0.015,50,0)),"") | AM56: =IF(ISNUMBER($AB56),IF($AB56=1,100,IF($AB56=0,50,0)),"") -> 50 | AN56: =IF(ISNUMBER($AC56),IF($AC56>=0.001,100,IF($AC56>=-0.003,50,0)),"") | AO56: =IF(ISNUMBER($AD56),IF($AD56>=0.04,100,IF($AD56>=0,50,0)),"") | AP56: =IF(ISNUMBER($AE56),IF($AE56>=25,100,IF($AE56>=-75,50,0)),"") | AQ56: =IF(ISNUMBER($AF56),IF($AF56>0,100,IF($AF56>=-50,50,0)),"") | AR56: =IF(ISNUMBER($AG56),IF($AG56=1,100,IF($AG56=0,50,0)),"") | AS56: =IF(ISNUMBER($AH56),IF($AH56<0,100,IF($AH56<=20,50,0)),"") | AT56: =IF(ISNUMBER($AI56),IF($AI56<0.95,100,IF($AI56<=1,50,0)),"") | AU56: =IF(ISNUMBER($AJ56),IF($AJ56<30,0,IF($AJ56<40,50,IF($AJ56<=90,100,50))),"") | AV56: =IF(ISNUMBER($AK56),IF($AK56>-0.2,100,IF($AK56>=-0.4,50,0)),"") | AW56: =01_指標庫!$H$4*ISNUMBER($F56)+01_指標庫!$H$5*ISNUMBER($AA56)+01_指標庫!$H$6*ISNUMBER($G56)+01_指標庫!$H$7*ISNUMBER($H56)+01_指標庫!$H$8*ISNUMBER($AF56)+01_指標庫!$H$9*ISNUMBER($AG56)+01_指標庫!$H$10*ISNUMBER($AB56)+01_指標庫!$H$11*ISNUMBER($AC56)+01_指標庫!$H$12*ISNUMBER($AD56)+01_指標庫!$H$13*ISNUMBER($AE56)+01_指標庫!$H$14*ISNUMBER($I56)+01_指標庫!$H$15*ISNUMBER($AH56)+01_指標庫!$H$16*ISNUMBER($K56)+01_指標庫!$H$17*ISNUMBER($AI56)+01_指標庫!$H$18*ISNUMBER($AJ56)+01_指標庫!$H$19*ISNUMBER($AK56)+01_指標庫!$H$20*ISNUMBER($BB56)+01_指標庫!$H$21*ISNUMBER($BC56) -> 49 | AX56: =IF(AW56=0,50,ROUND((01_指標庫!$H$4*IF(ISNUMBER($F56),L56,0)+01_指標庫!$H$5*IF(ISNUMBER($AA56),AL56,0)+01_指標庫!$H$6*IF(ISNUMBER($G56),M56,0)+01_指標庫!$H$7*IF(ISNUMBER($H56),N56,0)+01_指標庫!$H$8*IF(ISNUMBER($AF56),AQ56,0)+01_指標庫!$H$9*IF(ISNUMBER($AG56),AR56,0)+01_指標庫!$H$10*IF(ISNUMBER($AB56),AM56,0)+01_指標庫!$H$11*IF(ISNUMBER($AC56),AN56,0)+01_指標庫!$H$12*IF(ISNUMBER($AD56),AO56,0)+01_指標庫!$H$13*IF(ISNUMBER($AE56),AP56,0)+01_指標庫!$H$14*IF(ISNUMBER($I56),O56,0)+01_指標庫!$H$15*IF(ISNUMBER($AH56),AS56,0)+01_指標庫!$H$16*IF(ISNUMBER($K56),P56,0)+01_指標庫!$H$17*IF(ISNUMBER($AI56),AT56,0)+01_指標庫!$H$18*IF(ISNUMBER($AJ56),AU56,0)+01_指標庫!$H$19*IF(ISNUMBER($AK56),AV56,0)+01_指標庫!$H$20*IF(ISNUMBER($BB56),BB56,0)+01_指標庫!$H$21*IF(ISNUMBER($BC56),BC56,0))/AW56,1)) -> 72.4 | BA56: =AVERAGE($E52:$E56)/AVERAGE($E47:$E56)-1 -> 0.0037748325 | BB56: =IF(ISNUMBER($BA56),IF(OR($S56<=-0.03,$BA56<-0.003),0,IF(OR($S56<=-0.02,$BA56<0.01),50,100)),"") -> 50 | BC56: =IF(OR(COUNT($AZ56)=0,COUNT($AZ55)=0),"",IF(OR($AY56/$AZ55-1<=-0.03,$AZ56/$AZ55-1<=-0.045,IF(COUNT($AZ47:$AZ56)=10,AVERAGE($AZ52:$AZ56)/AVERAGE($AZ47:$AZ56)-1<-0.01,FALSE())),0,IF(OR($AZ56/$AZ55-1<=-0.02,IF(COUNT($AZ47:$AZ56)=10,AVERAGE($AZ52:$AZ56)/AVERAGE($AZ47:$AZ56)-1<0.005,FALSE())),50,100)))
A57: 53 | B57: 42634 | C57: 2016 | D57: 三 | E57: 4853.75 | F57: 0.083943 | G57: 0 | H57: 0.8571 | I57: 522 | J57: real | K57: 13.3 | L57: =IF(COUNT(F57)=0,50,IF(F57>=0,100,IF(F57>=-0.02,50,0))) -> 100 | M57: =IF(COUNT(G57)=0,50,IF(G57>-0.06,100,IF(G57>-0.15,50,0))) -> 100 | N57: =IF(COUNT(H57)=0,50,IF(H57>=0.6,100,IF(H57>=0.4,50,0))) -> 100 | O57: =IF(COUNT(I57)=0,50,IF(J57="proxy_vix",50,IF(I57<350,100,IF(I57<=450,50,0)))) -> 0 | P57: =IF(COUNT(K57)=0,50,IF(K57<20,100,IF(K57<=25,50,0))) -> 100 | S57: =$E57/$E56-1 -> 0.010099434 | T57: =$K57/$K56-1 -> -0.16457286 | Y57: =IF(AX57>=70,"EASY",IF(AX57>40,"UNCERTAIN","HARD")) -> EASY | AA57: =IF($A57<200,"",AVERAGE($E8:$E57)/AVERAGE($E5:$E57)-1) | AB57: =LOOKUP($B57,07_L1政策步階!$A$4:$A$14,07_L1政策步階!$C$4:$C$14) -> 0 | AL57: =IF(ISNUMBER($AA57),IF($AA57>=0.005,100,IF($AA57>=-0.015,50,0)),"") | AM57: =IF(ISNUMBER($AB57),IF($AB57=1,100,IF($AB57=0,50,0)),"") -> 50 | AN57: =IF(ISNUMBER($AC57),IF($AC57>=0.001,100,IF($AC57>=-0.003,50,0)),"") | AO57: =IF(ISNUMBER($AD57),IF($AD57>=0.04,100,IF($AD57>=0,50,0)),"") | AP57: =IF(ISNUMBER($AE57),IF($AE57>=25,100,IF($AE57>=-75,50,0)),"") | AQ57: =IF(ISNUMBER($AF57),IF($AF57>0,100,IF($AF57>=-50,50,0)),"") | AR57: =IF(ISNUMBER($AG57),IF($AG57=1,100,IF($AG57=0,50,0)),"") | AS57: =IF(ISNUMBER($AH57),IF($AH57<0,100,IF($AH57<=20,50,0)),"") | AT57: =IF(ISNUMBER($AI57),IF($AI57<0.95,100,IF($AI57<=1,50,0)),"") | AU57: =IF(ISNUMBER($AJ57),IF($AJ57<30,0,IF($AJ57<40,50,IF($AJ57<=90,100,50))),"") | AV57: =IF(ISNUMBER($AK57),IF($AK57>-0.2,100,IF($AK57>=-0.4,50,0)),"") | AW57: =01_指標庫!$H$4*ISNUMBER($F57)+01_指標庫!$H$5*ISNUMBER($AA57)+01_指標庫!$H$6*ISNUMBER($G57)+01_指標庫!$H$7*ISNUMBER($H57)+01_指標庫!$H$8*ISNUMBER($AF57)+01_指標庫!$H$9*ISNUMBER($AG57)+01_指標庫!$H$10*ISNUMBER($AB57)+01_指標庫!$H$11*ISNUMBER($AC57)+01_指標庫!$H$12*ISNUMBER($AD57)+01_指標庫!$H$13*ISNUMBER($AE57)+01_指標庫!$H$14*ISNUMBER($I57)+01_指標庫!$H$15*ISNUMBER($AH57)+01_指標庫!$H$16*ISNUMBER($K57)+01_指標庫!$H$17*ISNUMBER($AI57)+01_指標庫!$H$18*ISNUMBER($AJ57)+01_指標庫!$H$19*ISNUMBER($AK57)+01_指標庫!$H$20*ISNUMBER($BB57)+01_指標庫!$H$21*ISNUMBER($BC57) -> 49 | AX57: =IF(AW57=0,50,ROUND((01_指標庫!$H$4*IF(ISNUMBER($F57),L57,0)+01_指標庫!$H$5*IF(ISNUMBER($AA57),AL57,0)+01_指標庫!$H$6*IF(ISNUMBER($G57),M57,0)+01_指標庫!$H$7*IF(ISNUMBER($H57),N57,0)+01_指標庫!$H$8*IF(ISNUMBER($AF57),AQ57,0)+01_指標庫!$H$9*IF(ISNUMBER($AG57),AR57,0)+01_指標庫!$H$10*IF(ISNUMBER($AB57),AM57,0)+01_指標庫!$H$11*IF(ISNUMBER($AC57),AN57,0)+01_指標庫!$H$12*IF(ISNUMBER($AD57),AO57,0)+01_指標庫!$H$13*IF(ISNUMBER($AE57),AP57,0)+01_指標庫!$H$14*IF(ISNUMBER($I57),O57,0)+01_指標庫!$H$15*IF(ISNUMBER($AH57),AS57,0)+01_指標庫!$H$16*IF(ISNUMBER($K57),P57,0)+01_指標庫!$H$17*IF(ISNUMBER($AI57),AT57,0)+01_指標庫!$H$18*IF(ISNUMBER($AJ57),AU57,0)+01_指標庫!$H$19*IF(ISNUMBER($AK57),AV57,0)+01_指標庫!$H$20*IF(ISNUMBER($BB57),BB57,0)+01_指標庫!$H$21*IF(ISNUMBER($BC57),BC57,0))/AW57,1)) -> 72.4 | BA57: =AVERAGE($E53:$E57)/AVERAGE($E48:$E57)-1 -> 0.0078199886 | BB57: =IF(ISNUMBER($BA57),IF(OR($S57<=-0.03,$BA57<-0.003),0,IF(OR($S57<=-0.02,$BA57<0.01),50,100)),"") -> 50 | BC57: =IF(OR(COUNT($AZ57)=0,COUNT($AZ56)=0),"",IF(OR($AY57/$AZ56-1<=-0.03,$AZ57/$AZ56-1<=-0.045,IF(COUNT($AZ48:$AZ57)=10,AVERAGE($AZ53:$AZ57)/AVERAGE($AZ48:$AZ57)-1<-0.01,FALSE())),0,IF(OR($AZ57/$AZ56-1<=-0.02,IF(COUNT($AZ48:$AZ57)=10,AVERAGE($AZ53:$AZ57)/AVERAGE($AZ48:$AZ57)-1<0.005,FALSE())),50,100)))
A58: 54 | B58: 42635 | C58: 2016 | D58: 四 | E58: 4891.36 | F58: 0.092101 | G58: 0 | H58: 0.8571 | I58: 509 | J58: real | K58: 12.02 | L58: =IF(COUNT(F58)=0,50,IF(F58>=0,100,IF(F58>=-0.02,50,0))) -> 100 | M58: =IF(COUNT(G58)=0,50,IF(G58>-0.06,100,IF(G58>-0.15,50,0))) -> 100 | N58: =IF(COUNT(H58)=0,50,IF(H58>=0.6,100,IF(H58>=0.4,50,0))) -> 100 | O58: =IF(COUNT(I58)=0,50,IF(J58="proxy_vix",50,IF(I58<350,100,IF(I58<=450,50,0)))) -> 0 | P58: =IF(COUNT(K58)=0,50,IF(K58<20,100,IF(K58<=25,50,0))) -> 100 | S58: =$E58/$E57-1 -> 0.007748648 | T58: =$K58/$K57-1 -> -0.096240602 | Y58: =IF(AX58>=70,"EASY",IF(AX58>40,"UNCERTAIN","HARD")) -> EASY | AA58: =IF($A58<200,"",AVERAGE($E9:$E58)/AVERAGE($E5:$E58)-1) | AB58: =LOOKUP($B58,07_L1政策步階!$A$4:$A$14,07_L1政策步階!$C$4:$C$14) -> 0 | AL58: =IF(ISNUMBER($AA58),IF($AA58>=0.005,100,IF($AA58>=-0.015,50,0)),"") | AM58: =IF(ISNUMBER($AB58),IF($AB58=1,100,IF($AB58=0,50,0)),"") -> 50 | AN58: =IF(ISNUMBER($AC58),IF($AC58>=0.001,100,IF($AC58>=-0.003,50,0)),"") | AO58: =IF(ISNUMBER($AD58),IF($AD58>=0.04,100,IF($AD58>=0,50,0)),"") | AP58: =IF(ISNUMBER($AE58),IF($AE58>=25,100,IF($AE58>=-75,50,0)),"") | AQ58: =IF(ISNUMBER($AF58),IF($AF58>0,100,IF($AF58>=-50,50,0)),"") | AR58: =IF(ISNUMBER($AG58),IF($AG58=1,100,IF($AG58=0,50,0)),"") | AS58: =IF(ISNUMBER($AH58),IF($AH58<0,100,IF($AH58<=20,50,0)),"") | AT58: =IF(ISNUMBER($AI58),IF($AI58<0.95,100,IF($AI58<=1,50,0)),"") | AU58: =IF(ISNUMBER($AJ58),IF($AJ58<30,0,IF($AJ58<40,50,IF($AJ58<=90,100,50))),"") | AV58: =IF(ISNUMBER($AK58),IF($AK58>-0.2,100,IF($AK58>=-0.4,50,0)),"") | AW58: =01_指標庫!$H$4*ISNUMBER($F58)+01_指標庫!$H$5*ISNUMBER($AA58)+01_指標庫!$H$6*ISNUMBER($G58)+01_指標庫!$H$7*ISNUMBER($H58)+01_指標庫!$H$8*ISNUMBER($AF58)+01_指標庫!$H$9*ISNUMBER($AG58)+01_指標庫!$H$10*ISNUMBER($AB58)+01_指標庫!$H$11*ISNUMBER($AC58)+01_指標庫!$H$12*ISNUMBER($AD58)+01_指標庫!$H$13*ISNUMBER($AE58)+01_指標庫!$H$14*ISNUMBER($I58)+01_指標庫!$H$15*ISNUMBER($AH58)+01_指標庫!$H$16*ISNUMBER($K58)+01_指標庫!$H$17*ISNUMBER($AI58)+01_指標庫!$H$18*ISNUMBER($AJ58)+01_指標庫!$H$19*ISNUMBER($AK58)+01_指標庫!$H$20*ISNUMBER($BB58)+01_指標庫!$H$21*ISNUMBER($BC58) -> 49 | AX58: =IF(AW58=0,50,ROUND((01_指標庫!$H$4*IF(ISNUMBER($F58),L58,0)+01_指標庫!$H$5*IF(ISNUMBER($AA58),AL58,0)+01_指標庫!$H$6*IF(ISNUMBER($G58),M58,0)+01_指標庫!$H$7*IF(ISNUMBER($H58),N58,0)+01_指標庫!$H$8*IF(ISNUMBER($AF58),AQ58,0)+01_指標庫!$H$9*IF(ISNUMBER($AG58),AR58,0)+01_指標庫!$H$10*IF(ISNUMBER($AB58),AM58,0)+01_指標庫!$H$11*IF(ISNUMBER($AC58),AN58,0)+01_指標庫!$H$12*IF(ISNUMBER($AD58),AO58,0)+01_指標庫!$H$13*IF(ISNUMBER($AE58),AP58,0)+01_指標庫!$H$14*IF(ISNUMBER($I58),O58,0)+01_指標庫!$H$15*IF(ISNUMBER($AH58),AS58,0)+01_指標庫!$H$16*IF(ISNUMBER($K58),P58,0)+01_指標庫!$H$17*IF(ISNUMBER($AI58),AT58,0)+01_指標庫!$H$18*IF(ISNUMBER($AJ58),AU58,0)+01_指標庫!$H$19*IF(ISNUMBER($AK58),AV58,0)+01_指標庫!$H$20*IF(ISNUMBER($BB58),BB58,0)+01_指標庫!$H$21*IF(ISNUMBER($BC58),BC58,0))/AW58,1)) -> 72.4 | BA58: =AVERAGE($E54:$E58)/AVERAGE($E49:$E58)-1 -> 0.0089656562 | BB58: =IF(ISNUMBER($BA58),IF(OR($S58<=-0.03,$BA58<-0.003),0,IF(OR($S58<=-0.02,$BA58<0.01),50,100)),"") -> 50 | BC58: =IF(OR(COUNT($AZ58)=0,COUNT($AZ57)=0),"",IF(OR($AY58/$AZ57-1<=-0.03,$AZ58/$AZ57-1<=-0.045,IF(COUNT($AZ49:$AZ58)=10,AVERAGE($AZ54:$AZ58)/AVERAGE($AZ49:$AZ58)-1<-0.01,FALSE())),0,IF(OR($AZ58/$AZ57-1<=-0.02,IF(COUNT($AZ49:$AZ58)=10,AVERAGE($AZ54:$AZ58)/AVERAGE($AZ49:$AZ58)-1<0.005,FALSE())),50,100)))
A59: 55 | B59: 42636 | C59: 2016 | D59: 五 | E59: 4858.91 | F59: 0.084658 | G59: -0.006634 | H59: 0.8367 | I59: 510 | J59: real | K59: 12.29 | L59: =IF(COUNT(F59)=0,50,IF(F59>=0,100,IF(F59>=-0.02,50,0))) -> 100 | M59: =IF(COUNT(G59)=0,50,IF(G59>-0.06,100,IF(G59>-0.15,50,0))) -> 100 | N59: =IF(COUNT(H59)=0,50,IF(H59>=0.6,100,IF(H59>=0.4,50,0))) -> 100 | O59: =IF(COUNT(I59)=0,50,IF(J59="proxy_vix",50,IF(I59<350,100,IF(I59<=450,50,0)))) -> 0 | P59: =IF(COUNT(K59)=0,50,IF(K59<20,100,IF(K59<=25,50,0))) -> 100 | S59: =$E59/$E58-1 -> -0.0066341467 | T59: =$K59/$K58-1 -> 0.022462562 | Y59: =IF(AX59>=70,"EASY",IF(AX59>40,"UNCERTAIN","HARD")) -> EASY | AA59: =IF($A59<200,"",AVERAGE($E10:$E59)/AVERAGE($E5:$E59)-1) | AB59: =LOOKUP($B59,07_L1政策步階!$A$4:$A$14,07_L1政策步階!$C$4:$C$14) -> 0 | AL59: =IF(ISNUMBER($AA59),IF($AA59>=0.005,100,IF($AA59>=-0.015,50,0)),"") | AM59: =IF(ISNUMBER($AB59),IF($AB59=1,100,IF($AB59=0,50,0)),"") -> 50 | AN59: =IF(ISNUMBER($AC59),IF($AC59>=0.001,100,IF($AC59>=-0.003,50,0)),"") | AO59: =IF(ISNUMBER($AD59),IF($AD59>=0.04,100,IF($AD59>=0,50,0)),"") | AP59: =IF(ISNUMBER($AE59),IF($AE59>=25,100,IF($AE59>=-75,50,0)),"") | AQ59: =IF(ISNUMBER($AF59),IF($AF59>0,100,IF($AF59>=-50,50,0)),"") | AR59: =IF(ISNUMBER($AG59),IF($AG59=1,100,IF($AG59=0,50,0)),"") | AS59: =IF(ISNUMBER($AH59),IF($AH59<0,100,IF($AH59<=20,50,0)),"") | AT59: =IF(ISNUMBER($AI59),IF($AI59<0.95,100,IF($AI59<=1,50,0)),"") | AU59: =IF(ISNUMBER($AJ59),IF($AJ59<30,0,IF($AJ59<40,50,IF($AJ59<=90,100,50))),"") | AV59: =IF(ISNUMBER($AK59),IF($AK59>-0.2,100,IF($AK59>=-0.4,50,0)),"") | AW59: =01_指標庫!$H$4*ISNUMBER($F59)+01_指標庫!$H$5*ISNUMBER($AA59)+01_指標庫!$H$6*ISNUMBER($G59)+01_指標庫!$H$7*ISNUMBER($H59)+01_指標庫!$H$8*ISNUMBER($AF59)+01_指標庫!$H$9*ISNUMBER($AG59)+01_指標庫!$H$10*ISNUMBER($AB59)+01_指標庫!$H$11*ISNUMBER($AC59)+01_指標庫!$H$12*ISNUMBER($AD59)+01_指標庫!$H$13*ISNUMBER($AE59)+01_指標庫!$H$14*ISNUMBER($I59)+01_指標庫!$H$15*ISNUMBER($AH59)+01_指標庫!$H$16*ISNUMBER($K59)+01_指標庫!$H$17*ISNUMBER($AI59)+01_指標庫!$H$18*ISNUMBER($AJ59)+01_指標庫!$H$19*ISNUMBER($AK59)+01_指標庫!$H$20*ISNUMBER($BB59)+01_指標庫!$H$21*ISNUMBER($BC59) -> 49 | AX59: =IF(AW59=0,50,ROUND((01_指標庫!$H$4*IF(ISNUMBER($F59),L59,0)+01_指標庫!$H$5*IF(ISNUMBER($AA59),AL59,0)+01_指標庫!$H$6*IF(ISNUMBER($G59),M59,0)+01_指標庫!$H$7*IF(ISNUMBER($H59),N59,0)+01_指標庫!$H$8*IF(ISNUMBER($AF59),AQ59,0)+01_指標庫!$H$9*IF(ISNUMBER($AG59),AR59,0)+01_指標庫!$H$10*IF(ISNUMBER($AB59),AM59,0)+01_指標庫!$H$11*IF(ISNUMBER($AC59),AN59,0)+01_指標庫!$H$12*IF(ISNUMBER($AD59),AO59,0)+01_指標庫!$H$13*IF(ISNUMBER($AE59),AP59,0)+01_指標庫!$H$14*IF(ISNUMBER($I59),O59,0)+01_指標庫!$H$15*IF(ISNUMBER($AH59),AS59,0)+01_指標庫!$H$16*IF(ISNUMBER($K59),P59,0)+01_指標庫!$H$17*IF(ISNUMBER($AI59),AT59,0)+01_指標庫!$H$18*IF(ISNUMBER($AJ59),AU59,0)+01_指標庫!$H$19*IF(ISNUMBER($AK59),AV59,0)+01_指標庫!$H$20*IF(ISNUMBER($BB59),BB59,0)+01_指標庫!$H$21*IF(ISNUMBER($BC59),BC59,0))/AW59,1)) -> 72.4 | BA59: =AVERAGE($E55:$E59)/AVERAGE($E50:$E59)-1 -> 0.0069430549 | BB59: =IF(ISNUMBER($BA59),IF(OR($S59<=-0.03,$BA59<-0.003),0,IF(OR($S59<=-0.02,$BA59<0.01),50,100)),"") -> 50 | BC59: =IF(OR(COUNT($AZ59)=0,COUNT($AZ58)=0),"",IF(OR($AY59/$AZ58-1<=-0.03,$AZ59/$AZ58-1<=-0.045,IF(COUNT($AZ50:$AZ59)=10,AVERAGE($AZ55:$AZ59)/AVERAGE($AZ50:$AZ59)-1<-0.01,FALSE())),0,IF(OR($AZ59/$AZ58-1<=-0.02,IF(COUNT($AZ50:$AZ59)=10,AVERAGE($AZ55:$AZ59)/AVERAGE($AZ50:$AZ59)-1<0.005,FALSE())),50,100)))
A60: 56 | B60: 42639 | C60: 2016 | D60: 一 | E60: 4817.17 | F60: 0.075106 | G60: -0.015168 | H60: 0.8163 | I60: 516 | J60: real | K60: 14.5 | L60: =IF(COUNT(F60)=0,50,IF(F60>=0,100,IF(F60>=-0.02,50,0))) -> 100 | M60: =IF(COUNT(G60)=0,50,IF(G60>-0.06,100,IF(G60>-0.15,50,0))) -> 100 | N60: =IF(COUNT(H60)=0,50,IF(H60>=0.6,100,IF(H60>=0.4,50,0))) -> 100 | O60: =IF(COUNT(I60)=0,50,IF(J60="proxy_vix",50,IF(I60<350,100,IF(I60<=450,50,0)))) -> 0 | P60: =IF(COUNT(K60)=0,50,IF(K60<20,100,IF(K60<=25,50,0))) -> 100 | S60: =$E60/$E59-1 -> -0.008590404 | T60: =$K60/$K59-1 -> 0.17982099 | Y60: =IF(AX60>=70,"EASY",IF(AX60>40,"UNCERTAIN","HARD")) -> EASY | AA60: =IF($A60<200,"",AVERAGE($E11:$E60)/AVERAGE($E5:$E60)-1) | AB60: =LOOKUP($B60,07_L1政策步階!$A$4:$A$14,07_L1政策步階!$C$4:$C$14) -> 0 | AL60: =IF(ISNUMBER($AA60),IF($AA60>=0.005,100,IF($AA60>=-0.015,50,0)),"") | AM60: =IF(ISNUMBER($AB60),IF($AB60=1,100,IF($AB60=0,50,0)),"") -> 50 | AN60: =IF(ISNUMBER($AC60),IF($AC60>=0.001,100,IF($AC60>=-0.003,50,0)),"") | AO60: =IF(ISNUMBER($AD60),IF($AD60>=0.04,100,IF($AD60>=0,50,0)),"") | AP60: =IF(ISNUMBER($AE60),IF($AE60>=25,100,IF($AE60>=-75,50,0)),"") | AQ60: =IF(ISNUMBER($AF60),IF($AF60>0,100,IF($AF60>=-50,50,0)),"") | AR60: =IF(ISNUMBER($AG60),IF($AG60=1,100,IF($AG60=0,50,0)),"") | AS60: =IF(ISNUMBER($AH60),IF($AH60<0,100,IF($AH60<=20,50,0)),"") | AT60: =IF(ISNUMBER($AI60),IF($AI60<0.95,100,IF($AI60<=1,50,0)),"") | AU60: =IF(ISNUMBER($AJ60),IF($AJ60<30,0,IF($AJ60<40,50,IF($AJ60<=90,100,50))),"") | AV60: =IF(ISNUMBER($AK60),IF($AK60>-0.2,100,IF($AK60>=-0.4,50,0)),"") | AW60: =01_指標庫!$H$4*ISNUMBER($F60)+01_指標庫!$H$5*ISNUMBER($AA60)+01_指標庫!$H$6*ISNUMBER($G60)+01_指標庫!$H$7*ISNUMBER($H60)+01_指標庫!$H$8*ISNUMBER($AF60)+01_指標庫!$H$9*ISNUMBER($AG60)+01_指標庫!$H$10*ISNUMBER($AB60)+01_指標庫!$H$11*ISNUMBER($AC60)+01_指標庫!$H$12*ISNUMBER($AD60)+01_指標庫!$H$13*ISNUMBER($AE60)+01_指標庫!$H$14*ISNUMBER($I60)+01_指標庫!$H$15*ISNUMBER($AH60)+01_指標庫!$H$16*ISNUMBER($K60)+01_指標庫!$H$17*ISNUMBER($AI60)+01_指標庫!$H$18*ISNUMBER($AJ60)+01_指標庫!$H$19*ISNUMBER($AK60)+01_指標庫!$H$20*ISNUMBER($BB60)+01_指標庫!$H$21*ISNUMBER($BC60) -> 49 | AX60: =IF(AW60=0,50,ROUND((01_指標庫!$H$4*IF(ISNUMBER($F60),L60,0)+01_指標庫!$H$5*IF(ISNUMBER($AA60),AL60,0)+01_指標庫!$H$6*IF(ISNUMBER($G60),M60,0)+01_指標庫!$H$7*IF(ISNUMBER($H60),N60,0)+01_指標庫!$H$8*IF(ISNUMBER($AF60),AQ60,0)+01_指標庫!$H$9*IF(ISNUMBER($AG60),AR60,0)+01_指標庫!$H$10*IF(ISNUMBER($AB60),AM60,0)+01_指標庫!$H$11*IF(ISNUMBER($AC60),AN60,0)+01_指標庫!$H$12*IF(ISNUMBER($AD60),AO60,0)+01_指標庫!$H$13*IF(ISNUMBER($AE60),AP60,0)+01_指標庫!$H$14*IF(ISNUMBER($I60),O60,0)+01_指標庫!$H$15*IF(ISNUMBER($AH60),AS60,0)+01_指標庫!$H$16*IF(ISNUMBER($K60),P60,0)+01_指標庫!$H$17*IF(ISNUMBER($AI60),AT60,0)+01_指標庫!$H$18*IF(ISNUMBER($AJ60),AU60,0)+01_指標庫!$H$19*IF(ISNUMBER($AK60),AV60,0)+01_指標庫!$H$20*IF(ISNUMBER($BB60),BB60,0)+01_指標庫!$H$21*IF(ISNUMBER($BC60),BC60,0))/AW60,1)) -> 72.4 | BA60: =AVERAGE($E56:$E60)/AVERAGE($E51:$E60)-1 -> 0.0067210562 | BB60: =IF(ISNUMBER($BA60),IF(OR($S60<=-0.03,$BA60<-0.003),0,IF(OR($S60<=-0.02,$BA60<0.01),50,100)),"") -> 50 | BC60: =IF(OR(COUNT($AZ60)=0,COUNT($AZ59)=0),"",IF(OR($AY60/$AZ59-1<=-0.03,$AZ60/$AZ59-1<=-0.045,IF(COUNT($AZ51:$AZ60)=10,AVERAGE($AZ56:$AZ60)/AVERAGE($AZ51:$AZ60)-1<-0.01,FALSE())),0,IF(OR($AZ60/$AZ59-1<=-0.02,IF(COUNT($AZ51:$AZ60)=10,AVERAGE($AZ56:$AZ60)/AVERAGE($AZ51:$AZ60)-1<0.005,FALSE())),50,100)))
A61: 57 | B61: 42640 | C61: 2016 | D61: 二 | E61: 4866.71 | F61: 0.085891 | G61: -0.005039 | H61: 0.8571 | I61: 518 | J61: real | K61: 13.1 | L61: =IF(COUNT(F61)=0,50,IF(F61>=0,100,IF(F61>=-0.02,50,0))) -> 100 | M61: =IF(COUNT(G61)=0,50,IF(G61>-0.06,100,IF(G61>-0.15,50,0))) -> 100 | N61: =IF(COUNT(H61)=0,50,IF(H61>=0.6,100,IF(H61>=0.4,50,0))) -> 100 | O61: =IF(COUNT(I61)=0,50,IF(J61="proxy_vix",50,IF(I61<350,100,IF(I61<=450,50,0)))) -> 0 | P61: =IF(COUNT(K61)=0,50,IF(K61<20,100,IF(K61<=25,50,0))) -> 100 | S61: =$E61/$E60-1 -> 0.010284046 | T61: =$K61/$K60-1 -> -0.096551724 | Y61: =IF(AX61>=70,"EASY",IF(AX61>40,"UNCERTAIN","HARD")) -> EASY | AA61: =IF($A61<200,"",AVERAGE($E12:$E61)/AVERAGE($E5:$E61)-1) | AB61: =LOOKUP($B61,07_L1政策步階!$A$4:$A$14,07_L1政策步階!$C$4:$C$14) -> 0 | AL61: =IF(ISNUMBER($AA61),IF($AA61>=0.005,100,IF($AA61>=-0.015,50,0)),"") | AM61: =IF(ISNUMBER($AB61),IF($AB61=1,100,IF($AB61=0,50,0)),"") -> 50 | AN61: =IF(ISNUMBER($AC61),IF($AC61>=0.001,100,IF($AC61>=-0.003,50,0)),"") | AO61: =IF(ISNUMBER($AD61),IF($AD61>=0.04,100,IF($AD61>=0,50,0)),"") | AP61: =IF(ISNUMBER($AE61),IF($AE61>=25,100,IF($AE61>=-75,50,0)),"") | AQ61: =IF(ISNUMBER($AF61),IF($AF61>0,100,IF($AF61>=-50,50,0)),"") | AR61: =IF(ISNUMBER($AG61),IF($AG61=1,100,IF($AG61=0,50,0)),"") | AS61: =IF(ISNUMBER($AH61),IF($AH61<0,100,IF($AH61<=20,50,0)),"") | AT61: =IF(ISNUMBER($AI61),IF($AI61<0.95,100,IF($AI61<=1,50,0)),"") | AU61: =IF(ISNUMBER($AJ61),IF($AJ61<30,0,IF($AJ61<40,50,IF($AJ61<=90,100,50))),"") | AV61: =IF(ISNUMBER($AK61),IF($AK61>-0.2,100,IF($AK61>=-0.4,50,0)),"") | AW61: =01_指標庫!$H$4*ISNUMBER($F61)+01_指標庫!$H$5*ISNUMBER($AA61)+01_指標庫!$H$6*ISNUMBER($G61)+01_指標庫!$H$7*ISNUMBER($H61)+01_指標庫!$H$8*ISNUMBER($AF61)+01_指標庫!$H$9*ISNUMBER($AG61)+01_指標庫!$H$10*ISNUMBER($AB61)+01_指標庫!$H$11*ISNUMBER($AC61)+01_指標庫!$H$12*ISNUMBER($AD61)+01_指標庫!$H$13*ISNUMBER($AE61)+01_指標庫!$H$14*ISNUMBER($I61)+01_指標庫!$H$15*ISNUMBER($AH61)+01_指標庫!$H$16*ISNUMBER($K61)+01_指標庫!$H$17*ISNUMBER($AI61)+01_指標庫!$H$18*ISNUMBER($AJ61)+01_指標庫!$H$19*ISNUMBER($AK61)+01_指標庫!$H$20*ISNUMBER($BB61)+01_指標庫!$H$21*ISNUMBER($BC61) -> 49 | AX61: =IF(AW61=0,50,ROUND((01_指標庫!$H$4*IF(ISNUMBER($F61),L61,0)+01_指標庫!$H$5*IF(ISNUMBER($AA61),AL61,0)+01_指標庫!$H$6*IF(ISNUMBER($G61),M61,0)+01_指標庫!$H$7*IF(ISNUMBER($H61),N61,0)+01_指標庫!$H$8*IF(ISNUMBER($AF61),AQ61,0)+01_指標庫!$H$9*IF(ISNUMBER($AG61),AR61,0)+01_指標庫!$H$10*IF(ISNUMBER($AB61),AM61,0)+01_指標庫!$H$11*IF(ISNUMBER($AC61),AN61,0)+01_指標庫!$H$12*IF(ISNUMBER($AD61),AO61,0)+01_指標庫!$H$13*IF(ISNUMBER($AE61),AP61,0)+01_指標庫!$H$14*IF(ISNUMBER($I61),O61,0)+01_指標庫!$H$15*IF(ISNUMBER($AH61),AS61,0)+01_指標庫!$H$16*IF(ISNUMBER($K61),P61,0)+01_指標庫!$H$17*IF(ISNUMBER($AI61),AT61,0)+01_指標庫!$H$18*IF(ISNUMBER($AJ61),AU61,0)+01_指標庫!$H$19*IF(ISNUMBER($AK61),AV61,0)+01_指標庫!$H$20*IF(ISNUMBER($BB61),BB61,0)+01_指標庫!$H$21*IF(ISNUMBER($BC61),BC61,0))/AW61,1)) -> 72.4 | BA61: =AVERAGE($E57:$E61)/AVERAGE($E52:$E61)-1 -> 0.0062684885 | BB61: =IF(ISNUMBER($BA61),IF(OR($S61<=-0.03,$BA61<-0.003),0,IF(OR($S61<=-0.02,$BA61<0.01),50,100)),"") -> 50 | BC61: =IF(OR(COUNT($AZ61)=0,COUNT($AZ60)=0),"",IF(OR($AY61/$AZ60-1<=-0.03,$AZ61/$AZ60-1<=-0.045,IF(COUNT($AZ52:$AZ61)=10,AVERAGE($AZ57:$AZ61)/AVERAGE($AZ52:$AZ61)-1<-0.01,FALSE())),0,IF(OR($AZ61/$AZ60-1<=-0.02,IF(COUNT($AZ52:$AZ61)=10,AVERAGE($AZ57:$AZ61)/AVERAGE($AZ52:$AZ61)-1<0.005,FALSE())),50,100)))
A62: 58 | B62: 42641 | C62: 2016 | D62: 三 | E62: 4875.27 | F62: 0.087392 | G62: -0.003289 | H62: 0.8776 | I62: 514 | J62: real | K62: 12.39 | L62: =IF(COUNT(F62)=0,50,IF(F62>=0,100,IF(F62>=-0.02,50,0))) -> 100 | M62: =IF(COUNT(G62)=0,50,IF(G62>-0.06,100,IF(G62>-0.15,50,0))) -> 100 | N62: =IF(COUNT(H62)=0,50,IF(H62>=0.6,100,IF(H62>=0.4,50,0))) -> 100 | O62: =IF(COUNT(I62)=0,50,IF(J62="proxy_vix",50,IF(I62<350,100,IF(I62<=450,50,0)))) -> 0 | P62: =IF(COUNT(K62)=0,50,IF(K62<20,100,IF(K62<=25,50,0))) -> 100 | S62: =$E62/$E61-1 -> 0.0017588884 | T62: =$K62/$K61-1 -> -0.054198473 | Y62: =IF(AX62>=70,"EASY",IF(AX62>40,"UNCERTAIN","HARD")) -> EASY | AA62: =IF($A62<200,"",AVERAGE($E13:$E62)/AVERAGE($E5:$E62)-1) | AB62: =LOOKUP($B62,07_L1政策步階!$A$4:$A$14,07_L1政策步階!$C$4:$C$14) -> 0 | AL62: =IF(ISNUMBER($AA62),IF($AA62>=0.005,100,IF($AA62>=-0.015,50,0)),"") | AM62: =IF(ISNUMBER($AB62),IF($AB62=1,100,IF($AB62=0,50,0)),"") -> 50 | AN62: =IF(ISNUMBER($AC62),IF($AC62>=0.001,100,IF($AC62>=-0.003,50,0)),"") | AO62: =IF(ISNUMBER($AD62),IF($AD62>=0.04,100,IF($AD62>=0,50,0)),"") | AP62: =IF(ISNUMBER($AE62),IF($AE62>=25,100,IF($AE62>=-75,50,0)),"") | AQ62: =IF(ISNUMBER($AF62),IF($AF62>0,100,IF($AF62>=-50,50,0)),"") | AR62: =IF(ISNUMBER($AG62),IF($AG62=1,100,IF($AG62=0,50,0)),"") | AS62: =IF(ISNUMBER($AH62),IF($AH62<0,100,IF($AH62<=20,50,0)),"") | AT62: =IF(ISNUMBER($AI62),IF($AI62<0.95,100,IF($AI62<=1,50,0)),"") | AU62: =IF(ISNUMBER($AJ62),IF($AJ62<30,0,IF($AJ62<40,50,IF($AJ62<=90,100,50))),"") | AV62: =IF(ISNUMBER($AK62),IF($AK62>-0.2,100,IF($AK62>=-0.4,50,0)),"") | AW62: =01_指標庫!$H$4*ISNUMBER($F62)+01_指標庫!$H$5*ISNUMBER($AA62)+01_指標庫!$H$6*ISNUMBER($G62)+01_指標庫!$H$7*ISNUMBER($H62)+01_指標庫!$H$8*ISNUMBER($AF62)+01_指標庫!$H$9*ISNUMBER($AG62)+01_指標庫!$H$10*ISNUMBER($AB62)+01_指標庫!$H$11*ISNUMBER($AC62)+01_指標庫!$H$12*ISNUMBER($AD62)+01_指標庫!$H$13*ISNUMBER($AE62)+01_指標庫!$H$14*ISNUMBER($I62)+01_指標庫!$H$15*ISNUMBER($AH62)+01_指標庫!$H$16*ISNUMBER($K62)+01_指標庫!$H$17*ISNUMBER($AI62)+01_指標庫!$H$18*ISNUMBER($AJ62)+01_指標庫!$H$19*ISNUMBER($AK62)+01_指標庫!$H$20*ISNUMBER($BB62)+01_指標庫!$H$21*ISNUMBER($BC62) -> 49 | AX62: =IF(AW62=0,50,ROUND((01_指標庫!$H$4*IF(ISNUMBER($F62),L62,0)+01_指標庫!$H$5*IF(ISNUMBER($AA62),AL62,0)+01_指標庫!$H$6*IF(ISNUMBER($G62),M62,0)+01_指標庫!$H$7*IF(ISNUMBER($H62),N62,0)+01_指標庫!$H$8*IF(ISNUMBER($AF62),AQ62,0)+01_指標庫!$H$9*IF(ISNUMBER($AG62),AR62,0)+01_指標庫!$H$10*IF(ISNUMBER($AB62),AM62,0)+01_指標庫!$H$11*IF(ISNUMBER($AC62),AN62,0)+01_指標庫!$H$12*IF(ISNUMBER($AD62),AO62,0)+01_指標庫!$H$13*IF(ISNUMBER($AE62),AP62,0)+01_指標庫!$H$14*IF(ISNUMBER($I62),O62,0)+01_指標庫!$H$15*IF(ISNUMBER($AH62),AS62,0)+01_指標庫!$H$16*IF(ISNUMBER($K62),P62,0)+01_指標庫!$H$17*IF(ISNUMBER($AI62),AT62,0)+01_指標庫!$H$18*IF(ISNUMBER($AJ62),AU62,0)+01_指標庫!$H$19*IF(ISNUMBER($AK62),AV62,0)+01_指標庫!$H$20*IF(ISNUMBER($BB62),BB62,0)+01_指標庫!$H$21*IF(ISNUMBER($BC62),BC62,0))/AW62,1)) -> 72.4 | BA62: =AVERAGE($E58:$E62)/AVERAGE($E53:$E62)-1 -> 0.0044714716 | BB62: =IF(ISNUMBER($BA62),IF(OR($S62<=-0.03,$BA62<-0.003),0,IF(OR($S62<=-0.02,$BA62<0.01),50,100)),"") -> 50 | BC62: =IF(OR(COUNT($AZ62)=0,COUNT($AZ61)=0),"",IF(OR($AY62/$AZ61-1<=-0.03,$AZ62/$AZ61-1<=-0.045,IF(COUNT($AZ53:$AZ62)=10,AVERAGE($AZ58:$AZ62)/AVERAGE($AZ53:$AZ62)-1<-0.01,FALSE())),0,IF(OR($AZ62/$AZ61-1<=-0.02,IF(COUNT($AZ53:$AZ62)=10,AVERAGE($AZ58:$AZ62)/AVERAGE($AZ53:$AZ62)-1<0.005,FALSE())),50,100)))
A63: 59 | B63: 42642 | C63: 2016 | D63: 四 | E63: 4838.3 | F63: 0.078823 | G63: -0.010848 | H63: 0.8163 | I63: 509 | J63: real | K63: 14.02 | L63: =IF(COUNT(F63)=0,50,IF(F63>=0,100,IF(F63>=-0.02,50,0))) -> 100 | M63: =IF(COUNT(G63)=0,50,IF(G63>-0.06,100,IF(G63>-0.15,50,0))) -> 100 | N63: =IF(COUNT(H63)=0,50,IF(H63>=0.6,100,IF(H63>=0.4,50,0))) -> 100 | O63: =IF(COUNT(I63)=0,50,IF(J63="proxy_vix",50,IF(I63<350,100,IF(I63<=450,50,0)))) -> 0 | P63: =IF(COUNT(K63)=0,50,IF(K63<20,100,IF(K63<=25,50,0))) -> 100 | S63: =$E63/$E62-1 -> -0.0075831698 | T63: =$K63/$K62-1 -> 0.13155771 | Y63: =IF(AX63>=70,"EASY",IF(AX63>40,"UNCERTAIN","HARD")) -> EASY | AA63: =IF($A63<200,"",AVERAGE($E14:$E63)/AVERAGE($E5:$E63)-1) | AB63: =LOOKUP($B63,07_L1政策步階!$A$4:$A$14,07_L1政策步階!$C$4:$C$14) -> 0 | AL63: =IF(ISNUMBER($AA63),IF($AA63>=0.005,100,IF($AA63>=-0.015,50,0)),"") | AM63: =IF(ISNUMBER($AB63),IF($AB63=1,100,IF($AB63=0,50,0)),"") -> 50 | AN63: =IF(ISNUMBER($AC63),IF($AC63>=0.001,100,IF($AC63>=-0.003,50,0)),"") | AO63: =IF(ISNUMBER($AD63),IF($AD63>=0.04,100,IF($AD63>=0,50,0)),"") | AP63: =IF(ISNUMBER($AE63),IF($AE63>=25,100,IF($AE63>=-75,50,0)),"") | AQ63: =IF(ISNUMBER($AF63),IF($AF63>0,100,IF($AF63>=-50,50,0)),"") | AR63: =IF(ISNUMBER($AG63),IF($AG63=1,100,IF($AG63=0,50,0)),"") | AS63: =IF(ISNUMBER($AH63),IF($AH63<0,100,IF($AH63<=20,50,0)),"") | AT63: =IF(ISNUMBER($AI63),IF($AI63<0.95,100,IF($AI63<=1,50,0)),"") | AU63: =IF(ISNUMBER($AJ63),IF($AJ63<30,0,IF($AJ63<40,50,IF($AJ63<=90,100,50))),"") | AV63: =IF(ISNUMBER($AK63),IF($AK63>-0.2,100,IF($AK63>=-0.4,50,0)),"") | AW63: =01_指標庫!$H$4*ISNUMBER($F63)+01_指標庫!$H$5*ISNUMBER($AA63)+01_指標庫!$H$6*ISNUMBER($G63)+01_指標庫!$H$7*ISNUMBER($H63)+01_指標庫!$H$8*ISNUMBER($AF63)+01_指標庫!$H$9*ISNUMBER($AG63)+01_指標庫!$H$10*ISNUMBER($AB63)+01_指標庫!$H$11*ISNUMBER($AC63)+01_指標庫!$H$12*ISNUMBER($AD63)+01_指標庫!$H$13*ISNUMBER($AE63)+01_指標庫!$H$14*ISNUMBER($I63)+01_指標庫!$H$15*ISNUMBER($AH63)+01_指標庫!$H$16*ISNUMBER($K63)+01_指標庫!$H$17*ISNUMBER($AI63)+01_指標庫!$H$18*ISNUMBER($AJ63)+01_指標庫!$H$19*ISNUMBER($AK63)+01_指標庫!$H$20*ISNUMBER($BB63)+01_指標庫!$H$21*ISNUMBER($BC63) -> 49 | AX63: =IF(AW63=0,50,ROUND((01_指標庫!$H$4*IF(ISNUMBER($F63),L63,0)+01_指標庫!$H$5*IF(ISNUMBER($AA63),AL63,0)+01_指標庫!$H$6*IF(ISNUMBER($G63),M63,0)+01_指標庫!$H$7*IF(ISNUMBER($H63),N63,0)+01_指標庫!$H$8*IF(ISNUMBER($AF63),AQ63,0)+01_指標庫!$H$9*IF(ISNUMBER($AG63),AR63,0)+01_指標庫!$H$10*IF(ISNUMBER($AB63),AM63,0)+01_指標庫!$H$11*IF(ISNUMBER($AC63),AN63,0)+01_指標庫!$H$12*IF(ISNUMBER($AD63),AO63,0)+01_指標庫!$H$13*IF(ISNUMBER($AE63),AP63,0)+01_指標庫!$H$14*IF(ISNUMBER($I63),O63,0)+01_指標庫!$H$15*IF(ISNUMBER($AH63),AS63,0)+01_指標庫!$H$16*IF(ISNUMBER($K63),P63,0)+01_指標庫!$H$17*IF(ISNUMBER($AI63),AT63,0)+01_指標庫!$H$18*IF(ISNUMBER($AJ63),AU63,0)+01_指標庫!$H$19*IF(ISNUMBER($AK63),AV63,0)+01_指標庫!$H$20*IF(ISNUMBER($BB63),BB63,0)+01_指標庫!$H$21*IF(ISNUMBER($BC63),BC63,0))/AW63,1)) -> 72.4 | BA63: =AVERAGE($E59:$E63)/AVERAGE($E54:$E63)-1 -> 0.0018981508 | BB63: =IF(ISNUMBER($BA63),IF(OR($S63<=-0.03,$BA63<-0.003),0,IF(OR($S63<=-0.02,$BA63<0.01),50,100)),"") -> 50 | BC63: =IF(OR(COUNT($AZ63)=0,COUNT($AZ62)=0),"",IF(OR($AY63/$AZ62-1<=-0.03,$AZ63/$AZ62-1<=-0.045,IF(COUNT($AZ54:$AZ63)=10,AVERAGE($AZ59:$AZ63)/AVERAGE($AZ54:$AZ63)-1<-0.01,FALSE())),0,IF(OR($AZ63/$AZ62-1<=-0.02,IF(COUNT($AZ54:$AZ63)=10,AVERAGE($AZ59:$AZ63)/AVERAGE($AZ54:$AZ63)-1<0.005,FALSE())),50,100)))
